Workbook

Sheet Start here
A1: Eli - the next fifteen years
A4: This is yours. Nobody else's pay is in this file, and your numbers are not in anybody else's.
A6: You are 17, you turn 18 on 18 November 2026, you are homeschooled so you can work full time, and you already own a truck that can haul material and pull a trailer. That is a genuinely strong starting hand for someone your age, and it is worth saying plainly. This file is not a sales pitch. It shows what each step actually pays, what it costs to get there, and roughly when to take it.
A8: FIRST - the one thing that is time-sensitive:
A10: Until 18 November you are legally limited in what you can do on a jobsite, and it is not Charlie being careful. Federal law (29 CFR 570.68) bars anyone under 18 from excavating, working in, or backfilling trenches, with one narrow exception for HAND digging a trench under four feet. So running the mini-ex or the skid steer to cut or backfill a drain line is out, riding in either machine is out, and driving your truck for work or towing ANY trailer is out - towing under 18 is flatly prohibited with no exception. What you can do: hand-dig and hand-backfill under four feet, carry and lay pipe, shovel and wheelbarrow gravel, lay and repair sod, hand tools, setup and cleanup. That is still a full-time job at $20 an hour.
A12: On your birthday every one of those restrictions disappears at once. No waiting period, no paperwork. Machines, truck, trailer - all of it. That makes 18 November the single most valuable date in this file, and the tab called 'The next 90 days' is about being completely ready for it instead of starting to think about it that week.
A14: One piece of paperwork to sort now: Louisiana requires an employment certificate for every worker under 18, and the employer has to keep it on file. Because you are homeschooled there is no principal to sign it, so it comes from the East Baton Rouge Parish school superintendent's office. Get it done - it protects Charlie, and it costs an afternoon.
A16: Four things worth knowing before you read the rest:
A18: 1. The biggest single raise of your whole career is the next one. Laborer to equipment operator in Baton Rouge is $18.58 to $27.99 an hour at the medians - a 51% jump, about $9.41 an hour, near $19,600 a year - and it costs no money at all, only seat time and asking. Nothing else on the ladder has that ratio. Take it early. That is the single most useful sentence in this file.
A20: 2. Your truck is an asset, and assets get paid differently from labour. Right now it is being treated as a favour. It should not be. There is a whole tab on this - the short version is that the company can reimburse you at the IRS rate per business mile, that money is TAX-FREE to you if it is documented properly, and at 8,000 business miles a year it is close to $6,000 you keep entirely. Learning the difference between getting paid for your time and getting paid for what you own is the beginning of working IN a business rather than FOR one.
A22: 3. Contractors do not go broke because they cannot dig. They go broke because they bid the job wrong and find out too late. That is why there is a 'what you are learning' column on the ladder, and why job costing shows up at 21 rather than at 30.
A24: 4. On AI and robots: read that tab properly. The machines are coming for big flat repetitive ground first. Figuring out why a yard floods, and getting a trench between a fence, a pool and a tree root without hitting a gas line, is close to the last thing that gets automated. The office side - quoting, invoicing, scheduling - is being automated right now. So aim at the job that owns the customer and the licence, not the one that owns the shovel.
A26: None of this is a promise. It is arithmetic on today's numbers, and you can change every one of them.

Sheet The next 90 days
A1: The next 90 days - be ready on 18 November, not thinking about it
A2: The restrictions end on your birthday. Whether that date is worth anything depends entirely on what you did in the nine weeks before it.
A4: When | B4: What you do | C4: Why it matters
A5: This week | B5: Get the Louisiana employment certificate from the EBR Parish superintendent's office and give Charlie a copy. | C5: It is legally required while you are 17 and it is the only thing that protects Charlie if anybody ever asks. Doing it without being chased is the first thing on this list for a reason - it is the kind of thing that gets you trusted.
A6: This week | B6: Start the job notebook. Every day: what job, what you did, how long it took, what materials went in, what went wrong. | C6: In three years this notebook is what lets you estimate. Nobody can teach you what a job should cost - you can only have written down what it did cost, over and over.
A7: This week | B7: Call your insurance company about the truck before you ever tow for work. | C7: See the truck tab. This is the one that can actually hurt you.
A8: Weeks 1-4 | B8: Ask Charlie or Bryan to walk you through a Moasure survey and a quote on a real job. Just watch and write it down. | C8: The quote is where the money is decided. Everything you do with a shovel afterwards is executing a decision somebody already made.
A9: Weeks 1-4 | B9: Do the OSHA 10 card online. About $60-90 and a few evenings. | C9: Cheap, permanent, and it makes you the obvious person to trust around a trench. At 18 it makes you structurally useful rather than just young and willing.
A10: Weeks 2-6 | B10: Learn the machines with the engine OFF. Sit in the seat on the yard, learn every control, every service point, the grease points, the daily checks. | C10: You cannot legally operate yet, but nothing stops you from knowing the machine cold. On 18 November you want to be the guy who already knows where everything is, not the guy starting from zero.
A11: Weeks 4-8 | B11: Get the trenching competent-person training. $49-200. | C11: OSHA requires a designated competent person on trenching work. Being one of the few people on the crew who holds it is the fastest way to stop being the youngest guy and start being necessary.
A12: Weeks 6-9 | B12: Sort the truck out: know the tow rating, get the trailer wiring and brakes checked, sort the insurance answer, price a business-use endorsement. | C12: So that on the 18th the truck can start earning instead of waiting on a wiring harness.
A13: Weeks 6-9 | B13: Have the conversation with Charlie about how the truck gets paid for - mileage at the IRS rate, in writing. | C13: Ask before you start, not after six months of doing it for free. Asking early is normal and businesslike; asking late feels like a complaint. That distinction matters more than the money.
A14: 18 November | B14: Birthday. Every machine and the truck unlock the same day. | C14: Ask for the seat that week. Not in January.
A15: Weeks 1-4 after | B15: Get in the machine every single chance you get, including unpaid time on the yard if that is what it takes. | C15: The operator premium is $9.41 an hour over a labourer - about $19,600 a year - and it costs nothing but seat time. This is the highest-return thing you will ever do with your hours.
A16: First 90 days after | B16: Start tracking one number for Charlie without being asked: linear feet per crew day. | C16: Bringing a number to the owner that he did not ask for is how an 18-year-old becomes someone the business is built around. It is also the single cheapest way to show you think like an owner.

Sheet The ladder
A1: The ladder - what each step pays and what it takes
A2: Blue = change it. Hourly rates are Baton Rouge averages for each role, grown 3.5% a year for wage inflation - which is what construction wages have actually done. Take-home is after federal tax, Social Security and Medicare, and Louisiana's 3% flat rate.
A4: Wage inflation per year | B4: 0.035 | D4: Construction wages have run about 3.5%/yr nationally; Louisiana has run slower, near 2.45%.
A5: Paid hours per year | B5: 2080 | D5: 40 hours x 52 weeks. Overtime is on top - and the federal deduction for overtime premium pay is worth tracking.
A7: Year | B7: Age | C7: What you are | D7: Rate/hr today | E7: Rate/hr then | F7: Gross a year | G7: Take-home | H7: What you get that year | I7: What you are learning
A8: 1 | B8: 18 | C8: Laborer -> machines unlock 18 Nov | D8: 20 | E8: =D8*(1+$B$4)^0 -> 20 | F8: =E8*$B$5 -> 41600 | G8: =F8-MAX(0,MIN(F8-16100,12400))*0.1-MAX(0,MIN(F8-16100-12400,38000))*0.12-MAX(0,F8-16100-50400)*0.22-F8*0.0765-MAX(0,F8-12500)*0.03 -> 34732.6 | H8: Turning 18 unlocks every machine and the truck. OSHA 10. Trenching competent-person card. Louisiana employment certificate on file until then. FAA Part 107 drone licence. | I8: How the work actually goes together. Start a job notebook on day one: hours, machine time, materials, what went wrong. The notebook is the habit everything else on this page is built on.
A9: 2 | B9: 19 | C9: Laborer / operator trainee | D9: 23 | E9: =D9*(1+$B$4)^1 -> 23.805 | F9: =E9*$B$5 -> 49514.4 | G9: =F9-MAX(0,MIN(F9-16100,12400))*0.1-MAX(0,MIN(F9-16100-12400,38000))*0.12-MAX(0,F9-16100-50400)*0.22-F9*0.0765-MAX(0,F9-12500)*0.03 -> 40854.388 | H9: CDL Class A at BRCC - 6 weeks, $5,640. | I9: Get in the seat every chance you get. Hauling your own iron is the skill nobody can take off you.
A10: 3 | B10: 20 | C10: Equipment operator | D10: 26 | E10: =D10*(1+$B$4)^2 -> 27.85185 | F10: =E10*$B$5 -> 57931.848 | G10: =F10-MAX(0,MIN(F10-16100,12400))*0.1-MAX(0,MIN(F10-16100-12400,38000))*0.12-MAX(0,F10-16100-50400)*0.22-F10*0.0765-MAX(0,F10-12500)*0.03 -> 47365.284 | H10: OSHA 30. Open the LLC and the business bank account. | I10: Reading grade and fall. Why water goes where it goes. Open the company now - lenders want two years of history before they will lend.
A11: 4 | B11: 21 | C11: Equipment operator | D11: 28.3 | E11: =D11*(1+$B$4)^3 -> 31.376716 | F11: =E11*$B$5 -> 65263.569 | G11: =F11-MAX(0,MIN(F11-16100,12400))*0.1-MAX(0,MIN(F11-16100-12400,38000))*0.12-MAX(0,F11-16100-50400)*0.22-F11*0.0765-MAX(0,F11-12500)*0.03 -> 53036.371 | H11: M.J. Foster Promise money becomes available at 21. | I11: Job costing. Every job you work, write down what it should have cost and what it did. This is the single skill that separates owners from employees.
A12: 5 | B12: 22 | C12: Senior operator | D12: 30 | E12: =D12*(1+$B$4)^4 -> 34.42569 | F12: =E12*$B$5 -> 71605.435 | G12: =F12-MAX(0,MIN(F12-16100,12400))*0.1-MAX(0,MIN(F12-16100-12400,38000))*0.12-MAX(0,F12-16100-50400)*0.22-F12*0.0765-MAX(0,F12-12500)*0.03 -> 57431.261 | H12: Build a clean credit file. Secured card, paid in full, every month. | I12: Estimating. Start pricing jobs in your notebook before the quote goes out, then check yourself against the real number.
A13: 6 | B13: 23 | C13: Senior operator / lead hand | D13: 32 | E13: =D13*(1+$B$4)^5 -> 38.005962 | F13: =E13*$B$5 -> 79052.401 | G13: =F13-MAX(0,MIN(F13-16100,12400))*0.1-MAX(0,MIN(F13-16100-12400,38000))*0.12-MAX(0,F13-16100-50400)*0.22-F13*0.0765-MAX(0,F13-12500)*0.03 -> 62446.792 | H13: LDAF licences if the work calls for them. | I13: Running two or three men. Scheduling a day so nobody stands around.
A14: 7 | B14: 24 | C14: Lead hand | D14: 34 | E14: =D14*(1+$B$4)^6 -> 41.794681 | F14: =E14*$B$5 -> 86932.937 | G14: =F14-MAX(0,MIN(F14-16100,12400))*0.1-MAX(0,MIN(F14-16100-12400,38000))*0.12-MAX(0,F14-16100-50400)*0.22-F14*0.0765-MAX(0,F14-12500)*0.03 -> 67754.333 | I14: Contracts, scope and change orders. Unpaid change orders are how contractors go broke while staying busy.
A15: 8 | B15: 25 | C15: Assistant foreman | D15: 36 | E15: =D15*(1+$B$4)^7 -> 45.802053 | F15: =E15*$B$5 -> 95268.271 | G15: =F15-MAX(0,MIN(F15-16100,12400))*0.1-MAX(0,MIN(F15-16100-12400,38000))*0.12-MAX(0,F15-16100-50400)*0.22-F15*0.0765-MAX(0,F15-12500)*0.03 -> 73368.181 | H15: LSLBC Class 13 licence - minimum age 18, no experience requirement, $10,000 net worth or a bond in lieu. | I15: Talking to customers. Quoting inside 48 hours. In residential work, answering the phone is a competitive advantage and it is free.
A16: 9 | B16: 26 | C16: Foreman | D16: 38.51 | E16: =D16*(1+$B$4)^8 -> 50.710316 | F16: =E16*$B$5 -> 105477.46 | G16: =F16-MAX(0,MIN(F16-16100,12400))*0.1-MAX(0,MIN(F16-16100-12400,38000))*0.12-MAX(0,F16-16100-50400)*0.22-F16*0.0765-MAX(0,F16-12500)*0.03 -> 80244.067 | H16: First machine, if the numbers work. Used mini-ex, 2-3.5 tonne. | I16: Equipment economics. What a machine costs per hour to own and run, and when to repair instead of replace.
A17: 10 | B17: 27 | C17: Foreman | D17: 40 | E17: =D17*(1+$B$4)^9 -> 54.515894 | F17: =E17*$B$5 -> 113393.06 | G17: =F17-MAX(0,MIN(F17-16100,12400))*0.1-MAX(0,MIN(F17-16100-12400,38000))*0.12-MAX(0,F17-16100-50400)*0.22-F17*0.0765-MAX(0,F17-12500)*0.03 -> 85575.226 | I17: Bookkeeping and cash. Separate accounts, quarterly estimates, and never spending the tax money.
A18: 11 | B18: 28 | C18: Superintendent | D18: 44 | E18: =D18*(1+$B$4)^10 -> 62.066345 | F18: =E18*$B$5 -> 129098 | G18: =F18-MAX(0,MIN(F18-16100,12400))*0.1-MAX(0,MIN(F18-16100-12400,38000))*0.12-MAX(0,F18-16100-50400)*0.22-F18*0.0765-MAX(0,F18-12500)*0.03 -> 96152.502 | H18: Second machine or a partner's stake. | I18: Bidding whole jobs. Knowing which ones to walk away from - that judgement is worth more than any machine.
A19: 12 | B19: 29 | C19: Superintendent | D19: 47 | E19: =D19*(1+$B$4)^11 -> 68.618577 | F19: =E19*$B$5 -> 142726.64 | G19: =F19-MAX(0,MIN(F19-16100,12400))*0.1-MAX(0,MIN(F19-16100-12400,38000))*0.12-MAX(0,F19-16100-50400)*0.22-F19*0.0765-MAX(0,F19-12500)*0.03 -> 105331.39 | I19: Managing people who are older than you. This is the part that surprises everybody.
A20: 13 | B20: 30 | C20: Operations lead / partner | D20: 50 | E20: =D20*(1+$B$4)^12 -> 75.553433 | F20: =E20*$B$5 -> 157151.14 | G20: =F20-MAX(0,MIN(F20-16100,12400))*0.1-MAX(0,MIN(F20-16100-12400,38000))*0.12-MAX(0,F20-16100-50400)*0.22-F20*0.0765-MAX(0,F20-12500)*0.03 -> 115046.29 | H20: Either a real stake here, or your own company. | I20: Running a P&L. Owning the outcome, not the task.
A21: 14 | B21: 31 | C21: Partner or owner | D21: 54 | E21: =D21*(1+$B$4)^13 -> 84.453627 | F21: =E21*$B$5 -> 175663.54 | G21: =F21-MAX(0,MIN(F21-16100,12400))*0.1-MAX(0,MIN(F21-16100-12400,38000))*0.12-MAX(0,F21-16100-50400)*0.22-F21*0.0765-MAX(0,F21-12500)*0.03 -> 127514.4 | I21: Hiring. Building something that works when you are not standing there.
A22: 15 | B22: 32 | C22: Owner | D22: 58 | E22: =D22*(1+$B$4)^14 -> 93.884282 | F22: =E22*$B$5 -> 195279.31 | G22: =F22-MAX(0,MIN(F22-16100,12400))*0.1-MAX(0,MIN(F22-16100-12400,38000))*0.12-MAX(0,F22-16100-50400)*0.22-F22*0.0765-MAX(0,F22-12500)*0.03 -> 140725.61 | H22: Consider adding LSLBC Class 62 - docks, piers, bulkheads. The water work. | I22: Being the person other people work for. A different job entirely from the one you started.
A24: The rates are Baton Rouge averages, not promises. BLS May 2025: construction laborer $20.48/hr, equipment operator $28.30/hr, first-line construction supervisor $38.51/hr. Baton Rouge has roughly double the national concentration of construction work, which is genuinely in your favour.
A25: Equipment operator jobs are only growing 4% over the next decade - but there are about 42,500 openings a year because the people doing it now are retiring. The opportunity is replacement, not growth. That is still an opportunity.
A26: Certifications that are worth the money: the trenching competent-person card ($49-200, a few hours) makes you structurally necessary on a drainage crew at 19. The CDL ($5,640, six weeks) means the company does not pay a hauler $400-800 every time a machine moves. Most equipment 'certifications' are not worth paying for in Louisiana private work - seat time is what counts.

Sheet Your truck
A1: Your truck - what it is worth, and how to get paid for it properly
A2: Blue = change it. Right now your truck is a favour you do the company. It should be a line item. This tab shows what it is genuinely worth, how to be paid so the money is tax-free, and the one mistake that could cost you the truck.
A4: WHAT THE COMPANY SHOULD PAY YOU PER MILE
A5: Business miles you drive for the company in a year | B5: 8000 | C5: Only miles driven FOR work count - never your commute from home to the yard. Keep a log from the first day; an app is fine and a notebook is fine, but reconstructing it at the end of the year is not.
A6: IRS reimbursement rate ($/mile) | B6: 0.743 | C6: The 2026 IRS business rate changed mid-year: 72.5 cents January to June, 76 cents July to December. 0.743 is the blend. This is the rate the government itself says covers fuel, tyres, repairs, insurance and wear.
A7: What you should be reimbursed | B7: =B5*B6 -> 5944 | C7: And here is the part worth understanding: under an accountable plan this is NOT taxable income. It does not go on your W-2, no income tax, no Social Security or Medicare taken out. You keep all of it. The company still deducts every dollar. Both sides win, and it is completely legal - it just has to be documented.
A8: What a mile actually costs you (fuel, tyres, maintenance) | B8: 0.35 | C8: AAA puts the all-in cost of a half-ton pickup at about $1.10 a mile - but most of that is depreciation and finance on a NEW truck. On an older paid-off truck your real out-of-pocket per mile is closer to 35 cents at 2026 fuel prices.
A9: Your actual running cost | B9: =B5*B8 -> 2800
A10: WHAT YOU ACTUALLY CLEAR ON THE TRUCK | B10: =B7-B9 -> 3144 | C10: Tax-free, on top of your wages, for driving a truck you already own. Be honest with yourself though: you are also using the truck up. Some of this should go straight into a repair fund, which is on the Money tab.
A11: WHAT HAULING IS WORTH ON TOP OF THE MILES
A12: Equipment moves you do in a year (machine on a trailer) | B12: 60 | C12: Every time you move a machine instead of the company paying somebody else to.
A13: What an outside hauler would charge per move | B13: 400 | C13: Third-party equipment transport runs roughly $300-600 for a short cross-metro move, because short hauls are priced off a minimum rather than by the mile. A 24-foot equipment trailer alone rents for about $165 a day.
A14: What your hauling saves the company in a year | B14: =B12*B13 -> 24000 | C14: This is NOT automatically your money - it is your negotiating position. It is the number to have in your head when you ask to be paid for the truck as well as for your time.
A15: THE MISTAKE THAT COULD COST YOU THE TRUCK - READ THIS TWICE
A16: Your personal auto insurance almost certainly does NOT cover using the truck for business. Nearly every personal policy has a business-use exclusion. Towing a trailer with a machine on it, or hauling gravel for a paying job, is squarely business use.
A17: If you wreck while hauling and the insurer finds out it was a work trip, the realistic outcome is that they deny the claim and then decline to renew you. You would be paying for a wrecked truck yourself, at 18, and then shopping for insurance as a young driver with a cancellation on your record.
A18: What to do instead, before you tow anything for work: (1) call your own insurer, tell them plainly what the truck will be used for, and ask in writing what is and is not covered; (2) ask Charlie to confirm the company carries hired and non-owned auto coverage, which protects the COMPANY when you drive your own truck on its business - note it does NOT repair your truck; (3) if your carrier will not cover business use, find out what a commercial policy or a business-use endorsement costs before you start, not after.
A19: This is the single most important page in this whole file. Everything else here is about making money. This one is about not losing what you already own.
A20: Also worth knowing: under Louisiana law the company can be liable for what happens while you are driving on its business - one 2024 case held that simply having a mileage reimbursement policy extended an employer's liability into an employee's commute. That is a reason for Charlie to want this properly insured too, not just you.
A21: BEFORE YOU HITCH ANYTHING - THE WEIGHT QUESTION
A22: You need a Class A CDL only if BOTH the combined rating is 26,001 lb or more AND the trailer is rated over 10,000 lb. A half-ton pulling a small trailer is nowhere near that. But a 3.5-tonne class mini excavator weighs about 7,900 lb and a trailer rated to carry it weighs about 4,300 lb empty - roughly 12,200 lb combined. That is beyond what a half-ton should be towing, even though it does not require a CDL.
A23: Know your truck's tow rating and your trailer's GVWR before you load a machine, not after. Louisiana requires trailer brakes over 3,000 lb gross, operable from the cab, and safety chains. If a haul ever crosses into Mississippi or Texas it becomes interstate commerce and needs a USDOT number and driver files - keep the work in-state unless somebody has sorted that out.

Sheet Money
A1: What to do with it
A2: Blue = change it. The order matters: emergency fund first, then anything your employer matches, then the Roth, then the business fund. Saving is a percentage taken off the top the day the cheque lands - not whatever is left at the end of the month, because in a good month there is a lot left and in a bad month there is none.
A4: Emergency fund target ($) | B4: 7000 | D4: Not the generic 'three to six months'. Drainage work is weather-driven: size this to your own worst stretch. Ten wet weeks with no work is roughly $7,000 at today's pay.
A5: Share of take-home saved once the emergency fund is full | B5: 0.22 | D5: Aggressive but doable at 20 with no mortgage. Drop it in a year you need to; never drop it quietly.
A6: Roth IRA limit ($/yr) | B6: 7500 | D6: The 2026 limit. It rises most years - check it each January.
A7: Return assumption on long-term savings | B7: 0.07 | D7: A long-run stock-market average. Real markets do not deliver a constant 7% - some years are negative. This is arithmetic, not a forecast.
A9: Year | B9: 1 | C9: 2 | D9: 3 | E9: 4 | F9: 5 | G9: 6 | H9: 7 | I9: 8 | J9: 9 | K9: 10 | L9: 11 | M9: 12 | N9: 13 | O9: 14 | P9: 15 | R9: Notes
A10: Age | B10: 18 | C10: 19 | D10: 20 | E10: 21 | F10: 22 | G10: 23 | H10: 24 | I10: 25 | J10: 26 | K10: 27 | L10: 28 | M10: 29 | N10: 30 | O10: 31 | P10: 32
A11: Take-home that year | B11: ='The ladder'!G8 -> 34732.6 | C11: ='The ladder'!G9 -> 40854.388 | D11: ='The ladder'!G10 -> 47365.284 | E11: ='The ladder'!G11 -> 53036.371 | F11: ='The ladder'!G12 -> 57431.261 | G11: ='The ladder'!G13 -> 62446.792 | H11: ='The ladder'!G14 -> 67754.333 | I11: ='The ladder'!G15 -> 73368.181 | J11: ='The ladder'!G16 -> 80244.067 | K11: ='The ladder'!G17 -> 85575.226 | L11: ='The ladder'!G18 -> 96152.502 | M11: ='The ladder'!G19 -> 105331.39 | N11: ='The ladder'!G20 -> 115046.29 | O11: ='The ladder'!G21 -> 127514.4 | P11: ='The ladder'!G22 -> 140725.61
A12: Saved that year (all buckets) | B12: =B11*$B$5 -> 7641.172 | C12: =C11*$B$5 -> 8987.9654 | D12: =D11*$B$5 -> 10420.363 | E12: =E11*$B$5 -> 11668.002 | F12: =F11*$B$5 -> 12634.877 | G12: =G11*$B$5 -> 13738.294 | H12: =H11*$B$5 -> 14905.953 | I12: =I11*$B$5 -> 16141 | ... P12: =P11*$B$5 -> 30959.635
A13: → into the emergency fund | B13: =MIN(B12,MAX(0,$B$4-0)) -> 7000 | C13: =MIN(C12,MAX(0,$B$4-B14)) -> 0 | D13: =MIN(D12,MAX(0,$B$4-C14)) -> 0 | E13: =MIN(E12,MAX(0,$B$4-D14)) -> 0 | F13: =MIN(F12,MAX(0,$B$4-E14)) -> 0 | G13: =MIN(G12,MAX(0,$B$4-F14)) -> 0 | H13: =MIN(H12,MAX(0,$B$4-G14)) -> 0 | I13: =MIN(I12,MAX(0,$B$4-H14)) -> 0 | J13: =MIN(J12,MAX(0,$B$4-I14)) -> 0 | ... P13: =MIN(P12,MAX(0,$B$4-O14)) -> 0
A14: Emergency fund balance | B14: =0+B13 -> 7000 | C14: =B14+C13 -> 7000 | D14: =C14+D13 -> 7000 | E14: =D14+E13 -> 7000 | F14: =E14+F13 -> 7000 | G14: =F14+G13 -> 7000 | H14: =G14+H13 -> 7000 | I14: =H14+I13 -> 7000 | J14: =I14+J13 -> 7000 | ... P14: =O14+P13 -> 7000
A15: → into the Roth IRA | B15: =MIN($B$6,MAX(0,B12-B13)) -> 641.172 | C15: =MIN($B$6,MAX(0,C12-C13)) -> 7500 | D15: =MIN($B$6,MAX(0,D12-D13)) -> 7500 | E15: =MIN($B$6,MAX(0,E12-E13)) -> 7500 | F15: =MIN($B$6,MAX(0,F12-F13)) -> 7500 | G15: =MIN($B$6,MAX(0,G12-G13)) -> 7500 | H15: =MIN($B$6,MAX(0,H12-H13)) -> 7500 | I15: =MIN($B$6,MAX(0,I12-I13)) -> 7500 | ... P15: =MIN($B$6,MAX(0,P12-P13)) -> 7500
A16: Roth balance (contributions + growth) | B16: =(0)*(1+$B$7)+B15 -> 641.172 | C16: =(B16)*(1+$B$7)+C15 -> 8186.054 | D16: =(C16)*(1+$B$7)+D15 -> 16259.078 | E16: =(D16)*(1+$B$7)+E15 -> 24897.213 | F16: =(E16)*(1+$B$7)+F15 -> 34140.018 | G16: =(F16)*(1+$B$7)+G15 -> 44029.819 | H16: =(G16)*(1+$B$7)+H15 -> 54611.907 | I16: =(H16)*(1+$B$7)+I15 -> 65934.74 | J16: =(I16)*(1+$B$7)+J15 -> 78050.172 | ... P16: =(O16)*(1+$B$7)+P15 -> 170781.94
A17: → into the business fund | B17: =MAX(0,B12-B13-B15) -> 0 | C17: =MAX(0,C12-C13-C15) -> 1487.9654 | D17: =MAX(0,D12-D13-D15) -> 2920.3626 | E17: =MAX(0,E12-E13-E15) -> 4168.0015 | F17: =MAX(0,F12-F13-F15) -> 5134.8773 | G17: =MAX(0,G12-G13-G15) -> 6238.2942 | H17: =MAX(0,H12-H13-H15) -> 7405.9532 | I17: =MAX(0,I12-I13-I15) -> 8640.9997 | ... P17: =MAX(0,P12-P13-P15) -> 23459.635
A18: BUSINESS FUND BALANCE | B18: =(0)*(1+$B$7*0.4)+B17 -> 0 | C18: =(B18)*(1+$B$7*0.4)+C17 -> 1487.9654 | D18: =(C18)*(1+$B$7*0.4)+D17 -> 4449.9911 | E18: =(D18)*(1+$B$7*0.4)+E17 -> 8742.5923 | F18: =(E18)*(1+$B$7*0.4)+F17 -> 14122.262 | G18: =(F18)*(1+$B$7*0.4)+G17 -> 20755.98 | H18: =(G18)*(1+$B$7*0.4)+H17 -> 28743.1 | I18: =(H18)*(1+$B$7*0.4)+I17 -> 38188.907 | J18: =(I18)*(1+$B$7*0.4)+J17 -> 49411.891 | ... P18: =(O18)*(1+$B$7*0.4)+P17 -> 167004.54 | R18: Grown at a lower rate than the Roth on purpose - money you might need in three years should not sit in the stock market.
A19: Roth contributions you could take back out | B19: =0+B15 -> 641.172 | C19: =B19+C15 -> 8141.172 | D19: =C19+D15 -> 15641.172 | E19: =D19+E15 -> 23141.172 | F19: =E19+F15 -> 30641.172 | G19: =F19+G15 -> 38141.172 | H19: =G19+H15 -> 45641.172 | I19: =H19+I15 -> 53141.172 | J19: =I19+J15 -> 60641.172 | ... P19: =O19+P15 -> 105641.17 | R19: This is the detail almost nobody tells you. What you PUT IN to a Roth can be taken back out at any age, any time, with no tax and no penalty - only the growth is locked up. So the Roth doubles as your business capital. The catch: once taken out, that contribution room is gone for good.
A20: TOTAL LIQUID - what you could put into a business | B20: =B18+B19 -> 641.172 | C20: =C18+C19 -> 9629.1374 | D20: =D18+D19 -> 20091.163 | E20: =E18+E19 -> 31883.764 | F20: =F18+F19 -> 44763.434 | G20: =G18+G19 -> 58897.152 | H20: =H18+H19 -> 74384.272 | I20: =I18+I19 -> 91330.079 | ... P20: =P18+P19 -> 272645.72 | R20: Emergency fund deliberately excluded - that money is not for buying an excavator.
A22: Why a Roth and not anything else, at your age: you pay tax at 12% federal right now, which is about as low as it ever gets. A Roth means paying that 12% today and never paying tax on that money again - not on the growth, not at 60. At 7%, $7,500 a year from 18 to 30 is $97,500 put in and roughly $1.15 million at 60, all of it tax-free. Stopping at 22 instead still leaves about $564,000. The first five years do more work than the next twenty.
A23: Before the Roth, take any match your employer offers. A 50% match is a 50% return before the money has done anything. Ask whether there is a 401(k) or a SIMPLE IRA, whether the health plan is a high-deductible one with an HSA, and whether there is any disability cover. Only about 59% of workers at small companies have access to a retirement plan at all, so the answer may be no - ask anyway.
A24: The truck is the trap. A $75,000 new diesel pickup at 9% over six years is about $1,350 a month - roughly half your take-home at today's pay - on something that loses a quarter of its value in year one. The same payment invested is about $120,000 after six years. A $25,000 used truck does every single job the new one does. This is the most predictable mistake in the trade and it looks like a business expense while you are making it.
A25: Disability insurance: your body is the whole asset. Long-term disability runs roughly 1-3% of income, more for a high-risk trade - call it $900-$1,600 a year at your pay. Workers comp covers you on the job. It covers nothing on a Saturday. Premiums are cheapest and underwriting easiest while you are young and healthy, and waiting costs you permanently.
A26: None of this is financial advice and nobody here is a licensed advisor. It is arithmetic on published 2026 figures. Check the numbers each January, because the limits change every year.

Sheet Who to learn from
A1: Who to learn what from - and how to be someone people want to help
A2: You are standing next to three people who each know a completely different part of this business, plus a network you have not met yet. Most people your age never get that. Use it deliberately rather than by accident.
A4: Who | B4: What they know that you do not | C4: How to actually get it
A5: Charlie | B5: Selling and estimating. Why a homeowner picks one contractor over another, how to price a job, how to read what somebody actually wants. He has done every job in this company himself. | C5: Ride along on estimates and say nothing. Afterwards ask one question: why did you price it that way. Owners will teach almost anybody who is genuinely curious and not trying to look clever.
A6: Bryan | B6: Running people. Scheduling a day so nobody stands around, keeping crews, safety, job costing. Twenty-five years of it, plus running a bar - which is a harder people business than this one. | C6: Ask him how he decides who does what each morning. Then ask what he would do differently if he were starting over. People who have run something love that question and almost nobody asks it.
A7: Your dad | B7: The business side. Numbers, structure, how deals are put together, how software and systems make a small company punch above its size. | C7: The single most valuable thing here is learning to read a P&L and understand where money actually goes. Ask him to walk you through this workbook line by line - the thing you are holding is the lesson.
A8: The suppliers | B8: Aggregate, pipe and fabric vendors know every contractor in the parish and who pays on time. Terms from a supplier are working capital you do not have to borrow. | C8: Learn their names, be at the counter early, never be the one who argues about an invoice. In five years the supplier who trusts you is worth more than a bank line - and they decide that now, watching how you behave at 18.
A9: Other trades | B9: Plumbers, roofers, gutter installers, landscapers, realtors. They stand in the same yards you do and they see the drainage problems first. | C9: Be useful to them with no expectation. Referrals in this business flow along relationships, not advertising - and the ones that matter get built years before they pay off.
A10: A banker | B10: What a lender wants to see before they will lend to a 25-year-old with a plan. | C10: Open a business account before you need one and introduce yourself to an actual person at the branch. Lenders back people they have watched for a while. Starting that clock at 18 costs nothing.
A12: THE UNGLAMOROUS PART - how to be a good business person
A13: Answer the phone. In residential work, being the one who picks up is a genuine competitive advantage and it is free. Most contractors do not.
A14: Do what you said, when you said. Nearly all of business reputation is this one thing, repeated for years.
A15: Write it down. Change orders, promises, prices, what the customer asked for. Contractors go broke doing unpaid extra work they agreed to verbally.
A16: Never spend the tax money. Set it aside the week it comes in. More small businesses die of this than of bad work.
A17: Be early. It is the cheapest possible way to signal that you are serious, and at your age it is noticed more than anything you say.
A18: Own mistakes fast and completely. The people who go furthest are not the ones who never break a sprinkler line - they are the ones who say so before the customer finds it.
A19: Be someone people want to help. Almost everything good that happens in a trade comes through somebody who decided to put your name forward. That decision is made on how you behave when nothing is at stake.

Sheet Your own company
A1: If you start your own - which one, and what it costs
A2: Only if your future is not here. Ranked on what actually matters: can somebody with a trailer undercut you, what are the margins, and is a machine coming for it. The licence is not the wall - the capital is.
A4: The niche | B4: Startup capital | C4: Licence barrier | D4: Gross margin | E4: Recurring | F4: Robot risk | G4: Sells for | H4: Why it ranks here
A5: 1. Drainage & earthwork | B5: $80-250k | C5: LSLBC Class 13 | D5: 25-40% | E5: Low | F5: Very low | G5: 2.65x SDE | H5: You already know it. Class 13 also covers land clearing and erosion control, so one licence buys three lines of work. Baton Rouge has about double the national concentration of this work, and $29.4M of watershed money is being spent in your own parish. A machine is not coming for a trench between a fence and a pool.
A6: 2. Docks, piers & bulkheads | B6: $150k+ (barge, pile rig) | C6: LSLBC Class 62 + federal permits | D6: 35-50% | E6: Repair tail | F6: Very low | G6: 2.94x SDE | H6: The best margins and the highest resale multiple of anything on this list, and it is the water work you actually want to do. Docks run $20-40/sq ft, bulkheads $150-600 a linear foot. The permits - Army Corps Section 10 and 404 - are a pain, and that is exactly why it is a good business: they keep everybody else out. Add it around year 8-10, not year one.
A7: 3. Land clearing / mulching | B7: $150-250k | C7: None | D7: 40-55% | E7: None | F7: Low | G7: - | H7: Fast money - $1,000-$2,500 a day - but no licence barrier means it commoditises. Best as a bolt-on under your Class 13, not a business of its own.
A8: 4. Hardscape / outdoor living | B8: Medium | C8: Class 50 over threshold | D8: 40-55% | E8: None | F8: Low | G8: - | H8: Good margins, but it is selling to homeowners on design. Different personality.
A9: 5. Erosion control / shoreline | B9: High | C9: Class 5 / 10 | D9: Medium | E9: None | F9: Low | G9: - | H9: Real money, wrong timing. BP settlement money ends in 2031 and southeast Louisiana funding is already down two-thirds.
A10: 6. Irrigation | B10: Low | C10: LDAF Irrigation Contractor | D10: 40-50% | E10: High | F10: Medium | G10: - | H10: Low barrier to entry cuts both ways - easy for you, easy for everyone else.
A11: 7. Tree service | B11: Medium | C11: LDAF Arborist | D11: 40-55% | E11: Low | F11: Low | G11: - | H11: Storm-driven. Feast and famine, and dangerous.
A12: 8. Pool | B12: High | C12: Class 51 over $7,500 | D12: 25-35% | E12: Chem service | F12: Medium | G12: - | H12: Thin margins for the capital involved.
A13: 9. Lawn maintenance | B13: $8-15k | C13: NONE | D13: Net only 10-20% | E13: High | F13: HIGHEST | G13: 2.49x SDE - lowest | H13: The worst option, and it is the one everybody starts with. Zero licence barrier means you compete on price forever against anybody with a trailer. It is also the single category autonomous mowers are actively shipping into. Recurring revenue is its only virtue and buyers pay the lowest multiple of any category for it.
A15: WHAT IT ACTUALLY COSTS TO START
A16: Item | B16: Low | C16: High
A17: Used truck, 3/4 or 1 ton, with a gooseneck hitch | B17: 18000 | C17: 30000
A18: Used dump or equipment trailer | B18: 7000 | C18: 12000
A19: Used mini excavator, 2-3.5 tonne, mid hours | B19: 28000 | C19: 38000
A20: Attachments - thumb, grading bucket, auger | B20: 4000 | C20: 9000
A21: Hand tools, laser level, plate compactor, stock | B21: 4000 | C21: 7000
A22: Licence, exams, entity, first insurance payment | B22: 3000 | C22: 5000
A23: Working capital before the first cheque lands | B23: 10000 | C23: 20000
A24: MINIMUM TO START TAKING JOBS | B24: =SUM(B17:B23) -> 74000 | C24: =SUM(C17:C23) -> 121000 | E24: Rent the skid steer at the start. Own the truck, the trailer and the one machine you use every week.
A26: The on-ramp nobody mentions: in Louisiana you need no contractor licence at all for jobs under $7,500, and a home-improvement registration up to $50,000. So the first jobs - small yard drains, culverts, grading - can be done legally with a rented machine while you build a bank statement and a reputation. That is how this starts, not with $100,000 of iron.
A27: Open the LLC and the business bank account about two years before you want to borrow. Equipment lenders want two years of business history. If you want to finance a machine at 25, the company exists at 23. Nobody tells people this and it costs them a year.
A28: Credit is the cheapest thing you own. A surety bond costs 0.5-3% of face value if your credit is above 675 and 5-10% if it is below 599 - on the same bond. The $10,000 net-worth requirement for a Louisiana licence can be met with a bond instead of cash, which is the door for a young contractor. Good credit makes that door cost $50 a year instead of $1,000.
A29: Insurance is not optional and it is not cheap: a small excavation contractor runs $12,000-$35,000 a year all in - general liability, workers comp, commercial auto, and inland marine on the machines. An uninsured stolen excavator ends the business in one night.

Sheet AI and robots
A1: What actually changes, and when
A3: The honest version, in one paragraph
A4: Machines are coming for repetitive work on big, flat, open, mapped ground first - mowing a hundred acres, moving a million yards of dirt on a highway job. They are nowhere near the work you do. As of right now you cannot buy an autonomous compact excavator for residential drainage; that product does not exist. What is already here is machine control and GPS grade, which makes one operator faster - a tool, not a replacement. Meanwhile the office side is automating fast: over half of home-service owners already use AI for quoting and invoicing. So the safe place to stand is the one that owns the licence, the customer and the judgement - not the one that owns the shovel, and not the one that just does the paperwork.
A6: When you are 25 - we can be fairly confident
A7: Very little changes for a Baton Rouge drainage crew. Drone survey and machine control are standard. Quoting and scheduling are AI-assisted end to end. Autonomous mowers have taken real share of big commercial turf and essentially none of complicated residential work. Every relevant job category is projected to GROW through 2035, and there are tens of thousands of openings a year because the people doing it now are retiring. Your problem at 25 will be finding good people, not being replaced.
A9: When you are 35 - directionally, not precisely
A10: Autonomous earthmoving is plausibly routine on large open civil sites. Companies are already running excavators with empty cabs on big jobs. Residential retrofit work - tight, unmapped, full of tree roots and gas lines and liability - is likely still human-led with robot help. By then you should own machines rather than compete with them. That is the whole hedge: be the person who buys the robot.
A12: When you are 45 - nobody knows, and anyone who says otherwise is guessing
A13: The hard part of robotics is hands - force, touch, and working in places nobody mapped first. That problem is not solved and the people working on it do not have a timeline. It might break open in ten years; it has also been ten years away for forty years. The right response to that is not to pick a side. It is to build a position that survives either outcome.
A15: What survives either outcome
A16: • Owning the company. About 38% of construction managers are self-employed and the median is around $115,000. Automation moves money to whoever owns the machine and the customer.
A17: • Licences. Louisiana licences are a legal barrier to entry. Software cannot hold one - a person has to. They are the cheapest durable protection you can buy and you can start collecting them before you are 20.
... A25: The biggest risk to your next ten years is not a machine taking your job. It is your back. Construction kills about 9.2 workers per 100,000 against 3.3 across all jobs, and trench work is among the most dangerous in it. Moving off the shovel and onto the truck, the estimate and the ownership side by about 30 is the same plan as the robot hedge. They are not two plans. They are one.
