Workbook

Sheet Your numbers
A1: Ned Pearson - Growth & Operations Lead
A2: Blue = change it. This file is yours alone - it contains nobody else's compensation, and nobody else's file contains yours.
A4: Base salary, years 1-2 ($/yr) | B4: 60000 | C4: Fractional, about 25 hours a week.
A5: Base salary, year 3 ($/yr) | B5: 66000
A6: Base salary, years 4-5 ($/yr) | B6: 72000
A7: Base increase per year after year 5 | B7: 0.0275 | C7: Tracks general inflation once the role is established.
A8: Growth share (% of operating profit above the baseline) | B8: 0.1 | C8: Paid on profit above what the business already earns - nothing on the baseline.
A9: Baseline profit the share is measured above ($/yr) | B9: 0 | C9: Essentially zero today, which is the honest number. Raise it if the business grows before the arrangement starts.
A10: Profits interest (% of value created above the hurdle) | B10: 0.15 | C10: An LLC profits interest: a share of future growth only, with no claim on what the company is worth today. Not taxable at grant under Rev. Proc. 93-27, and file an 83(b) within 30 days.
A11: The hurdle - what the company is worth the day you start ($) | B11: 170000 | C11: Set by a contemporaneous valuation, not a guess. A hurdle nobody can defend is the usual way these grants fall apart in an audit.

Sheet Year by year
A1: What you earn, year by year
A2: Every figure is a formula off your own inputs and the locked company snapshot. Change an input and all fifteen years move.
A5: Year | B5: 1 | C5: 2 | D5: 3 | E5: 4 | F5: 5 | G5: 6 | H5: 7 | I5: 8 | J5: 9 | K5: 10 | L5: 11 | M5: 12 | N5: 13 | O5: 14 | P5: 15 | R5: Notes
A6: Operating profit before you are paid | B6: 164146.07 | C6: 153726.24 | D6: 211218.98 | E6: 337332.01 | F6: 329969.66 | G6: 316088.77 | H6: 447197.76 | I6: 585647.49 | J6: 731486.59 | K6: 748428.47 | L6: 912695.92 | M6: 1084746.4 | N6: 1264609.9 | O6: 1330797.9 | P6: 1394843.5 | R6: From the company snapshot, after Charlie's draw and before anything to you.
A7: Base salary | B7: ='Your numbers'!$B$4 -> 60000 | C7: ='Your numbers'!$B$4 -> 60000 | D7: ='Your numbers'!$B$5 -> 66000 | E7: ='Your numbers'!$B$6 -> 72000 | F7: ='Your numbers'!$B$6 -> 72000 | G7: =F7*(1+'Your numbers'!$B$7) -> 73980 | H7: =G7*(1+'Your numbers'!$B$7) -> 76014.45 | I7: =H7*(1+'Your numbers'!$B$7) -> 78104.847 | J7: =I7*(1+'Your numbers'!$B$7) -> 80252.731 | K7: =J7*(1+'Your numbers'!$B$7) -> 82459.681 | L7: =K7*(1+'Your numbers'!$B$7) -> 84727.322 | M7: =L7*(1+'Your numbers'!$B$7) -> 87057.323 | N7: =M7*(1+'Your numbers'!$B$7) -> 89451.4 | ... P7: =O7*(1+'Your numbers'!$B$7) -> 94438.874
A8: Profit above the baseline | B8: =MAX(0,B6-'Your numbers'!$B$9) -> 164146.07 | C8: =MAX(0,C6-'Your numbers'!$B$9) -> 153726.24 | D8: =MAX(0,D6-'Your numbers'!$B$9) -> 211218.98 | E8: =MAX(0,E6-'Your numbers'!$B$9) -> 337332.01 | F8: =MAX(0,F6-'Your numbers'!$B$9) -> 329969.66 | G8: =MAX(0,G6-'Your numbers'!$B$9) -> 316088.77 | H8: =MAX(0,H6-'Your numbers'!$B$9) -> 447197.76 | I8: =MAX(0,I6-'Your numbers'!$B$9) -> 585647.49 | ... P8: =MAX(0,P6-'Your numbers'!$B$9) -> 1394843.5
A9: Growth share earned | B9: =B8*'Your numbers'!$B$8 -> 16414.607 | C9: =C8*'Your numbers'!$B$8 -> 15372.624 | D9: =D8*'Your numbers'!$B$8 -> 21121.898 | E9: =E8*'Your numbers'!$B$8 -> 33733.201 | F9: =F8*'Your numbers'!$B$8 -> 32996.966 | G9: =G8*'Your numbers'!$B$8 -> 31608.877 | H9: =H8*'Your numbers'!$B$8 -> 44719.776 | I9: =I8*'Your numbers'!$B$8 -> 58564.749 | ... P9: =P8*'Your numbers'!$B$8 -> 139484.35
A10: TOTAL CASH TO YOU | B10: =B7+B9 -> 76414.607 | C10: =C7+C9 -> 75372.624 | D10: =D7+D9 -> 87121.898 | E10: =E7+E9 -> 105733.2 | F10: =F7+F9 -> 104996.97 | G10: =G7+G9 -> 105588.88 | H10: =H7+H9 -> 120734.23 | I10: =I7+I9 -> 136669.6 | ... P10: =P7+P9 -> 233923.22
A11: Cumulative cash | B11: =B10 -> 76414.607 | C11: =B11+C10 -> 151787.23 | D11: =C11+D10 -> 238909.13 | E11: =D11+E10 -> 344642.33 | F11: =E11+F10 -> 449639.3 | G11: =F11+G10 -> 555228.17 | H11: =G11+H10 -> 675962.4 | I11: =H11+I10 -> 812632 | J11: =I11+J10 -> 966033.38 | ... P11: =O11+P10 -> 2169691.5
A12: As a share of revenue | B12: =B10/1107883.476 -> 0.068973506 | C12: =C10/1130224.27392 -> 0.066688202 | D12: =D10/1470581.13731659 -> 0.059243177 | E12: =E10/2128361.5241759 -> 0.049678215 | F12: =F10/2531696.60117519 -> 0.041472966 | G12: =G10/2960567.60023987 -> 0.035665079 | H12: =H10/3415973.30476096 -> 0.035344019 | I12: =I10/3898958.3702101 -> 0.035052848 | J12: =J10/4410614.70976327 -> 0.034780048 | K12: =K10/4952082.94628947 -> 0.031764922 | L12: =L10/5524553.93215493 -> 0.031857217 | M12: =M10/6129270.33838766 -> 0.031901345 | N12: =N10/6767528.314843 -> 0.031904172 | O12: =O10/7045784.99129078 -> 0.031932724 | P12: =P10/7328447.27269707 -> 0.031919889 | R12: The affordability test. Past roughly 6-7% of revenue the role is eating the growth it exists to create.
A13: THE PROFITS INTEREST - NOT INCOME, ONLY PAYS ON A SALE OR A BUYOUT
A14: What the whole company is worth | B14: 691314.4 | C14: 752384.28 | D14: 925823.92 | E14: 1742417.7 | F14: 1826323.6 | G14: 1879798.6 | H14: 2566573.4 | I14: 3338763.7 | J14: 4199351.5 | K14: 4551505.5 | L14: 7514344.3 | M14: 8966057.5 | N14: 10536753 | O14: 11512932 | P14: 12490191
A15: Value created above the hurdle | B15: =MAX(0,B14-'Your numbers'!$B$11) -> 521314.4 | C15: =MAX(0,C14-'Your numbers'!$B$11) -> 582384.28 | D15: =MAX(0,D14-'Your numbers'!$B$11) -> 755823.92 | E15: =MAX(0,E14-'Your numbers'!$B$11) -> 1572417.7 | F15: =MAX(0,F14-'Your numbers'!$B$11) -> 1656323.6 | G15: =MAX(0,G14-'Your numbers'!$B$11) -> 1709798.6 | H15: =MAX(0,H14-'Your numbers'!$B$11) -> 2396573.4 | I15: =MAX(0,I14-'Your numbers'!$B$11) -> 3168763.7 | ... P15: =MAX(0,P14-'Your numbers'!$B$11) -> 12320191
A16: YOUR STAKE, IF IT WERE SETTLED THAT YEAR | B16: =B15*'Your numbers'!$B$10 -> 78197.16 | C16: =C15*'Your numbers'!$B$10 -> 87357.642 | D16: =D15*'Your numbers'!$B$10 -> 113373.59 | E16: =E15*'Your numbers'!$B$10 -> 235862.65 | F16: =F15*'Your numbers'!$B$10 -> 248448.53 | G16: =G15*'Your numbers'!$B$10 -> 256469.79 | H16: =H15*'Your numbers'!$B$10 -> 359486.02 | I16: =I15*'Your numbers'!$B$10 -> 475314.55 | ... P16: =P15*'Your numbers'!$B$10 -> 1848028.6 | R16: Taxed as a capital gain, not income - and only when it actually pays.
A17: EVERYTHING, IF YOU WALKED AWAY THAT YEAR | B17: =B11+B16 -> 154611.77 | C17: =C11+C16 -> 239144.87 | D17: =D11+D16 -> 352282.72 | E17: =E11+E16 -> 580504.98 | F17: =F11+F16 -> 698087.83 | G17: =G11+G16 -> 811697.96 | H17: =H11+H16 -> 1035448.4 | I17: =I11+I16 -> 1287946.5 | ... P17: =P11+P16 -> 4017720.1 | R17: Cash taken along the way plus the stake settled at the end. The honest total.

Sheet The company
A1: Scag Scapes - the plan these numbers sit on top of
A2: A fixed snapshot from the master model, dated September 2026. These are NOT inputs - they are the agreed plan, and they are locked so nothing here can be changed by accident. Everything on your own tabs is live and yours to change.
A4: If the company's plan itself changes, this snapshot gets reissued. Ask for a fresh copy rather than editing this one.
A6: Year | B6: 1 | C6: 2 | D6: 3 | E6: 4 | F6: 5 | G6: 6 | H6: 7 | I6: 8 | J6: 9 | K6: 10 | L6: 11 | M6: 12 | N6: 13 | O6: 14 | P6: 15 | R6: Notes
A7: Total revenue | B7: 1107883.5 | C7: 1130224.3 | D7: 1470581.1 | E7: 2128361.5 | F7: 2531696.6 | G7: 2960567.6 | H7: 3415973.3 | I7: 3898958.4 | J7: 4410614.7 | K7: 4952082.9 | L7: 5524553.9 | M7: 6129270.3 | N7: 6767528.3 | O7: 7045785 | P7: 7328447.3
A8: Crews running | B8: 2 | C8: 2 | D8: 2.5 | E8: 3.5 | F8: 4 | G8: 4.5 | H8: 5 | I8: 5.5 | J8: 6 | K8: 6.5 | L8: 7 | M8: 7.5 | N8: 8 | O8: 8 | P8: 8
A9: People on the payroll | B9: 9 | C9: 9 | D9: 12 | E9: 16 | F9: 19 | G9: 23 | H9: 25 | I9: 27 | J9: 28 | K9: 32 | L9: 33 | M9: 36 | N9: 37 | O9: 37 | P9: 37
A10: Operating profit before Charlie's draw and before any partner is paid | B10: 314146.07 | C10: 303726.24 | D10: 361218.98 | E10: 487332.01 | F10: 479969.66 | G10: 466088.77 | H10: 597197.76 | I10: 735647.49 | J10: 881486.59 | K10: 898428.47 | L10: 1062695.9 | M10: 1234746.4 | N10: 1414609.9 | O10: 1480797.9 | P10: 1544843.5 | R10: The pot that everyone - Charlie, and anyone else with a share - is paid out of.
A11: Cash in the company at year end | B11: 62958.429 | C11: 124448.93 | D11: 195086.52 | E11: 302319.32 | F11: 420457.19 | G11: 533042.69 | H11: 698071.8 | I11: 918480.79 | J11: 1197225.4 | K11: 1482746.8 | L11: 1833975.2 | M11: 2254023.8 | N11: 2746017.7 | O11: 3278336.9 | P11: 3836274.3
A12: What the whole company is worth | B12: 691314.4 | C12: 752384.28 | D12: 925823.92 | E12: 1742417.7 | F12: 1826323.6 | G12: 1879798.6 | H12: 2566573.4 | I12: 3338763.7 | J12: 4199351.5 | K12: 4551505.5 | L12: 7514344.3 | M12: 8966057.5 | N12: 10536753 | O12: 11512932 | P12: 12490191 | R12: Priced on owner's cash under $2M of revenue and on EBITDA above it, because the size of the company decides who is allowed to buy it. Full workings are in the master model.

Sheet Buyout options
A1: Buying Ned out - what it costs in any year
A2: Blue = change it. Neither side should ever have to guess what a separation costs. This is the formula, agreed in advance, while everyone still likes each other. A buyout is almost never paid in one cheque - the monthly figures are what it actually looks like.
A4: Discount for an internal buyout (a minority stake, no control, no market) | B4: 0.2 | D4: A stake nobody else can buy is worth less than a proportionate slice of the whole. 20% is a common working figure - it is a negotiating position, not a published fact.
A5: Interest rate on a buyout paid over time (APR) | B5: 0.0875 | D5: Roughly what the business itself can borrow at. Paying a departing partner is not cheaper than paying a bank.
A8: Year | B8: 1 | C8: 2 | D8: 3 | E8: 4 | F8: 5 | G8: 6 | H8: 7 | I8: 8 | J8: 9 | K8: 10 | L8: 11 | M8: 12 | N8: 13 | O8: 14 | P8: 15 | R8: Notes
A9: What the stake is worth that year | B9: ='Year by year'!B16 -> 78197.16 | C9: ='Year by year'!C16 -> 87357.642 | D9: ='Year by year'!D16 -> 113373.59 | E9: ='Year by year'!E16 -> 235862.65 | F9: ='Year by year'!F16 -> 248448.53 | G9: ='Year by year'!G16 -> 256469.79 | H9: ='Year by year'!H16 -> 359486.02 | I9: ='Year by year'!I16 -> 475314.55 | ... P9: ='Year by year'!P16 -> 1848028.6 | R9: Straight from your own proforma tab.
A10: Buyout price after the internal discount | B10: =B9*(1-$B$4) -> 62557.728 | C10: =C9*(1-$B$4) -> 69886.114 | D10: =D9*(1-$B$4) -> 90698.87 | E10: =E9*(1-$B$4) -> 188690.12 | F10: =F9*(1-$B$4) -> 198758.83 | G10: =G9*(1-$B$4) -> 205175.83 | H10: =H9*(1-$B$4) -> 287588.81 | I10: =I9*(1-$B$4) -> 380251.64 | ... P10: =P9*(1-$B$4) -> 1478422.9
A11: Paid as a lump sum | B11: =B10 -> 62557.728 | C11: =C10 -> 69886.114 | D11: =D10 -> 90698.87 | E11: =E10 -> 188690.12 | F11: =F10 -> 198758.83 | G11: =G10 -> 205175.83 | H11: =H10 -> 287588.81 | I11: =I10 -> 380251.64 | ... P11: =P10 -> 1478422.9
A12: Or monthly over 3 years | B12: =IF(B10=0,0,PMT($B$5/12,36,-B10)) -> 1982.0482 | C12: =IF(C10=0,0,PMT($B$5/12,36,-C10)) -> 2214.2372 | D12: =IF(D10=0,0,PMT($B$5/12,36,-D10)) -> 2873.6583 | E12: =IF(E10=0,0,PMT($B$5/12,36,-E10)) -> 5978.3648 | F12: =IF(F10=0,0,PMT($B$5/12,36,-F10)) -> 6297.3767 | G12: =IF(G10=0,0,PMT($B$5/12,36,-G10)) -> 6500.6898 | H12: =IF(H10=0,0,PMT($B$5/12,36,-H10)) -> 9111.8222 | I12: =IF(I10=0,0,PMT($B$5/12,36,-I10)) -> 12047.706 | ... P12: =IF(P10=0,0,PMT($B$5/12,36,-P10)) -> 46841.622
A13: Or monthly over 5 years | B13: =IF(B10=0,0,PMT($B$5/12,60,-B10)) -> 1291.0184 | C13: =IF(C10=0,0,PMT($B$5/12,60,-C10)) -> 1442.256 | D13: =IF(D10=0,0,PMT($B$5/12,60,-D10)) -> 1871.7737 | E13: =IF(E10=0,0,PMT($B$5/12,60,-E10)) -> 3894.042 | F13: =IF(F10=0,0,PMT($B$5/12,60,-F10)) -> 4101.8322 | G13: =IF(G10=0,0,PMT($B$5/12,60,-G10)) -> 4234.2613 | H13: =IF(H10=0,0,PMT($B$5/12,60,-H10)) -> 5935.0372 | I13: =IF(I10=0,0,PMT($B$5/12,60,-I10)) -> 7847.3416 | ... P13: =IF(P10=0,0,PMT($B$5/12,60,-P10)) -> 30510.557 | R13: Five years is the usual shape. It is long enough that the payment comes out of the profit the departing partner helped build, rather than out of the company's working capital.
A14: Or monthly over 7 years | B14: =IF(B10=0,0,PMT($B$5/12,84,-B10)) -> 998.57725 | C14: =IF(C10=0,0,PMT($B$5/12,84,-C10)) -> 1115.5566 | D14: =IF(D10=0,0,PMT($B$5/12,84,-D10)) -> 1447.78 | E14: =IF(E10=0,0,PMT($B$5/12,84,-E10)) -> 3011.9646 | F14: =IF(F10=0,0,PMT($B$5/12,84,-F10)) -> 3172.6862 | G14: =IF(G10=0,0,PMT($B$5/12,84,-G10)) -> 3275.1176 | H14: =IF(H10=0,0,PMT($B$5/12,84,-H10)) -> 4590.6342 | I14: =IF(I10=0,0,PMT($B$5/12,84,-I10)) -> 6069.7639 | ... P14: =IF(P10=0,0,PMT($B$5/12,84,-P10)) -> 23599.314
A15: CAN THE COMPANY ACTUALLY PAY IT?
A16: Operating profit that year | B16: 314146.07 | C16: 303726.24 | D16: 361218.98 | E16: 487332.01 | F16: 479969.66 | G16: 466088.77 | H16: 597197.76 | I16: 735647.49 | J16: 881486.59 | K16: 898428.47 | L16: 1062695.9 | M16: 1234746.4 | N16: 1414609.9 | O16: 1480797.9 | P16: 1544843.5
A17: Cash in the company at year end | B17: 62958.429 | C17: 124448.93 | D17: 195086.52 | E17: 302319.32 | F17: 420457.19 | G17: 533042.69 | H17: 698071.8 | I17: 918480.79 | J17: 1197225.4 | K17: 1482746.8 | L17: 1833975.2 | M17: 2254023.8 | N17: 2746017.7 | O17: 3278336.9 | P17: 3836274.3
A18: The 5-year payment as a share of that year's profit | B18: =IF(B16=0,0,B13*12/B16) -> 0.049315341 | C18: =IF(C16=0,0,C13*12/C16) -> 0.056982472 | D18: =IF(D16=0,0,D13*12/D16) -> 0.062181905 | E18: =IF(E16=0,0,E13*12/E16) -> 0.095886382 | F18: =IF(F16=0,0,F13*12/F16) -> 0.10255229 | G18: =IF(G16=0,0,G13*12/G16) -> 0.10901601 | H18: =IF(H16=0,0,H13*12/H16) -> 0.11925773 | I18: =IF(I16=0,0,I13*12/I16) -> 0.1280071 | ... P18: =IF(P16=0,0,P13*12/P16) -> 0.23699921 | R18: Above roughly 25% and the buyout is eating the business rather than being funded by it. That is the number to argue about, not the headline price.
A19: Could it be paid in cash outright? | B19: =IF(B10=0,"-",IF(B17>=B10,"yes","no - needs a note")) -> yes | C19: =IF(C10=0,"-",IF(C17>=C10,"yes","no - needs a note")) -> yes | D19: =IF(D10=0,"-",IF(D17>=D10,"yes","no - needs a note")) -> yes | E19: =IF(E10=0,"-",IF(E17>=E10,"yes","no - needs a note")) -> yes | F19: =IF(F10=0,"-",IF(F17>=F10,"yes","no - needs a note")) -> yes | G19: =IF(G10=0,"-",IF(G17>=G10,"yes","no - needs a note")) -> yes | H19: =IF(H10=0,"-",IF(H17>=H10,"yes","no - needs a note")) -> yes | I19: =IF(I10=0,"-",IF(I17>=I10,"yes","no - needs a note")) -> yes | ... P19: =IF(P10=0,"-",IF(P17>=P10,"yes","no - needs a note")) -> yes
A21: THE RULES THAT MAKE THIS WORK
A22: 1. The price is a FORMULA, not a negotiation. It is agreed now, in writing, and applied whenever it is needed. Nobody gets to re-open the multiple in the middle of an argument.
A23: 2. The company has the first right to buy. If it declines, the other partners may. If they decline, the stake can be offered outside - with the company holding a right to match.
A24: 3. Payment terms are the company's choice from the options above, but the term may not exceed seven years and the rate may not be below the rate above.
A25: 4. A departure for cause is different: unvested value is forfeited, and vested value is bought at the lower of cost or formula. 'Cause' is defined narrowly on the Obligations tab - not 'we fell out'.
A26: 5. Death or disability is treated as a good-leaver departure at full formula value, paid to the estate on the same terms. Consider funding this with a small term life policy; it costs very little at these ages.
A27: 6. Any dispute over the number goes to the company's CPA, whose determination binds both sides. Two friends have no other way to break a tie, and courts are worse.

Sheet Obligations
A1: What each side owes the other
A2: We are friends, which is exactly why this is written down. Friendship makes the hard conversation more expensive, not less - so the rules get agreed while everyone is comfortable, and there is deliberate slack built into every one of them.
A4: WHAT NED OWES THE COMPANY
A5: The obligation | B5: What it actually means | C5: How we know it is being met
A6: Leads and marketing | B6: Own everything upstream of the quote: the lead sources, the spend, the response time, the reviews and the referral engine. Leads arrive, or this role has not been done. | C6: Leads and cost per lead reported monthly. The agreed target is set each January and missed months are flagged the same month, not at year end.
A7: The software | B7: Build, run and maintain the Command platform. Keep it working. Fix what breaks. Train whoever needs training. | C7: Uptime and the fact that crews and the office actually use it. A system nobody uses is a system that was not delivered.
A8: The numbers | B8: Keep the model current, produce the monthly figures Charlie needs to run the business, and tell him bad news early rather than tidily. | C8: A monthly pack, on the same date every month, whether the news is good or not.
A9: Show up | B9: Be reachable and present for the agreed hours. Fractional means fewer hours, not optional ones. | C9: Agreed in advance. If the hours need to change, they get renegotiated rather than quietly reduced.
A10: Confidentiality and non-circumvention | B10: Charlie's customers, pricing and data are his. Not to be used elsewhere, during or after. | C10: Covered in the mutual NDA and repeated here so it cannot be claimed it was never discussed.
A12: WHAT THE COMPANY OWES NED
A13: The obligation | B13: What it actually means | C13: How we know it is being met
A14: Pay on time | B14: The base is paid on the same day each month. The growth share is calculated within 60 days of year end and paid within 30 days of that. | C14: Late pay is itself a Step 2 event. It is not a cash-flow question, it is a trust question.
A15: Open books | B15: Full access to the accounts needed to calculate the share. The share cannot be verified by somebody who cannot see the numbers. | C15: Read access to the books, and the CPA's year-end figure as the binding one.
A16: Actually run the plan | B16: The share is earned on profit growth. That growth requires Charlie to do the agreed things - hire the crews, hold the price, work the gates. If he declines to run the plan, the share cannot be earned through no fault of Ned's. | C16: If an agreed growth step is refused, that year's share is calculated as though it had been taken - or the arrangement ends cleanly. Not both parties losing.
A17: Decision authority | B17: Within the agreed areas - marketing spend up to the budget, the software, the systems - decisions are Ned's to make and not re-litigated afterwards. | C17: Written down, once, at the start.
A18: The equity is real | B18: The profits interest is granted when agreed, papered by an attorney, with an 83(b) filed. A promise of equity that never gets documented is not equity. | C18: Signed operating agreement amendment. There is no informal version of this.
A20: IF SOMEBODY IS NOT HOLDING UP THEIR END
A21: Stage | B21: What happens | C21: The consequence
A22: Step 1 - Say it out loud | B22: A conversation, in private, naming the specific thing. Not a mood, not a hint, not a comment in front of the crew. Most problems die here and never get further. | C22: No paperwork. No consequence. This step is free and it is the one most often skipped.
A23: Step 2 - Put it in writing | B23: If it is still happening 30 days later: one page, dated, naming the obligation, what was missed, and what fixing it looks like. Both sides sign that they have read it. This is not a disciplinary letter - it is a shared record so that in six months nobody is arguing about what was said. | C23: A signed note in the file. Nothing else changes - no pay cut, no equity change.
A24: Step 3 - A real cure period | B24: 90 days to fix it, with a specific, measurable definition of fixed agreed at the start of the 90 days rather than judged at the end of it. | C24: Reviewed at the end of the 90 days by both parties, in writing.
A25: Step 4 - Consequence | B25: If the same obligation is missed twice in twelve months after a Step 3 cure: vesting pauses until it is corrected. Vesting PAUSES - nothing already earned is taken away. If the miss is on the company's side instead, the partner's notice period shortens and vesting accelerates by the same amount. | C25: The vesting clock stops. It restarts when the cure is confirmed.
A26: Step 5 - Separation, on good terms | B26: Either side may end it on 90 days' written notice, for any reason or none. Everything vested is bought at the formula price on the Buyout tab. This is the normal exit and it is nobody's failure. | C26: Formula price, standard payment terms.
A27: Cause - the narrow exception | B27: Only for the items listed below. Cause requires written notice, a 15-day cure where a cure is possible, and the CPA's concurrence that it qualifies. Unvested value is forfeited and vested value is bought at the lower of cost or formula. | C27: Deliberately hard to invoke. 'We disagree' and 'it is not working' are Step 5, not cause.
A29: WHAT COUNTS AS CAUSE - AND NOTHING ELSE DOES
A30: • | B30: Dishonesty about money - taking it, hiding it, or misreporting it.
A31: • | B31: Working against the company: competing with it, soliciting its customers or crews for somebody else, or handing its data to a competitor.
A32: • | B32: A criminal act that materially damages the business or its reputation.
A33: • | B33: Complete and sustained abandonment of the role - not a slow patch, not a disagreement about direction, and not a year where the numbers were disappointing.
A34: • | B34: Nothing else. In particular: being wrong, being late, being difficult, losing an argument, or the plan simply not working are NOT cause. They are Step 5.
A36: The tiebreaker: any disagreement about whether an obligation has been met goes to the company's CPA. Their call binds both sides. It is not a court, it is not a lawyer, and it costs almost nothing - which is the point.
A38: The slack is deliberate. Two conversations and ninety days before anything at all happens to anyone's money. That is more rope than any employer would give, and it is there because these are friendships first. What the slack is NOT is permission for a problem to go unnamed for a year and then surface as a fight.
A40: None of this is legal drafting. It is the commercial agreement in plain words so that an attorney can paper it quickly and cheaply, and so that both signers actually understand what they signed.
