Workbook

Sheet Your numbers
A1: Bryan Rogers - Chief Operating Officer
A2: Blue = change it. This file is yours alone - it contains nobody else's compensation, and nobody else's file contains yours.
A4: Base salary while revenue is under $1.5M ($/yr) | B4: 95000 | C4: BLS May 2025, Baton Rouge metro, General and Operations Managers: median $107,140, mean $136,200, 25th percentile $74,000. This sits just under the local median because that is what a two-crew company can carry.
A5: Base salary at $1.5M to $3M revenue ($/yr) | B5: 120000 | C5: Roughly the Baton Rouge metro mean for the occupation.
A6: Base salary at $3M to $6M revenue ($/yr) | B6: 155000 | C6: Between the local mean and the 75th percentile ($167,430). At this size it is a genuinely different job.
A7: Base salary above $6M revenue ($/yr) | B7: 185000 | C7: Approaching the CFMA survey band for a construction Operations Manager, though those respondents are much larger contractors.
A8: Target bonus (% of base) | B8: 0.22 | C8: 20-30% is the norm for a COO. Tied to gross profit per crew-day, job margin, callbacks and crews staffed - deliberately NOT to net profit, which the owner controls through discretionary spending.
A9: Share of the bonus actually earned (1.0 = full target) | B9: 1 | C9: Drop it to 0.7 or 0.5 to see a year where the targets are missed.
A10: Equity granted (% of the company) | B10: 0.12 | C10: Recruited COOs in venture-backed companies get 1-5%, but that band does not fit a cash-flow business with no exit in sight. An operating partner who sells a business to join sits at 10-25%. This is judgment, not survey data, and it is the most negotiable number here.
A11: Years to fully vest | B11: 4 | C11: Four years with a one-year cliff. Nothing at all vests if you leave inside twelve months.
A12: The hurdle - what the company is worth the day you start ($) | B12: 722514.4 | C12: Written as a profits interest, so it pays on growth from your start date and nothing on what Charlie already built. That is what makes it untaxed at grant.
A13: What the bar pays you today ($/yr) | B13: 128375 | C13: BizBuySell 2025: median seller's discretionary earnings for a bar was $128,375 on $800,000 of revenue - pre-tax and before debt service. REPLACE THIS WITH YOUR REAL NUMBER. The whole comparison turns on it.
A14: Share of full-time you work today (%) | B14: 0.6 | C14: About three days a week while the bar is still yours. Salary and bonus below are scaled by this until the year you go full-time.
A15: Year you go full-time (1-15) | B15: 2 | C15: The year the bar is sold or handed off and you are at 100%. Change it if that timeline moves.

Sheet Year by year
A1: What you earn, year by year
A2: Every figure is a formula off your own inputs and the locked company snapshot.
A5: Year | B5: 1 | C5: 2 | D5: 3 | E5: 4 | F5: 5 | G5: 6 | H5: 7 | I5: 8 | J5: 9 | K5: 10 | L5: 11 | M5: 12 | N5: 13 | O5: 14 | P5: 15 | R5: Notes
A6: Company revenue | B6: 1107883.5 | C6: 1130224.3 | D6: 1470581.1 | E6: 2128361.5 | F6: 2531696.6 | G6: 2960567.6 | H6: 3415973.3 | I6: 3898958.4 | J6: 4410614.7 | K6: 4952082.9 | L6: 5524553.9 | M6: 6129270.3 | N6: 6767528.3 | O6: 7045785 | P6: 7328447.3
A7: Base salary (steps with the size of the company, ramped while you still run the bar) | B7: =IF(B6>=6000000,'Your numbers'!$B$7,IF(B6>=3000000,'Your numbers'!$B$6,IF(B6>=1500000,'Your numbers'!$B$5,'Your numbers'!$B$4)))*IF(1>='Your numbers'!$B$15,1,'Your numbers'!$B$14) -> 57000 | C7: =IF(C6>=6000000,'Your numbers'!$B$7,IF(C6>=3000000,'Your numbers'!$B$6,IF(C6>=1500000,'Your numbers'!$B$5,'Your numbers'!$B$4)))*IF(2>='Your numbers'!$B$15,1,'Your numbers'!$B$14) -> 95000 | D7: =IF(D6>=6000000,'Your numbers'!$B$7,IF(D6>=3000000,'Your numbers'!$B$6,IF(D6>=1500000,'Your numbers'!$B$5,'Your numbers'!$B$4)))*IF(3>='Your numbers'!$B$15,1,'Your numbers'!$B$14) -> 95000 | E7: =IF(E6>=6000000,'Your numbers'!$B$7,IF(E6>=3000000,'Your numbers'!$B$6,IF(E6>=1500000,'Your numbers'!$B$5,'Your numbers'!$B$4)))*IF(4>='Your numbers'!$B$15,1,'Your numbers'!$B$14) -> 120000 | F7: =IF(F6>=6000000,'Your numbers'!$B$7,IF(F6>=3000000,'Your numbers'!$B$6,IF(F6>=1500000,'Your numbers'!$B$5,'Your numbers'!$B$4)))*IF(5>='Your numbers'!$B$15,1,'Your numbers'!$B$14) -> 120000 | G7: =IF(G6>=6000000,'Your numbers'!$B$7,IF(G6>=3000000,'Your numbers'!$B$6,IF(G6>=1500000,'Your numbers'!$B$5,'Your numbers'!$B$4)))*IF(6>='Your numbers'!$B$15,1,'Your numbers'!$B$14) -> 120000 | H7: =IF(H6>=6000000,'Your numbers'!$B$7,IF(H6>=3000000,'Your numbers'!$B$6,IF(H6>=1500000,'Your numbers'!$B$5,'Your numbers'!$B$4)))*IF(7>='Your numbers'!$B$15,1,'Your numbers'!$B$14) -> 155000 | I7: =IF(I6>=6000000,'Your numbers'!$B$7,IF(I6>=3000000,'Your numbers'!$B$6,IF(I6>=1500000,'Your numbers'!$B$5,'Your numbers'!$B$4)))*IF(8>='Your numbers'!$B$15,1,'Your numbers'!$B$14) -> 155000 | J7: =IF(J6>=6000000,'Your numbers'!$B$7,IF(J6>=3000000,'Your numbers'!$B$6,IF(J6>=1500000,'Your numbers'!$B$5,'Your numbers'!$B$4)))*IF(9>='Your numbers'!$B$15,1,'Your numbers'!$B$14) -> 155000 | K7: =IF(K6>=6000000,'Your numbers'!$B$7,IF(K6>=3000000,'Your numbers'!$B$6,IF(K6>=1500000,'Your numbers'!$B$5,'Your numbers'!$B$4)))*IF(10>='Your numbers'!$B$15,1,'Your numbers'!$B$14) -> 155000 | L7: =IF(L6>=6000000,'Your numbers'!$B$7,IF(L6>=3000000,'Your numbers'!$B$6,IF(L6>=1500000,'Your numbers'!$B$5,'Your numbers'!$B$4)))*IF(11>='Your numbers'!$B$15,1,'Your numbers'!$B$14) -> 155000 | M7: =IF(M6>=6000000,'Your numbers'!$B$7,IF(M6>=3000000,'Your numbers'!$B$6,IF(M6>=1500000,'Your numbers'!$B$5,'Your numbers'!$B$4)))*IF(12>='Your numbers'!$B$15,1,'Your numbers'!$B$14) -> 185000 | N7: =IF(N6>=6000000,'Your numbers'!$B$7,IF(N6>=3000000,'Your numbers'!$B$6,IF(N6>=1500000,'Your numbers'!$B$5,'Your numbers'!$B$4)))*IF(13>='Your numbers'!$B$15,1,'Your numbers'!$B$14) -> 185000 | O7: =IF(O6>=6000000,'Your numbers'!$B$7,IF(O6>=3000000,'Your numbers'!$B$6,IF(O6>=1500000,'Your numbers'!$B$5,'Your numbers'!$B$4)))*IF(14>='Your numbers'!$B$15,1,'Your numbers'!$B$14) -> 185000 | P7: =IF(P6>=6000000,'Your numbers'!$B$7,IF(P6>=3000000,'Your numbers'!$B$6,IF(P6>=1500000,'Your numbers'!$B$5,'Your numbers'!$B$4)))*IF(15>='Your numbers'!$B$15,1,'Your numbers'!$B$14) -> 185000 | R7: The raise happens when the business gets there - and you are the person most able to make it get there. Scaled down to your actual share of full-time until the year you go full-time, set above.
A8: Bonus earned | B8: =B7*'Your numbers'!$B$8*'Your numbers'!$B$9 -> 12540 | C8: =C7*'Your numbers'!$B$8*'Your numbers'!$B$9 -> 20900 | D8: =D7*'Your numbers'!$B$8*'Your numbers'!$B$9 -> 20900 | E8: =E7*'Your numbers'!$B$8*'Your numbers'!$B$9 -> 26400 | F8: =F7*'Your numbers'!$B$8*'Your numbers'!$B$9 -> 26400 | G8: =G7*'Your numbers'!$B$8*'Your numbers'!$B$9 -> 26400 | H8: =H7*'Your numbers'!$B$8*'Your numbers'!$B$9 -> 34100 | I8: =I7*'Your numbers'!$B$8*'Your numbers'!$B$9 -> 34100 | ... P8: =P7*'Your numbers'!$B$8*'Your numbers'!$B$9 -> 40700
A9: TOTAL CASH TO YOU | B9: =B7+B8 -> 69540 | C9: =C7+C8 -> 115900 | D9: =D7+D8 -> 115900 | E9: =E7+E8 -> 146400 | F9: =F7+F8 -> 146400 | G9: =G7+G8 -> 146400 | H9: =H7+H8 -> 189100 | I9: =I7+I8 -> 189100 | ... P9: =P7+P8 -> 225700
A10: Less the operations manager you replace | B10: 0 | C10: 0 | D10: 0 | E10: 79827.687 | F10: 82621.656 | G10: 85513.414 | H10: 88506.383 | I10: 91604.107 | J10: 94810.251 | K10: 98128.609 | L10: 101563.11 | M10: 105117.82 | N10: 108796.94 | O10: 112604.84 | P10: 116546.01 | R10: The plan always intended to hire an operations manager once it hit three crews. You replace that hire, so your real cost to the business is lower than your package.
A11: NET COST OF YOU TO THE BUSINESS | B11: =B9-B10 -> 69540 | C11: =C9-C10 -> 115900 | D11: =D9-D10 -> 115900 | E11: =E9-E10 -> 66572.313 | F11: =F9-F10 -> 63778.344 | G11: =G9-G10 -> 60886.586 | H11: =H9-H10 -> 100593.62 | I11: =I9-I10 -> 97495.893 | ... P11: =P9-P10 -> 109153.99
A12: EQUITY - EARNED OVER TIME, NOT GIVEN ON DAY ONE
A13: Vested share of the grant | B13: =MIN(1,MAX(0,1/'Your numbers'!$B$11)) -> 0.25 | C13: =MIN(1,MAX(0,2/'Your numbers'!$B$11)) -> 0.5 | D13: =MIN(1,MAX(0,3/'Your numbers'!$B$11)) -> 0.75 | E13: =MIN(1,MAX(0,4/'Your numbers'!$B$11)) -> 1 | F13: =MIN(1,MAX(0,5/'Your numbers'!$B$11)) -> 1 | G13: =MIN(1,MAX(0,6/'Your numbers'!$B$11)) -> 1 | H13: =MIN(1,MAX(0,7/'Your numbers'!$B$11)) -> 1 | I13: =MIN(1,MAX(0,8/'Your numbers'!$B$11)) -> 1 | J13: =MIN(1,MAX(0,9/'Your numbers'!$B$11)) -> 1 | K13: =MIN(1,MAX(0,10/'Your numbers'!$B$11)) -> 1 | L13: =MIN(1,MAX(0,11/'Your numbers'!$B$11)) -> 1 | M13: =MIN(1,MAX(0,12/'Your numbers'!$B$11)) -> 1 | N13: =MIN(1,MAX(0,13/'Your numbers'!$B$11)) -> 1 | O13: =MIN(1,MAX(0,14/'Your numbers'!$B$11)) -> 1 | P13: =MIN(1,MAX(0,15/'Your numbers'!$B$11)) -> 1 | R13: One-year cliff, then a quarter a year. Unvested equity is forfeited on departure; vested equity is bought at the formula price on the Buyout tab.
A14: Equity you have actually earned (%) | B14: =B13*'Your numbers'!$B$10 -> 0.03 | C14: =C13*'Your numbers'!$B$10 -> 0.06 | D14: =D13*'Your numbers'!$B$10 -> 0.09 | E14: =E13*'Your numbers'!$B$10 -> 0.12 | F14: =F13*'Your numbers'!$B$10 -> 0.12 | G14: =G13*'Your numbers'!$B$10 -> 0.12 | H14: =H13*'Your numbers'!$B$10 -> 0.12 | I14: =I13*'Your numbers'!$B$10 -> 0.12 | ... P14: =P13*'Your numbers'!$B$10 -> 0.12
A15: What the whole company is worth | B15: 737130.15 | C15: 793606.67 | D15: 973791.85 | E15: 1704841.1 | F15: 1781926.3 | G15: 2078739.7 | H15: 2788865.5 | I15: 3584726.6 | J15: 4191175.9 | K15: 5168219 | L15: 8245690.5 | M15: 9739722.2 | N15: 11353080 | O15: 12401842 | P15: 13454922
A16: Value created since you joined | B16: =MAX(0,B15-'Your numbers'!$B$12) -> 14615.751 | C16: =MAX(0,C15-'Your numbers'!$B$12) -> 71092.269 | D16: =MAX(0,D15-'Your numbers'!$B$12) -> 251277.45 | E16: =MAX(0,E15-'Your numbers'!$B$12) -> 982326.7 | F16: =MAX(0,F15-'Your numbers'!$B$12) -> 1059411.9 | G16: =MAX(0,G15-'Your numbers'!$B$12) -> 1356225.3 | H16: =MAX(0,H15-'Your numbers'!$B$12) -> 2066351.1 | I16: =MAX(0,I15-'Your numbers'!$B$12) -> 2862212.2 | ... P16: =MAX(0,P15-'Your numbers'!$B$12) -> 12732408
A17: WHAT YOUR STAKE IS WORTH | B17: =B14*B16 -> 438.47254 | C17: =C14*C16 -> 4265.5362 | D17: =D14*D16 -> 22614.97 | E17: =E14*E16 -> 117879.2 | F17: =F14*F16 -> 127129.42 | G17: =G14*G16 -> 162747.04 | H17: =H14*H16 -> 247962.13 | I17: =I14*I16 -> 343465.47 | ... P17: =P14*P16 -> 1527888.9
A18: AGAINST WHAT YOU ALREADY HAVE - THE ACTUAL DECISION
A19: What the bar pays you | B19: ='Your numbers'!$B$13*(1.0275)^0 -> 128375 | C19: ='Your numbers'!$B$13*(1.0275)^1 -> 131905.31 | D19: ='Your numbers'!$B$13*(1.0275)^2 -> 135532.71 | E19: ='Your numbers'!$B$13*(1.0275)^3 -> 139259.86 | F19: ='Your numbers'!$B$13*(1.0275)^4 -> 143089.5 | G19: ='Your numbers'!$B$13*(1.0275)^5 -> 147024.47 | H19: ='Your numbers'!$B$13*(1.0275)^6 -> 151067.64 | I19: ='Your numbers'!$B$13*(1.0275)^7 -> 155222 | J19: ='Your numbers'!$B$13*(1.0275)^8 -> 159490.6 | K19: ='Your numbers'!$B$13*(1.0275)^9 -> 163876.59 | L19: ='Your numbers'!$B$13*(1.0275)^10 -> 168383.2 | M19: ='Your numbers'!$B$13*(1.0275)^11 -> 173013.74 | N19: ='Your numbers'!$B$13*(1.0275)^12 -> 177771.62 | O19: ='Your numbers'!$B$13*(1.0275)^13 -> 182660.34 | P19: ='Your numbers'!$B$13*(1.0275)^14 -> 187683.5 | R19: Grown at inflation. Replace the input with your real number.
A20: Cash difference that year | B20: =B9-B19 -> -58835 | C20: =C9-C19 -> -16005.312 | D20: =D9-D19 -> -19632.709 | E20: =E9-E19 -> 7140.1419 | F20: =F9-F19 -> 3310.4958 | G20: =G9-G19 -> -624.46554 | H20: =H9-H19 -> 38032.362 | I20: =I9-I19 -> 33878.002 | ... P20: =P9-P19 -> 38016.504 | R20: Negative early. That is the honest shape of this - you take a pay cut to buy equity in something bigger.
A21: Cumulative cash difference | B21: =B20 -> -58835 | C21: =B21+C20 -> -74840.312 | D21: =C21+D20 -> -94473.021 | E21: =D21+E20 -> -87332.879 | F21: =E21+F20 -> -84022.383 | G21: =F21+G20 -> -84646.849 | H21: =G21+H20 -> -46614.487 | I21: =H21+I20 -> -12736.486 | J21: =I21+J20 -> 16872.911 | ... P21: =O21+P20 -> 244483.93
A22: CASH DIFFERENCE PLUS EQUITY EARNED | B22: =B21+B17 -> -58396.527 | C22: =C21+C17 -> -70574.776 | D22: =D21+D17 -> -71858.051 | E22: =E21+E17 -> 30546.325 | F22: =F21+F17 -> 43107.039 | G22: =G21+G17 -> 78100.19 | H22: =H21+H17 -> 201347.65 | I22: =I21+I17 -> 330728.98 | ... P22: =P21+P17 -> 1772372.8 | R22: The year this turns positive is the year the move has paid for itself. The bar's sale proceeds sit on top - that money is yours either way.
A23: Are you ahead yet? | B23: =IF(B22>0,"AHEAD","behind") -> behind | C23: =IF(C22>0,"AHEAD","behind") -> behind | D23: =IF(D22>0,"AHEAD","behind") -> behind | E23: =IF(E22>0,"AHEAD","behind") -> AHEAD | F23: =IF(F22>0,"AHEAD","behind") -> AHEAD | G23: =IF(G22>0,"AHEAD","behind") -> AHEAD | H23: =IF(H22>0,"AHEAD","behind") -> AHEAD | I23: =IF(I22>0,"AHEAD","behind") -> AHEAD | ... P23: =IF(P22>0,"AHEAD","behind") -> AHEAD

Sheet The company
A1: Scag Scapes - the plan these numbers sit on top of
A2: A fixed snapshot from the master model, dated September 2026. These are NOT inputs - they are the agreed plan, and they are locked so nothing here can be changed by accident. Everything on your own tabs is live and yours to change.
A4: If the company's plan itself changes, this snapshot gets reissued. Ask for a fresh copy rather than editing this one.
A6: Year | B6: 1 | C6: 2 | D6: 3 | E6: 4 | F6: 5 | G6: 6 | H6: 7 | I6: 8 | J6: 9 | K6: 10 | L6: 11 | M6: 12 | N6: 13 | O6: 14 | P6: 15 | R6: Notes
A7: Total revenue | B7: 1107883.5 | C7: 1130224.3 | D7: 1470581.1 | E7: 2128361.5 | F7: 2531696.6 | G7: 2960567.6 | H7: 3415973.3 | I7: 3898958.4 | J7: 4410614.7 | K7: 4952082.9 | L7: 5524553.9 | M7: 6129270.3 | N7: 6767528.3 | O7: 7045785 | P7: 7328447.3
A8: Crews running | B8: 2 | C8: 2 | D8: 2.5 | E8: 3.5 | F8: 4 | G8: 4.5 | H8: 5 | I8: 5.5 | J8: 6 | K8: 6.5 | L8: 7 | M8: 7.5 | N8: 8 | O8: 8 | P8: 8
A9: People on the payroll | B9: 9 | C9: 9 | D9: 12 | E9: 16 | F9: 19 | G9: 22 | H9: 24 | I9: 26 | J9: 28 | K9: 30 | L9: 31 | M9: 34 | N9: 35 | O9: 35 | P9: 35
A10: Operating profit before Charlie's draw and before any partner is paid | B10: 309346.07 | C10: 298686.24 | D10: 355430.85 | E10: 480212.62 | F10: 471947.32 | G10: 514099.93 | H10: 646151.3 | I10: 785530.44 | J10: 869075.96 | K10: 1029166.3 | L10: 1197070.7 | M10: 1372827.4 | N10: 1556465.4 | O10: 1627343.7 | P10: 1696229.8 | R10: The pot that everyone - Charlie, and anyone else with a share - is paid out of.
A11: Cash in the company at year end | B11: 61038.429 | C11: 120512.93 | D11: 188835.27 | E11: 293220.32 | F11: 408149.24 | G11: 539939.21 | H11: 724549.73 | I11: 964911.91 | J11: 1238692.3 | K11: 1576508.8 | L11: 1981487.1 | M11: 2456768.1 | N11: 3005504.2 | O11: 3596441.7 | P11: 4214933.6
A12: What the whole company is worth | B12: 737130.15 | C12: 793606.67 | D12: 973791.85 | E12: 1704841.1 | F12: 1781926.3 | G12: 2078739.7 | H12: 2788865.5 | I12: 3584726.6 | J12: 4191175.9 | K12: 5168219 | L12: 8245690.5 | M12: 9739722.2 | N12: 11353080 | O12: 12401842 | P12: 13454922 | R12: Priced on owner's cash under $2M of revenue and on EBITDA above it, because the size of the company decides who is allowed to buy it. Full workings are in the master model.

Sheet Buyout options
A1: Buying Bryan out - what it costs in any year
A2: Blue = change it. Neither side should ever have to guess what a separation costs. This is the formula, agreed in advance, while everyone still likes each other. A buyout is almost never paid in one cheque - the monthly figures are what it actually looks like.
A4: Discount for an internal buyout (a minority stake, no control, no market) | B4: 0.2 | D4: A stake nobody else can buy is worth less than a proportionate slice of the whole. 20% is a common working figure - it is a negotiating position, not a published fact.
A5: Interest rate on a buyout paid over time (APR) | B5: 0.0875 | D5: Roughly what the business itself can borrow at. Paying a departing partner is not cheaper than paying a bank.
A8: Year | B8: 1 | C8: 2 | D8: 3 | E8: 4 | F8: 5 | G8: 6 | H8: 7 | I8: 8 | J8: 9 | K8: 10 | L8: 11 | M8: 12 | N8: 13 | O8: 14 | P8: 15 | R8: Notes
A9: What the stake is worth that year | B9: ='Year by year'!B17 -> 438.47254 | C9: ='Year by year'!C17 -> 4265.5362 | D9: ='Year by year'!D17 -> 22614.97 | E9: ='Year by year'!E17 -> 117879.2 | F9: ='Year by year'!F17 -> 127129.42 | G9: ='Year by year'!G17 -> 162747.04 | H9: ='Year by year'!H17 -> 247962.13 | I9: ='Year by year'!I17 -> 343465.47 | ... P9: ='Year by year'!P17 -> 1527888.9 | R9: Straight from your own proforma tab. Only the VESTED portion is ever bought - that is what the vesting column above is for.
A10: Buyout price after the internal discount | B10: =B9*(1-$B$4) -> 350.77803 | C10: =C9*(1-$B$4) -> 3412.4289 | D10: =D9*(1-$B$4) -> 18091.976 | E10: =E9*(1-$B$4) -> 94303.363 | F10: =F9*(1-$B$4) -> 101703.54 | G10: =G9*(1-$B$4) -> 130197.63 | H10: =H9*(1-$B$4) -> 198369.71 | I10: =I9*(1-$B$4) -> 274772.37 | ... P10: =P9*(1-$B$4) -> 1222311.1
A11: Paid as a lump sum | B11: =B10 -> 350.77803 | C11: =C10 -> 3412.4289 | D11: =D10 -> 18091.976 | E11: =E10 -> 94303.363 | F11: =F10 -> 101703.54 | G11: =G10 -> 130197.63 | H11: =H10 -> 198369.71 | I11: =I10 -> 274772.37 | ... P11: =P10 -> 1222311.1
A12: Or monthly over 3 years | B12: =IF(B10=0,0,PMT($B$5/12,36,-B10)) -> 11.113878 | C12: =IF(C10=0,0,PMT($B$5/12,36,-C10)) -> 108.11772 | D12: =IF(D10=0,0,PMT($B$5/12,36,-D10)) -> 573.21725 | E12: =IF(E10=0,0,PMT($B$5/12,36,-E10)) -> 2987.8613 | F12: =IF(F10=0,0,PMT($B$5/12,36,-F10)) -> 3222.3248 | G12: =IF(G10=0,0,PMT($B$5/12,36,-G10)) -> 4125.1176 | H12: =IF(H10=0,0,PMT($B$5/12,36,-H10)) -> 6285.0481 | I12: =IF(I10=0,0,PMT($B$5/12,36,-I10)) -> 8705.7525 | ... P12: =IF(P10=0,0,PMT($B$5/12,36,-P10)) -> 38727.103
A13: Or monthly over 5 years | B13: =IF(B10=0,0,PMT($B$5/12,60,-B10)) -> 7.2390878 | C13: =IF(C10=0,0,PMT($B$5/12,60,-C10)) -> 70.42309 | D13: =IF(D10=0,0,PMT($B$5/12,60,-D10)) -> 373.36832 | E13: =IF(E10=0,0,PMT($B$5/12,60,-E10)) -> 1946.1605 | F13: =IF(F10=0,0,PMT($B$5/12,60,-F10)) -> 2098.8796 | G13: =IF(G10=0,0,PMT($B$5/12,60,-G10)) -> 2686.9188 | H13: =IF(H10=0,0,PMT($B$5/12,60,-H10)) -> 4093.8018 | I13: =IF(I10=0,0,PMT($B$5/12,60,-I10)) -> 5670.5414 | ... P13: =IF(P10=0,0,PMT($B$5/12,60,-P10)) -> 25225.119 | R13: Five years is the usual shape. It is long enough that the payment comes out of the profit the departing partner helped build, rather than out of the company's working capital.
A14: Or monthly over 7 years | B14: =IF(B10=0,0,PMT($B$5/12,84,-B10)) -> 5.5992916 | C14: =IF(C10=0,0,PMT($B$5/12,84,-C10)) -> 54.47087 | D14: =IF(D10=0,0,PMT($B$5/12,84,-D10)) -> 288.79303 | E14: =IF(E10=0,0,PMT($B$5/12,84,-E10)) -> 1505.3167 | F14: =IF(F10=0,0,PMT($B$5/12,84,-F10)) -> 1623.4419 | G14: =IF(G10=0,0,PMT($B$5/12,84,-G10)) -> 2078.2787 | H14: =IF(H10=0,0,PMT($B$5/12,84,-H10)) -> 3166.4749 | I14: =IF(I10=0,0,PMT($B$5/12,84,-I10)) -> 4386.0519 | ... P14: =IF(P10=0,0,PMT($B$5/12,84,-P10)) -> 19511.132
A15: CAN THE COMPANY ACTUALLY PAY IT?
A16: Operating profit that year | B16: 309346.07 | C16: 298686.24 | D16: 355430.85 | E16: 480212.62 | F16: 471947.32 | G16: 514099.93 | H16: 646151.3 | I16: 785530.44 | J16: 869075.96 | K16: 1029166.3 | L16: 1197070.7 | M16: 1372827.4 | N16: 1556465.4 | O16: 1627343.7 | P16: 1696229.8
A17: Cash in the company at year end | B17: 61038.429 | C17: 120512.93 | D17: 188835.27 | E17: 293220.32 | F17: 408149.24 | G17: 539939.21 | H17: 724549.73 | I17: 964911.91 | J17: 1238692.3 | K17: 1576508.8 | L17: 1981487.1 | M17: 2456768.1 | N17: 3005504.2 | O17: 3596441.7 | P17: 4214933.6
A18: The 5-year payment as a share of that year's profit | B18: =IF(B16=0,0,B13*12/B16) -> 0.00028081512 | C18: =IF(C16=0,0,C13*12/C16) -> 0.0028293137 | D18: =IF(D16=0,0,D13*12/D16) -> 0.012605602 | E18: =IF(E16=0,0,E13*12/E16) -> 0.048632469 | F18: =IF(F16=0,0,F13*12/F16) -> 0.053367302 | G18: =IF(G16=0,0,G13*12/G16) -> 0.062717429 | H18: =IF(H16=0,0,H13*12/H16) -> 0.076028048 | I18: =IF(I16=0,0,I13*12/I16) -> 0.086624901 | ... P18: =IF(P16=0,0,P13*12/P16) -> 0.17845544 | R18: Above roughly 25% and the buyout is eating the business rather than being funded by it. That is the number to argue about, not the headline price.
A19: Could it be paid in cash outright? | B19: =IF(B10=0,"-",IF(B17>=B10,"yes","no - needs a note")) -> yes | C19: =IF(C10=0,"-",IF(C17>=C10,"yes","no - needs a note")) -> yes | D19: =IF(D10=0,"-",IF(D17>=D10,"yes","no - needs a note")) -> yes | E19: =IF(E10=0,"-",IF(E17>=E10,"yes","no - needs a note")) -> yes | F19: =IF(F10=0,"-",IF(F17>=F10,"yes","no - needs a note")) -> yes | G19: =IF(G10=0,"-",IF(G17>=G10,"yes","no - needs a note")) -> yes | H19: =IF(H10=0,"-",IF(H17>=H10,"yes","no - needs a note")) -> yes | I19: =IF(I10=0,"-",IF(I17>=I10,"yes","no - needs a note")) -> yes | ... P19: =IF(P10=0,"-",IF(P17>=P10,"yes","no - needs a note")) -> yes
A21: THE RULES THAT MAKE THIS WORK
A22: 1. The price is a FORMULA, not a negotiation. It is agreed now, in writing, and applied whenever it is needed. Nobody gets to re-open the multiple in the middle of an argument.
A23: 2. The company has the first right to buy. If it declines, the other partners may. If they decline, the stake can be offered outside - with the company holding a right to match.
A24: 3. Payment terms are the company's choice from the options above, but the term may not exceed seven years and the rate may not be below the rate above.
A25: 4. A departure for cause is different: unvested value is forfeited, and vested value is bought at the lower of cost or formula. 'Cause' is defined narrowly on the Obligations tab - not 'we fell out'.
A26: 5. Death or disability is treated as a good-leaver departure at full formula value, paid to the estate on the same terms. Consider funding this with a small term life policy; it costs very little at these ages.
A27: 6. Any dispute over the number goes to the company's CPA, whose determination binds both sides. Two friends have no other way to break a tie, and courts are worse.

Sheet Obligations
A1: What each side owes the other
A2: We are friends, which is exactly why this is written down. Friendship makes the hard conversation more expensive, not less - so the rules get agreed while everyone is comfortable, and there is deliberate slack built into every one of them.
A4: WHAT BRYAN OWES THE COMPANY
A5: The obligation | B5: What it actually means | C5: How we know it is being met
A6: Run the field | B6: Everything after a job is sold: scheduling, dispatch, crews, quality, equipment, purchasing. If it happens on a job site, it is yours. | C6: Weekly operating review. The measure is the baseline set in your first 90 days, improved - not an industry benchmark, because none exists for this work.
A7: Safety, and the competent-person programme | B7: OSHA 29 CFR 1926 Subpart P requires a designated competent person with authority to pull crews out of a trench. Build the programme, own the training records, own the daily inspections. | C7: Designations current, records kept, inspections logged. This one is a legal obligation, not a preference.
A8: Job costing | B8: Every finished job costed against its estimate - labour hours, machine hours, fuel, materials, dump fees - every week. | C8: A weekly job-cost report. Contractors do not fail because they cannot dig; they fail because they bid wrong and find out too late.
A9: Keep the crews | B9: Hire, train and retain foremen and laborers. Turnover is the most expensive line item that never appears on a P&L. | C9: Turnover tracked against the baseline. Construction runs about 4.0% monthly separations against 3.6% for private industry overall.
A10: Full time and undivided | B10: This is the job, not one of the jobs. If the bar has not sold, it is being run by somebody else. | C10: Agreed in writing before the start date, including what happens if the bar takes longer to sell than expected.
A12: WHAT THE COMPANY OWES BRYAN
A13: The obligation | B13: What it actually means | C13: How we know it is being met
A14: Do not overrule you in front of a crew | B14: The single most common way this arrangement fails. If Charlie reverses a decision in front of the men, the crew learns who really decides, and every instruction afterwards routes around you. Disagreements happen away from the crew, every time. | C14: A standing rule, agreed out loud, with the right to call it out when it happens. This one belongs in writing more than anything else on this page.
A15: Written decision rights | B15: Your spending limit, your hiring authority, the discount floor below which pricing comes back to Charlie. Written once, at the start, so disagreements are procedural rather than personal. | C15: A one-page authority schedule, signed. Reviewed annually.
A16: Pay and equity on schedule | B16: Salary on the same day each month. The bonus calculated and paid within 90 days of year end. The equity granted when agreed, papered by an attorney, with the hurdle valued contemporaneously. | C16: Late or undocumented equity is a Step 2 event immediately. A promise of equity that is never papered is not equity.
A17: Let go of the work | B17: Charlie has done every one of these jobs himself for years and the instinct to take them back is muscle memory, not malice. Delegation has to be real, and it has to survive the first time you do something differently than he would. | C17: Reviewed every quarter: what has actually transferred, and what has quietly come back.
A18: Tell you the truth about money | B18: Full access to the numbers you are held accountable for. Nobody can be measured on a figure they are not allowed to see. | C18: Read access to job costing and the monthly P&L from day one.
A20: IF SOMEBODY IS NOT HOLDING UP THEIR END
A21: Stage | B21: What happens | C21: The consequence
A22: Step 1 - Say it out loud | B22: A conversation, in private, naming the specific thing. Not a mood, not a hint, not a comment in front of the crew. Most problems die here and never get further. | C22: No paperwork. No consequence. This step is free and it is the one most often skipped.
A23: Step 2 - Put it in writing | B23: If it is still happening 30 days later: one page, dated, naming the obligation, what was missed, and what fixing it looks like. Both sides sign that they have read it. This is not a disciplinary letter - it is a shared record so that in six months nobody is arguing about what was said. | C23: A signed note in the file. Nothing else changes - no pay cut, no equity change.
A24: Step 3 - A real cure period | B24: 90 days to fix it, with a specific, measurable definition of fixed agreed at the start of the 90 days rather than judged at the end of it. | C24: Reviewed at the end of the 90 days by both parties, in writing.
A25: Step 4 - Consequence | B25: If the same obligation is missed twice in twelve months after a Step 3 cure: vesting pauses until it is corrected. Vesting PAUSES - nothing already earned is taken away. If the miss is on the company's side instead, the partner's notice period shortens and vesting accelerates by the same amount. | C25: The vesting clock stops. It restarts when the cure is confirmed.
A26: Step 5 - Separation, on good terms | B26: Either side may end it on 90 days' written notice, for any reason or none. Everything vested is bought at the formula price on the Buyout tab. This is the normal exit and it is nobody's failure. | C26: Formula price, standard payment terms.
A27: Cause - the narrow exception | B27: Only for the items listed below. Cause requires written notice, a 15-day cure where a cure is possible, and the CPA's concurrence that it qualifies. Unvested value is forfeited and vested value is bought at the lower of cost or formula. | C27: Deliberately hard to invoke. 'We disagree' and 'it is not working' are Step 5, not cause.
A29: WHAT COUNTS AS CAUSE - AND NOTHING ELSE DOES
A30: • | B30: Dishonesty about money - taking it, hiding it, or misreporting it.
A31: • | B31: A wilful safety violation, or falsifying a safety or inspection record. In trench work this is the one that can kill somebody.
A32: • | B32: Working against the company: competing, or soliciting its customers or crews for somebody else.
A33: • | B33: A criminal act that materially damages the business or its reputation.
A34: • | B34: Complete and sustained abandonment of the role.
A35: • | B35: Nothing else. A bad quarter, a wrong call, a clash with Charlie, or growth that did not arrive are NOT cause. They are Step 5, on good terms, at the formula price.
A37: The tiebreaker: any disagreement about whether an obligation has been met goes to the company's CPA. Their call binds both sides. It is not a court, it is not a lawyer, and it costs almost nothing - which is the point.
A39: The slack is deliberate. Two conversations and ninety days before anything at all happens to anyone's money. That is more rope than any employer would give, and it is there because these are friendships first. What the slack is NOT is permission for a problem to go unnamed for a year and then surface as a fight.
A41: None of this is legal drafting. It is the commercial agreement in plain words so that an attorney can paper it quickly and cheaply, and so that both signers actually understand what they signed.
