Workbook

Sheet Assumptions
A1: Scag Scapes LLC - Growth Proforma - Assumptions
A2: Blue = you can change it (yellow = the big levers). Black = formula, locked. Every tab recalculates from this one.
A4: OPERATIONS
A5: Average all-in revenue per linear foot ($/LF) | B5: 50 | C5: Charlie publishes $25-60/LF. $50 is the default because at 900 LF it reproduces Charlie's own rules of thumb: labor ~32% and ~50% margin.
A6: LF per month before Ned - today baseline (french drains only) | B6: 400 | C6: Where Charlie is right now, one crew. Used only to show the before/after - it does not drive the forward plan.
A7: Initial investment - next cash injection into the business ($) | B7: 25000 | C7: Funds launching two full crews together on day one instead of growing into a second crew over time: Crew 2's equipment down payment, hiring and the first months of marketing at full volume. Added to cash once, at the start of month 1. Change this to see what a bigger or smaller injection buys.
A8: Crew 1 - LF installed per month, month 1 | B8: 900 | C8: The plan starts with both crews already at Charlie's 800-1,000 LF/month goal - no ramp. Lower this to model easing in instead.
A9: Revenue per crew-day today ($) - Charlie | B9: 1500 | C9: Charlie: an average job day is about $1,500 of revenue now. The model reproduces this in month 1 (drain days + other-work days); shown as a check in the KPI rows.
A10: Working days per crew per month | B10: 21
A11: LF a crew installs per working day (productivity) | B11: 43 | C11: 900 LF / 21 days. At 400 LF/month a crew is only on drains ~9 days; the rest is other work. Growth = filling every day with drain feet.
A12: Other work revenue per crew-day when not on drains ($) - TODAY ONLY, before Ned | B12: 1000 | C12: Describes Charlie's situation right now, before French-drain volume fills every day - not part of the forward plan, which is drains only.
A13: Crew 1 - LF target per month (reached by month 6) | B13: 900 | C13: Charlie's stated goal (800-1,000).
A14: Crew 2 - start month (1-24) | B14: 1 | C14: Both crews launch together in month 1, funded by the initial investment above. Move this later to phase Crew 2 in instead.
A15: Crew 2 - LF per month, first month | B15: 900 | C15: Crew 2 also starts at target - no ramp, matching Crew 1.
A16: Crew 2 - LF target per month | B16: 900 | C16: Same productivity as Crew 1 once trained.
A17: Average job size (LF) | B17: 100 | C17: Demo average; a 100 LF job at $50/LF = $5,000 all-in.
A18: Backlog customers will wait (months of capacity) - demand beyond this is lost | B18: 1 | C18: A homeowner in a wet yard will wait about a month; past that they call the next company.
A19: COST STRUCTURE (share of install revenue)
A20: Labor cost method (1 = fixed 32% of revenue, 2 = crew wages x hours x burden) | B20: 2 | C20: 2 is the default: labor is what the crew is paid whether it installs 400 LF or 900 LF - that is why productivity is the margin lever. Set 1 to use Charlie's flat 32%.
A21: Direct labor % of revenue (used when method = 1) | B21: 0.32 | C21: Charlie: labor is roughly 32% of project cost.
A22: Materials + fuel % of revenue | B22: 0.2 | C22: Charlie: materials and gas roughly 20%.
A23: Crew wage - average $/hr | B23: 22.5 | C23: Charlie pays $20-25/hr. Change it and every month recalculates (method 2).
A24: Crew lead premium $/hr (added to one person per crew) | B24: 3 | C24: Lead earns $3/hr more than the laborers.
A25: Payroll burden % (taxes, WC, insurance) | B25: 0.14 | C25: Louisiana small-contractor burden estimate; replace with the actual workers' comp rate.
A26: Crew size (people) | B26: 3 | C26: Charlie.
A27: Paid hours per crew member per month | B27: 173 | C27: 40 h/wk x 52 / 12.
A28: Overtime hours per crew member per month | B28: 0 | C28: Paid at 1.5x. Set > 0 in busy months to see the effect.
A29: MAINTENANCE PLAN - 'DRAIN CHECK' (water-jet clean + flow test)
A30: Plan price per visit ($) | B30: 249 | C30: Angi 2026: hydro jetting $350-600 national average $475; priced under market because the crew knows the system it built.
A31: Plan close rate - customers who take a cleaning plan | B31: 0.6 | C31: Charlie's number: about 6 in 10 customers take a cleaning either yearly or every two years. Offered on every quote and again at the warranty walk.
A32: Share of plan customers on a 1-year cleaning (the rest are every 2 years) | B32: 0.5 | C32: Charlie: yearly or every 2 years. Move this and every plan number in the workbook moves.
A33: Cleaning visits per plan customer per year - computed | B33: =$B$32*1+(1-$B$32)*0.5 -> 0.75 | C33: Half on a yearly clean and half every two years averages 0.75 visits a year per customer. Not an input.
A34: Existing customers to offer the plan to (count) | B34: 150 | C34: Charlie to confirm; past installs are the first list.
A35: Existing-customer conversion in year 1 | B35: 0.15 | C35: Assumption; one text + one warranty-walk offer.
A36: Plan start month | B36: 3 | C36: Jetter already owned; needs a script, a price and a text template.
A37: Cost per maintenance visit ($) - 1 tech, 2 hrs, fuel, water | B37: 70 | C37: 1 person x 2 h x $22.50 x 1.18 burden + $17 fuel/consumables.
A38: LONG RANGE AND COMPANY VALUE
A39: Years to show on the long-range tab (1-15) | B39: 10 | C39: Change this to see 1 year or 15. The tab always computes 15; this is what gets summarised.
A40: Crews added per year after year 5 | B40: 0.5 | C40: Half a crew a year = one new crew every two years. The gates still apply: nothing is added until the last crew runs at target.
A41: Most crews one yard and one owner can run | B41: 8 | C41: Past this the answer is a second location or a general manager, which is a different plan.
A42: Long-range price increase per year | B42: 0.03 | C42: Roughly inflation. Applied to $/LF and the plan price from year 3 on.
A43: Plan customers lost per year (churn) | B43: 0.08 | C43: Moves, sells the house, does it himself.
A44: Profit taken out each year - income tax and distributions (% of operating profit) | B44: 0.6 | C44: Pass-through income tax plus what the owner actually takes out on top of the draw. The rest stays in the company as working capital.
A45: Value of equipment owned today ($) | B45: 60000 | C45: Charlie to confirm: trailer, skid steer, mini excavator, truck, jetter and tools at what they would sell for today.
A46: Equipment written off over (years, straight line) | B46: 7 | C46: For book value only - the CPA sets actual depreciation.
A47: Value multiple WITH a recurring service book (x owner cash) | B47: 2.5 | C47: JUDGMENT OVERLAY, not comp-derived - and narrower than it used to be. The transaction data does not support a large recurring-revenue premium at this size: pest control, the most contract-recurring home service there is, sells at 2.04x SDE - BELOW landscaping's 2.30x (BizBuySell, 945 sales). Recurring shows up in the REVENUE multiple (0.96x vs 0.63x), not the earnings multiple. 2.5x is defensible as an upper-quartile outcome for a documented, non-owner-dependent business (landscaping upper quartile is 3.01x), not as proof that plans add half a turn. The real multiple expansion is on the Buyout & exit tab: it comes from getting bigger, not from the plan book.
A48: Value multiple WITHOUT a service book (x owner cash) | B48: 2.1 | C48: Judgment: a pure job shop with no repeating revenue sits at the bottom of the range. Landscaping lower quartile is 1.70x, median 2.30x.
A49: Service contracts also valued at (x annual plan revenue) | B49: 1 | C49: A cross-check on the plan book on its own, the way a buyer of a route or a service contract would price it.
A50: HEADCOUNT RULES (how many people it takes)
A51: Crews per office admin | B51: 2 | C51: One admin can carry the phone, AP/AR and scheduling for about two crews.
A52: Crews per operations manager | B52: 4 | C52: First one hired before Crew 3.
A53: Crews per estimator | B53: 3 | C53: First one hired before Crew 4.
A54: Cleaning visits one technician can do in a year | B54: 900 | C54: About four jetting-and-flow-test visits a day, 225 days a year. The technician's time and fuel are already inside the cost per visit below - this row is only to show how many people it takes.
A55: Office admin salary ($/yr) | B55: 48000
A56: Operations manager salary ($/yr) | B56: 72000
A57: Estimator salary ($/yr, base plus commission) | B57: 58000
A58: CASH TIMING
A59: Deposit % collected at signing | B59: 0.3 | C59: Command sends a 30% deposit link by text at acceptance.
A60: Balance collected in month of completion (%) | B60: 0.9 | C60: Remainder collected in the following month (slow payers).
A61: Materials paid in month of install (%) | B61: 1 | C61: Supplier terms: assume paid same month (no net-30).
A62: Opening cash ($) | B62: 25000 | C62: Charlie to fill in.
A63: MARKETING & LEADS
A64: Google Local Services Ads - monthly budget ($) | B64: 900 | C64: Starts month 1. Drain/sewer LSA CPL $59, book rate 39.5% (SearchLight, Feb 2026).
A65: Google LSA - cost per lead ($) | B65: 59 | C65: SearchLight Feb 2026, drain/sewer category.
A66: Google LSA - leads that become an estimate visit | B66: 0.5 | C66: LSA book rate is 39.5% industry-wide (SearchLight); with 60-second text-back we assume half of leads book a visit.
A67: Facebook + Instagram - monthly budget ($) | B67: 600 | C67: Starts month 2. Meta home-services CPL ~$34; landscaping $45-80 (AdAmigo 2026 via Valley Marketing).
A68: Meta - cost per lead ($) | B68: 55 | C68: Middle of the landscaping range.
A69: Meta - leads that become an estimate visit | B69: 0.3 | C69: Lower intent than search; instant text-back is what gets them to book.
A70: Organic / referral / review leads per month (month 1) | B70: 6 | C70: Charlie's current inbound. Grows with reviews and the referral ask.
A71: Organic lead growth per month (%) | B71: 0.06 | C71: Review flywheel + parish pages + Facebook organic.
A72: Organic / referral - leads that become an estimate visit | B72: 0.65 | C72: Warm leads book easily.
A73: CLOSE RATE - Charlie's number
A74: Close rate on estimates run (quote -> sold job) | B74: 0.7 | C74: Charlie: about 7 of 10 quoted jobs sell. Change this one cell and every channel, the proforma and the scenarios move.
A75: Marketing budget multiplier once Crew 2 starts | B75: 1.6 | C75: Two crews need ~2x the leads; LSA and Meta budgets scale by this from Crew 2's start month.
A76: Content, reviews, GBP, website - monthly ($) | B76: 300 | C76: Photo/video posts, review management, parish pages.
A77: OVERHEAD (monthly)
A78: Owner draw ($) | B78: 12500 | C78: Charlie to set. Default is $150,000/yr - see the Write-offs and taxes tab for how deductions bring taxable profit down from there.
A79: Insurance - GL, auto, equipment ($) | B79: 900 | C79: Estimate; use actual policy.
A80: Existing truck / equipment payments ($) | B80: 1800 | C80: Charlie to fill in.
A81: Software, hosting, phone, Twilio, Stripe fees ($) | B81: 350 | C81: Command hosting $199 + Twilio/Stripe usage.
A82: Bookkeeping / CPA ($) | B82: 250 | C82: Estimate.
A83: Shop, fuel for estimates, tools, misc ($) | B83: 600 | C83: Estimate.
A84: Yard space used at 1655 Cottondale Dr (sq ft) - set 0 if not renting | B84: 2500 | C84: Equipment, trailer and material bins. 2,000-3,000 sq ft fits one crew's set plus pipe and rock; add ~1,000 sq ft per additional crew.
A85: Yard rent rate ($ per sq ft per month) | B85: 0.85 | C85: Introductory offer. Going rate for this type of yard storage in 70815 is about $1.19/sq ft. Change it and every tab moves.
A86: Yard rent - start month (1-24) | B86: 1 | C86: Month the space is first used.
A87: Yard rent per month ($) - computed | B87: =$B$84*$B$85 -> 2125 | C87: Sq ft x rate. Not an input.
A88: Growth & operations lead - Ned (monthly, TBD) | B88: 0 | C88: Left at $0 on purpose - terms to be agreed. Enter a number to see the effect.
A89: CREW 2 EQUIPMENT - rent first, then own (Crew 1 already owns its trailer, skid steer and mini excavator)
A90: Mini excavator (3.5-4 ton, used) - purchase price ($) | B90: 50000 | C90: Used KX040 / 26G class. Crew 1's is owned; Crew 2 needs its own.
A91: Mini excavator - rental per month ($) | B91: 2000 | C91: Home Depot 4-week rate ~$1,700-2,000 (live in the app); Sunbelt/United quote-only.
A92: Mini excavator - months rented before buying | B92: 3 | C92: Rent while Crew 2 proves itself; buy after it hits target twice. 0 = buy at start.
A93: Skid steer / CTL (used) - purchase price ($) | B93: 38000 | C93: Used T66 / 259D class.
A94: Skid steer - rental per month ($) | B94: 1700 | C94: Chain 4-week rate (rate card, CALL_TO_CONFIRM).
A95: Skid steer - months rented before buying | B95: 3
A96: Dump trailer 7x14 (new) - purchase price ($) | B96: 9500 | C96: Trailers rent badly and hold value - buy at start.
A97: Dump trailer - rental per month ($) | B97: 600
A98: Dump trailer - months rented before buying | B98: 0 | C98: 0 = buy at Crew 2 start.
A99: Truck 3/4-ton (used) - purchase price ($) | B99: 35000
A100: Truck - rental per month ($) | B100: 0 | C100: Not rented.
A101: Truck - months rented before buying | B101: 0
...

Sheet Proforma 24 mo
A1: Scag Scapes LLC - 24-month operating proforma ($, monthly)
A2: All cells are formulas driven by the Assumptions tab. Month 1 = first month of the plan.
A4: Month | B4: 1 | C4: 2 | D4: 3 | E4: 4 | F4: 5 | G4: 6 | H4: 7 | I4: 8 | J4: 9 | K4: 10 | L4: 11 | M4: 12 | N4: 13 | O4: 14 | P4: 15 | Q4: 16 | R4: 17 | S4: 18 | T4: 19 | U4: 20 | V4: 21 | W4: 22 | X4: 23 | Y4: 24 | Z4: Year 1 | AA4: Year 2 | AB4: 24-mo total
A5: CAPACITY (linear feet installed)
A6: Crew 1 - LF/month | B6: =MIN(Assumptions!$B$13,Assumptions!$B$8+(Assumptions!$B$13-Assumptions!$B$8)*(1-1)/5) -> 900 | C6: =MIN(Assumptions!$B$13,Assumptions!$B$8+(Assumptions!$B$13-Assumptions!$B$8)*(2-1)/5) -> 900 | D6: =MIN(Assumptions!$B$13,Assumptions!$B$8+(Assumptions!$B$13-Assumptions!$B$8)*(3-1)/5) -> 900 | E6: =MIN(Assumptions!$B$13,Assumptions!$B$8+(Assumptions!$B$13-Assumptions!$B$8)*(4-1)/5) -> 900 | F6: =MIN(Assumptions!$B$13,Assumptions!$B$8+(Assumptions!$B$13-Assumptions!$B$8)*(5-1)/5) -> 900 | G6: =MIN(Assumptions!$B$13,Assumptions!$B$8+(Assumptions!$B$13-Assumptions!$B$8)*(6-1)/5) -> 900 | H6: =MIN(Assumptions!$B$13,Assumptions!$B$8+(Assumptions!$B$13-Assumptions!$B$8)*(7-1)/5) -> 900 | I6: =MIN(Assumptions!$B$13,Assumptions!$B$8+(Assumptions!$B$13-Assumptions!$B$8)*(8-1)/5) -> 900 | J6: =MIN(Assumptions!$B$13,Assumptions!$B$8+(Assumptions!$B$13-Assumptions!$B$8)*(9-1)/5) -> 900 | K6: =MIN(Assumptions!$B$13,Assumptions!$B$8+(Assumptions!$B$13-Assumptions!$B$8)*(10-1)/5) -> 900 | L6: =MIN(Assumptions!$B$13,Assumptions!$B$8+(Assumptions!$B$13-Assumptions!$B$8)*(11-1)/5) -> 900 | M6: =MIN(Assumptions!$B$13,Assumptions!$B$8+(Assumptions!$B$13-Assumptions!$B$8)*(12-1)/5) -> 900 | N6: =MIN(Assumptions!$B$13,Assumptions!$B$8+(Assumptions!$B$13-Assumptions!$B$8)*(13-1)/5) -> 900 | O6: =MIN(Assumptions!$B$13,Assumptions!$B$8+(Assumptions!$B$13-Assumptions!$B$8)*(14-1)/5) -> 900 | P6: =MIN(Assumptions!$B$13,Assumptions!$B$8+(Assumptions!$B$13-Assumptions!$B$8)*(15-1)/5) -> 900 | Q6: =MIN(Assumptions!$B$13,Assumptions!$B$8+(Assumptions!$B$13-Assumptions!$B$8)*(16-1)/5) -> 900 | R6: =MIN(Assumptions!$B$13,Assumptions!$B$8+(Assumptions!$B$13-Assumptions!$B$8)*(17-1)/5) -> 900 | S6: =MIN(Assumptions!$B$13,Assumptions!$B$8+(Assumptions!$B$13-Assumptions!$B$8)*(18-1)/5) -> 900 | T6: =MIN(Assumptions!$B$13,Assumptions!$B$8+(Assumptions!$B$13-Assumptions!$B$8)*(19-1)/5) -> 900 | U6: =MIN(Assumptions!$B$13,Assumptions!$B$8+(Assumptions!$B$13-Assumptions!$B$8)*(20-1)/5) -> 900 | V6: =MIN(Assumptions!$B$13,Assumptions!$B$8+(Assumptions!$B$13-Assumptions!$B$8)*(21-1)/5) -> 900 | W6: =MIN(Assumptions!$B$13,Assumptions!$B$8+(Assumptions!$B$13-Assumptions!$B$8)*(22-1)/5) -> 900 | X6: =MIN(Assumptions!$B$13,Assumptions!$B$8+(Assumptions!$B$13-Assumptions!$B$8)*(23-1)/5) -> 900 | Y6: =MIN(Assumptions!$B$13,Assumptions!$B$8+(Assumptions!$B$13-Assumptions!$B$8)*(24-1)/5) -> 900 | Z6: =SUM(B6:M6) -> 10800 | AA6: =SUM(N6:Y6) -> 10800 | AB6: =SUM(B6:Y6) -> 21600
A7: Crew 2 - LF/month | B7: =IF(1<Assumptions!$B$14,0,MIN(Assumptions!$B$16,Assumptions!$B$15+(Assumptions!$B$16-Assumptions!$B$15)*(1-Assumptions!$B$14)/3)) -> 900 | C7: =IF(2<Assumptions!$B$14,0,MIN(Assumptions!$B$16,Assumptions!$B$15+(Assumptions!$B$16-Assumptions!$B$15)*(2-Assumptions!$B$14)/3)) -> 900 | D7: =IF(3<Assumptions!$B$14,0,MIN(Assumptions!$B$16,Assumptions!$B$15+(Assumptions!$B$16-Assumptions!$B$15)*(3-Assumptions!$B$14)/3)) -> 900 | E7: =IF(4<Assumptions!$B$14,0,MIN(Assumptions!$B$16,Assumptions!$B$15+(Assumptions!$B$16-Assumptions!$B$15)*(4-Assumptions!$B$14)/3)) -> 900 | F7: =IF(5<Assumptions!$B$14,0,MIN(Assumptions!$B$16,Assumptions!$B$15+(Assumptions!$B$16-Assumptions!$B$15)*(5-Assumptions!$B$14)/3)) -> 900 | G7: =IF(6<Assumptions!$B$14,0,MIN(Assumptions!$B$16,Assumptions!$B$15+(Assumptions!$B$16-Assumptions!$B$15)*(6-Assumptions!$B$14)/3)) -> 900 | H7: =IF(7<Assumptions!$B$14,0,MIN(Assumptions!$B$16,Assumptions!$B$15+(Assumptions!$B$16-Assumptions!$B$15)*(7-Assumptions!$B$14)/3)) -> 900 | I7: =IF(8<Assumptions!$B$14,0,MIN(Assumptions!$B$16,Assumptions!$B$15+(Assumptions!$B$16-Assumptions!$B$15)*(8-Assumptions!$B$14)/3)) -> 900 | J7: =IF(9<Assumptions!$B$14,0,MIN(Assumptions!$B$16,Assumptions!$B$15+(Assumptions!$B$16-Assumptions!$B$15)*(9-Assumptions!$B$14)/3)) -> 900 | K7: =IF(10<Assumptions!$B$14,0,MIN(Assumptions!$B$16,Assumptions!$B$15+(Assumptions!$B$16-Assumptions!$B$15)*(10-Assumptions!$B$14)/3)) -> 900 | L7: =IF(11<Assumptions!$B$14,0,MIN(Assumptions!$B$16,Assumptions!$B$15+(Assumptions!$B$16-Assumptions!$B$15)*(11-Assumptions!$B$14)/3)) -> 900 | M7: =IF(12<Assumptions!$B$14,0,MIN(Assumptions!$B$16,Assumptions!$B$15+(Assumptions!$B$16-Assumptions!$B$15)*(12-Assumptions!$B$14)/3)) -> 900 | N7: =IF(13<Assumptions!$B$14,0,MIN(Assumptions!$B$16,Assumptions!$B$15+(Assumptions!$B$16-Assumptions!$B$15)*(13-Assumptions!$B$14)/3)) -> 900 | O7: =IF(14<Assumptions!$B$14,0,MIN(Assumptions!$B$16,Assumptions!$B$15+(Assumptions!$B$16-Assumptions!$B$15)*(14-Assumptions!$B$14)/3)) -> 900 | P7: =IF(15<Assumptions!$B$14,0,MIN(Assumptions!$B$16,Assumptions!$B$15+(Assumptions!$B$16-Assumptions!$B$15)*(15-Assumptions!$B$14)/3)) -> 900 | Q7: =IF(16<Assumptions!$B$14,0,MIN(Assumptions!$B$16,Assumptions!$B$15+(Assumptions!$B$16-Assumptions!$B$15)*(16-Assumptions!$B$14)/3)) -> 900 | R7: =IF(17<Assumptions!$B$14,0,MIN(Assumptions!$B$16,Assumptions!$B$15+(Assumptions!$B$16-Assumptions!$B$15)*(17-Assumptions!$B$14)/3)) -> 900 | S7: =IF(18<Assumptions!$B$14,0,MIN(Assumptions!$B$16,Assumptions!$B$15+(Assumptions!$B$16-Assumptions!$B$15)*(18-Assumptions!$B$14)/3)) -> 900 | T7: =IF(19<Assumptions!$B$14,0,MIN(Assumptions!$B$16,Assumptions!$B$15+(Assumptions!$B$16-Assumptions!$B$15)*(19-Assumptions!$B$14)/3)) -> 900 | U7: =IF(20<Assumptions!$B$14,0,MIN(Assumptions!$B$16,Assumptions!$B$15+(Assumptions!$B$16-Assumptions!$B$15)*(20-Assumptions!$B$14)/3)) -> 900 | V7: =IF(21<Assumptions!$B$14,0,MIN(Assumptions!$B$16,Assumptions!$B$15+(Assumptions!$B$16-Assumptions!$B$15)*(21-Assumptions!$B$14)/3)) -> 900 | W7: =IF(22<Assumptions!$B$14,0,MIN(Assumptions!$B$16,Assumptions!$B$15+(Assumptions!$B$16-Assumptions!$B$15)*(22-Assumptions!$B$14)/3)) -> 900 | X7: =IF(23<Assumptions!$B$14,0,MIN(Assumptions!$B$16,Assumptions!$B$15+(Assumptions!$B$16-Assumptions!$B$15)*(23-Assumptions!$B$14)/3)) -> 900 | Y7: =IF(24<Assumptions!$B$14,0,MIN(Assumptions!$B$16,Assumptions!$B$15+(Assumptions!$B$16-Assumptions!$B$15)*(24-Assumptions!$B$14)/3)) -> 900 | Z7: =SUM(B7:M7) -> 10800 | AA7: =SUM(N7:Y7) -> 10800 | AB7: =SUM(B7:Y7) -> 21600
A8: Capacity - total LF/month | B8: =B6+B7 -> 1800 | C8: =C6+C7 -> 1800 | D8: =D6+D7 -> 1800 | E8: =E6+E7 -> 1800 | F8: =F6+F7 -> 1800 | G8: =G6+G7 -> 1800 | H8: =H6+H7 -> 1800 | I8: =I6+I7 -> 1800 | ... Y8: =Y6+Y7 -> 1800 | Z8: =SUM(B8:M8) -> 21600 | AA8: =SUM(N8:Y8) -> 21600 | AB8: =SUM(B8:Y8) -> 43200
A9: DEMAND (leads and jobs)
A10: Leads - Google LSA | B10: =Assumptions!$B$64*IF(1>=Assumptions!$B$14,Assumptions!$B$75,1)/Assumptions!$B$65 -> 24.40678 | C10: =Assumptions!$B$64*IF(2>=Assumptions!$B$14,Assumptions!$B$75,1)/Assumptions!$B$65 -> 24.40678 | D10: =Assumptions!$B$64*IF(3>=Assumptions!$B$14,Assumptions!$B$75,1)/Assumptions!$B$65 -> 24.40678 | E10: =Assumptions!$B$64*IF(4>=Assumptions!$B$14,Assumptions!$B$75,1)/Assumptions!$B$65 -> 24.40678 | F10: =Assumptions!$B$64*IF(5>=Assumptions!$B$14,Assumptions!$B$75,1)/Assumptions!$B$65 -> 24.40678 | G10: =Assumptions!$B$64*IF(6>=Assumptions!$B$14,Assumptions!$B$75,1)/Assumptions!$B$65 -> 24.40678 | H10: =Assumptions!$B$64*IF(7>=Assumptions!$B$14,Assumptions!$B$75,1)/Assumptions!$B$65 -> 24.40678 | I10: =Assumptions!$B$64*IF(8>=Assumptions!$B$14,Assumptions!$B$75,1)/Assumptions!$B$65 -> 24.40678 | J10: =Assumptions!$B$64*IF(9>=Assumptions!$B$14,Assumptions!$B$75,1)/Assumptions!$B$65 -> 24.40678 | K10: =Assumptions!$B$64*IF(10>=Assumptions!$B$14,Assumptions!$B$75,1)/Assumptions!$B$65 -> 24.40678 | L10: =Assumptions!$B$64*IF(11>=Assumptions!$B$14,Assumptions!$B$75,1)/Assumptions!$B$65 -> 24.40678 | M10: =Assumptions!$B$64*IF(12>=Assumptions!$B$14,Assumptions!$B$75,1)/Assumptions!$B$65 -> 24.40678 | N10: =Assumptions!$B$64*IF(13>=Assumptions!$B$14,Assumptions!$B$75,1)/Assumptions!$B$65 -> 24.40678 | O10: =Assumptions!$B$64*IF(14>=Assumptions!$B$14,Assumptions!$B$75,1)/Assumptions!$B$65 -> 24.40678 | P10: =Assumptions!$B$64*IF(15>=Assumptions!$B$14,Assumptions!$B$75,1)/Assumptions!$B$65 -> 24.40678 | Q10: =Assumptions!$B$64*IF(16>=Assumptions!$B$14,Assumptions!$B$75,1)/Assumptions!$B$65 -> 24.40678 | R10: =Assumptions!$B$64*IF(17>=Assumptions!$B$14,Assumptions!$B$75,1)/Assumptions!$B$65 -> 24.40678 | S10: =Assumptions!$B$64*IF(18>=Assumptions!$B$14,Assumptions!$B$75,1)/Assumptions!$B$65 -> 24.40678 | T10: =Assumptions!$B$64*IF(19>=Assumptions!$B$14,Assumptions!$B$75,1)/Assumptions!$B$65 -> 24.40678 | U10: =Assumptions!$B$64*IF(20>=Assumptions!$B$14,Assumptions!$B$75,1)/Assumptions!$B$65 -> 24.40678 | V10: =Assumptions!$B$64*IF(21>=Assumptions!$B$14,Assumptions!$B$75,1)/Assumptions!$B$65 -> 24.40678 | W10: =Assumptions!$B$64*IF(22>=Assumptions!$B$14,Assumptions!$B$75,1)/Assumptions!$B$65 -> 24.40678 | X10: =Assumptions!$B$64*IF(23>=Assumptions!$B$14,Assumptions!$B$75,1)/Assumptions!$B$65 -> 24.40678 | Y10: =Assumptions!$B$64*IF(24>=Assumptions!$B$14,Assumptions!$B$75,1)/Assumptions!$B$65 -> 24.40678 | Z10: =SUM(B10:M10) -> 292.88136 | AA10: =SUM(N10:Y10) -> 292.88136 | AB10: =SUM(B10:Y10) -> 585.76271
A11: Leads - Facebook / Instagram | B11: =IF(1>=2,Assumptions!$B$67*IF(1>=Assumptions!$B$14,Assumptions!$B$75,1)/Assumptions!$B$68,0) -> 0 | C11: =IF(2>=2,Assumptions!$B$67*IF(2>=Assumptions!$B$14,Assumptions!$B$75,1)/Assumptions!$B$68,0) -> 17.454545 | D11: =IF(3>=2,Assumptions!$B$67*IF(3>=Assumptions!$B$14,Assumptions!$B$75,1)/Assumptions!$B$68,0) -> 17.454545 | E11: =IF(4>=2,Assumptions!$B$67*IF(4>=Assumptions!$B$14,Assumptions!$B$75,1)/Assumptions!$B$68,0) -> 17.454545 | F11: =IF(5>=2,Assumptions!$B$67*IF(5>=Assumptions!$B$14,Assumptions!$B$75,1)/Assumptions!$B$68,0) -> 17.454545 | G11: =IF(6>=2,Assumptions!$B$67*IF(6>=Assumptions!$B$14,Assumptions!$B$75,1)/Assumptions!$B$68,0) -> 17.454545 | H11: =IF(7>=2,Assumptions!$B$67*IF(7>=Assumptions!$B$14,Assumptions!$B$75,1)/Assumptions!$B$68,0) -> 17.454545 | I11: =IF(8>=2,Assumptions!$B$67*IF(8>=Assumptions!$B$14,Assumptions!$B$75,1)/Assumptions!$B$68,0) -> 17.454545 | J11: =IF(9>=2,Assumptions!$B$67*IF(9>=Assumptions!$B$14,Assumptions!$B$75,1)/Assumptions!$B$68,0) -> 17.454545 | K11: =IF(10>=2,Assumptions!$B$67*IF(10>=Assumptions!$B$14,Assumptions!$B$75,1)/Assumptions!$B$68,0) -> 17.454545 | L11: =IF(11>=2,Assumptions!$B$67*IF(11>=Assumptions!$B$14,Assumptions!$B$75,1)/Assumptions!$B$68,0) -> 17.454545 | M11: =IF(12>=2,Assumptions!$B$67*IF(12>=Assumptions!$B$14,Assumptions!$B$75,1)/Assumptions!$B$68,0) -> 17.454545 | N11: =IF(13>=2,Assumptions!$B$67*IF(13>=Assumptions!$B$14,Assumptions!$B$75,1)/Assumptions!$B$68,0) -> 17.454545 | O11: =IF(14>=2,Assumptions!$B$67*IF(14>=Assumptions!$B$14,Assumptions!$B$75,1)/Assumptions!$B$68,0) -> 17.454545 | P11: =IF(15>=2,Assumptions!$B$67*IF(15>=Assumptions!$B$14,Assumptions!$B$75,1)/Assumptions!$B$68,0) -> 17.454545 | Q11: =IF(16>=2,Assumptions!$B$67*IF(16>=Assumptions!$B$14,Assumptions!$B$75,1)/Assumptions!$B$68,0) -> 17.454545 | R11: =IF(17>=2,Assumptions!$B$67*IF(17>=Assumptions!$B$14,Assumptions!$B$75,1)/Assumptions!$B$68,0) -> 17.454545 | S11: =IF(18>=2,Assumptions!$B$67*IF(18>=Assumptions!$B$14,Assumptions!$B$75,1)/Assumptions!$B$68,0) -> 17.454545 | T11: =IF(19>=2,Assumptions!$B$67*IF(19>=Assumptions!$B$14,Assumptions!$B$75,1)/Assumptions!$B$68,0) -> 17.454545 | U11: =IF(20>=2,Assumptions!$B$67*IF(20>=Assumptions!$B$14,Assumptions!$B$75,1)/Assumptions!$B$68,0) -> 17.454545 | V11: =IF(21>=2,Assumptions!$B$67*IF(21>=Assumptions!$B$14,Assumptions!$B$75,1)/Assumptions!$B$68,0) -> 17.454545 | W11: =IF(22>=2,Assumptions!$B$67*IF(22>=Assumptions!$B$14,Assumptions!$B$75,1)/Assumptions!$B$68,0) -> 17.454545 | X11: =IF(23>=2,Assumptions!$B$67*IF(23>=Assumptions!$B$14,Assumptions!$B$75,1)/Assumptions!$B$68,0) -> 17.454545 | Y11: =IF(24>=2,Assumptions!$B$67*IF(24>=Assumptions!$B$14,Assumptions!$B$75,1)/Assumptions!$B$68,0) -> 17.454545 | Z11: =SUM(B11:M11) -> 192 | AA11: =SUM(N11:Y11) -> 209.45455 | AB11: =SUM(B11:Y11) -> 401.45455
A12: Leads - organic, referral, reviews, rain trigger | B12: =Assumptions!$B$70*(1+Assumptions!$B$71)^(1-1) -> 6 | C12: =Assumptions!$B$70*(1+Assumptions!$B$71)^(2-1) -> 6.36 | D12: =Assumptions!$B$70*(1+Assumptions!$B$71)^(3-1) -> 6.7416 | E12: =Assumptions!$B$70*(1+Assumptions!$B$71)^(4-1) -> 7.146096 | F12: =Assumptions!$B$70*(1+Assumptions!$B$71)^(5-1) -> 7.5748618 | G12: =Assumptions!$B$70*(1+Assumptions!$B$71)^(6-1) -> 8.0293535 | H12: =Assumptions!$B$70*(1+Assumptions!$B$71)^(7-1) -> 8.5111147 | I12: =Assumptions!$B$70*(1+Assumptions!$B$71)^(8-1) -> 9.0217816 | J12: =Assumptions!$B$70*(1+Assumptions!$B$71)^(9-1) -> 9.5630884 | K12: =Assumptions!$B$70*(1+Assumptions!$B$71)^(10-1) -> 10.136874 | L12: =Assumptions!$B$70*(1+Assumptions!$B$71)^(11-1) -> 10.745086 | M12: =Assumptions!$B$70*(1+Assumptions!$B$71)^(12-1) -> 11.389791 | N12: =Assumptions!$B$70*(1+Assumptions!$B$71)^(13-1) -> 12.073179 | O12: =Assumptions!$B$70*(1+Assumptions!$B$71)^(14-1) -> 12.79757 | P12: =Assumptions!$B$70*(1+Assumptions!$B$71)^(15-1) -> 13.565424 | Q12: =Assumptions!$B$70*(1+Assumptions!$B$71)^(16-1) -> 14.379349 | R12: =Assumptions!$B$70*(1+Assumptions!$B$71)^(17-1) -> 15.24211 | S12: =Assumptions!$B$70*(1+Assumptions!$B$71)^(18-1) -> 16.156637 | T12: =Assumptions!$B$70*(1+Assumptions!$B$71)^(19-1) -> 17.126035 | U12: =Assumptions!$B$70*(1+Assumptions!$B$71)^(20-1) -> 18.153597 | V12: =Assumptions!$B$70*(1+Assumptions!$B$71)^(21-1) -> 19.242813 | W12: =Assumptions!$B$70*(1+Assumptions!$B$71)^(22-1) -> 20.397382 | X12: =Assumptions!$B$70*(1+Assumptions!$B$71)^(23-1) -> 21.621224 | Y12: =Assumptions!$B$70*(1+Assumptions!$B$71)^(24-1) -> 22.918498 | Z12: =SUM(B12:M12) -> 101.21965 | AA12: =SUM(N12:Y12) -> 203.67382 | AB12: =SUM(B12:Y12) -> 304.89346
A13: Total leads | B13: =B10+B11+B12 -> 30.40678 | C13: =C10+C11+C12 -> 48.221325 | D13: =D10+D11+D12 -> 48.602925 | E13: =E10+E11+E12 -> 49.007421 | F13: =F10+F11+F12 -> 49.436187 | G13: =G10+G11+G12 -> 49.890679 | H13: =H10+H11+H12 -> 50.37244 | I13: =I10+I11+I12 -> 50.883107 | ... Y13: =Y10+Y11+Y12 -> 64.779823 | Z13: =SUM(B13:M13) -> 586.101 | AA13: =SUM(N13:Y13) -> 706.00972 | AB13: =SUM(B13:Y13) -> 1292.1107
A14: Estimate visits booked (leads x booking rate by channel) | B14: =B10*Assumptions!$B$66+B11*Assumptions!$B$69+B12*Assumptions!$B$72 -> 16.10339 | C14: =C10*Assumptions!$B$66+C11*Assumptions!$B$69+C12*Assumptions!$B$72 -> 21.573753 | D14: =D10*Assumptions!$B$66+D11*Assumptions!$B$69+D12*Assumptions!$B$72 -> 21.821793 | E14: =E10*Assumptions!$B$66+E11*Assumptions!$B$69+E12*Assumptions!$B$72 -> 22.084716 | F14: =F10*Assumptions!$B$66+F11*Assumptions!$B$69+F12*Assumptions!$B$72 -> 22.363414 | G14: =G10*Assumptions!$B$66+G11*Assumptions!$B$69+G12*Assumptions!$B$72 -> 22.658833 | H14: =H10*Assumptions!$B$66+H11*Assumptions!$B$69+H12*Assumptions!$B$72 -> 22.971978 | I14: =I10*Assumptions!$B$66+I11*Assumptions!$B$69+I12*Assumptions!$B$72 -> 23.303911 | ... Y14: =Y10*Assumptions!$B$66+Y11*Assumptions!$B$69+Y12*Assumptions!$B$72 -> 32.336777 | Z14: =SUM(B14:M14) -> 269.83345 | AA14: =SUM(N14:Y14) -> 341.66502 | AB14: =SUM(B14:Y14) -> 611.49847
A15: Jobs sold (estimates x Charlie's close rate) | B15: =B14*Assumptions!$B$74 -> 11.272373 | C15: =C14*Assumptions!$B$74 -> 15.101627 | D15: =D14*Assumptions!$B$74 -> 15.275255 | E15: =E14*Assumptions!$B$74 -> 15.459301 | F15: =F14*Assumptions!$B$74 -> 15.65439 | G15: =G14*Assumptions!$B$74 -> 15.861183 | H15: =H14*Assumptions!$B$74 -> 16.080385 | I15: =I14*Assumptions!$B$74 -> 16.312738 | ... Y15: =Y14*Assumptions!$B$74 -> 22.635744 | Z15: =SUM(B15:M15) -> 188.88341 | AA15: =SUM(N15:Y15) -> 239.16552 | AB15: =SUM(B15:Y15) -> 428.04893
A16: LF demanded (jobs x average job LF) | B16: =B15*Assumptions!$B$17 -> 1127.2373 | C16: =C15*Assumptions!$B$17 -> 1510.1627 | D16: =D15*Assumptions!$B$17 -> 1527.5255 | E16: =E15*Assumptions!$B$17 -> 1545.9301 | F16: =F15*Assumptions!$B$17 -> 1565.439 | G16: =G15*Assumptions!$B$17 -> 1586.1183 | H16: =H15*Assumptions!$B$17 -> 1608.0385 | I16: =I15*Assumptions!$B$17 -> 1631.2738 | ... Y16: =Y15*Assumptions!$B$17 -> 2263.5744 | Z16: =SUM(B16:M16) -> 18888.341 | AA16: =SUM(N16:Y16) -> 23916.552 | AB16: =SUM(B16:Y16) -> 42804.893
A17: LF installed (lesser of demand + backlog, capacity) | B17: =MIN(B16+0,B8) -> 1127.2373 | C17: =MIN(C16+B18,C8) -> 1510.1627 | D17: =MIN(D16+C18,D8) -> 1527.5255 | E17: =MIN(E16+D18,E8) -> 1545.9301 | F17: =MIN(F16+E18,F8) -> 1565.439 | G17: =MIN(G16+F18,G8) -> 1586.1183 | H17: =MIN(H16+G18,H8) -> 1608.0385 | I17: =MIN(I16+H18,I8) -> 1631.2738 | J17: =MIN(J16+I18,J8) -> 1655.9033 | ... Y17: =MIN(Y16+X18,Y8) -> 1800 | Z17: =SUM(B17:M17) -> 18888.341 | AA17: =SUM(N17:Y17) -> 21570.112 | AB17: =SUM(B17:Y17) -> 40458.454
A18: Backlog carried to next month (LF, capped; excess is lost demand) | B18: =MIN(B8*Assumptions!$B$18,MAX(0,B16+0-B17)) -> 0 | C18: =MIN(C8*Assumptions!$B$18,MAX(0,C16+B18-C17)) -> 0 | D18: =MIN(D8*Assumptions!$B$18,MAX(0,D16+C18-D17)) -> 0 | E18: =MIN(E8*Assumptions!$B$18,MAX(0,E16+D18-E17)) -> 0 | F18: =MIN(F8*Assumptions!$B$18,MAX(0,F16+E18-F17)) -> 0 | G18: =MIN(G8*Assumptions!$B$18,MAX(0,G16+F18-G17)) -> 0 | H18: =MIN(H8*Assumptions!$B$18,MAX(0,H16+G18-H17)) -> 0 | I18: =MIN(I8*Assumptions!$B$18,MAX(0,I16+H18-I17)) -> 0 | J18: =MIN(J8*Assumptions!$B$18,MAX(0,J16+I18-J17)) -> 0 | ... Y18: =MIN(Y8*Assumptions!$B$18,MAX(0,Y16+X18-Y17)) -> 1800
A19: Crew utilization | B19: =IF(B8=0,0,B17/B8) -> 0.62624294 | C19: =IF(C8=0,0,C17/C8) -> 0.8389793 | D19: =IF(D8=0,0,D17/D8) -> 0.8486253 | E19: =IF(E8=0,0,E17/E8) -> 0.85885006 | F19: =IF(F8=0,0,F17/F8) -> 0.86968831 | G19: =IF(G8=0,0,G17/G8) -> 0.88117685 | H19: =IF(H8=0,0,H17/H8) -> 0.8933547 | I19: =IF(I8=0,0,I17/I8) -> 0.90626322 | ... Y19: =IF(Y8=0,0,Y17/Y8) -> 1
A20: REVENUE
A21: Crew-days on drains (LF / LF per day) | B21: =B17/Assumptions!$B$11 -> 26.214821 | C21: =C17/Assumptions!$B$11 -> 35.120064 | D21: =D17/Assumptions!$B$11 -> 35.52385 | E21: =E17/Assumptions!$B$11 -> 35.951863 | F21: =F17/Assumptions!$B$11 -> 36.405557 | G21: =G17/Assumptions!$B$11 -> 36.886473 | H21: =H17/Assumptions!$B$11 -> 37.396243 | I21: =I17/Assumptions!$B$11 -> 37.9366 | ... Y21: =Y17/Assumptions!$B$11 -> 41.860465
A22: Drainage revenue (LF installed x $/LF) | B22: =B17*Assumptions!$B$5 -> 56361.864 | C22: =C17*Assumptions!$B$5 -> 75508.137 | D22: =D17*Assumptions!$B$5 -> 76376.277 | E22: =E17*Assumptions!$B$5 -> 77296.506 | F22: =F17*Assumptions!$B$5 -> 78271.948 | G22: =G17*Assumptions!$B$5 -> 79305.916 | H22: =H17*Assumptions!$B$5 -> 80401.923 | I22: =I17*Assumptions!$B$5 -> 81563.69 | ... Y22: =Y17*Assumptions!$B$5 -> 90000 | Z22: =SUM(B22:M22) -> 944417.07 | AA22: =SUM(N22:Y22) -> 1078505.6 | AB22: =SUM(B22:Y22) -> 2022922.7
A23: Install revenue (french drains only) | B23: =B22 -> 56361.864 | C23: =C22 -> 75508.137 | D23: =D22 -> 76376.277 | E23: =E22 -> 77296.506 | F23: =F22 -> 78271.948 | G23: =G22 -> 79305.916 | H23: =H22 -> 80401.923 | I23: =I22 -> 81563.69 | ... Y23: =Y22 -> 90000 | Z23: =SUM(B23:M23) -> 944417.07 | AA23: =SUM(N23:Y23) -> 1078505.6 | AB23: =SUM(B23:Y23) -> 2022922.7
A24: New Drain Check plans sold (count) | B24: =IF(1<Assumptions!$B$36,0,B17/Assumptions!$B$17*Assumptions!$B$31+IF(1<=Assumptions!$B$36+11,Assumptions!$B$34*Assumptions!$B$35/12,0)) -> 0 | C24: =IF(2<Assumptions!$B$36,0,C17/Assumptions!$B$17*Assumptions!$B$31+IF(2<=Assumptions!$B$36+11,Assumptions!$B$34*Assumptions!$B$35/12,0)) -> 0 | D24: =IF(3<Assumptions!$B$36,0,D17/Assumptions!$B$17*Assumptions!$B$31+IF(3<=Assumptions!$B$36+11,Assumptions!$B$34*Assumptions!$B$35/12,0)) -> 11.040153 | E24: =IF(4<Assumptions!$B$36,0,E17/Assumptions!$B$17*Assumptions!$B$31+IF(4<=Assumptions!$B$36+11,Assumptions!$B$34*Assumptions!$B$35/12,0)) -> 11.150581 | F24: =IF(5<Assumptions!$B$36,0,F17/Assumptions!$B$17*Assumptions!$B$31+IF(5<=Assumptions!$B$36+11,Assumptions!$B$34*Assumptions!$B$35/12,0)) -> 11.267634 | G24: =IF(6<Assumptions!$B$36,0,G17/Assumptions!$B$17*Assumptions!$B$31+IF(6<=Assumptions!$B$36+11,Assumptions!$B$34*Assumptions!$B$35/12,0)) -> 11.39171 | H24: =IF(7<Assumptions!$B$36,0,H17/Assumptions!$B$17*Assumptions!$B$31+IF(7<=Assumptions!$B$36+11,Assumptions!$B$34*Assumptions!$B$35/12,0)) -> 11.523231 | I24: =IF(8<Assumptions!$B$36,0,I17/Assumptions!$B$17*Assumptions!$B$31+IF(8<=Assumptions!$B$36+11,Assumptions!$B$34*Assumptions!$B$35/12,0)) -> 11.662643 | J24: =IF(9<Assumptions!$B$36,0,J17/Assumptions!$B$17*Assumptions!$B$31+IF(9<=Assumptions!$B$36+11,Assumptions!$B$34*Assumptions!$B$35/12,0)) -> 11.81042 | K24: =IF(10<Assumptions!$B$36,0,K17/Assumptions!$B$17*Assumptions!$B$31+IF(10<=Assumptions!$B$36+11,Assumptions!$B$34*Assumptions!$B$35/12,0)) -> 11.967063 | L24: =IF(11<Assumptions!$B$36,0,L17/Assumptions!$B$17*Assumptions!$B$31+IF(11<=Assumptions!$B$36+11,Assumptions!$B$34*Assumptions!$B$35/12,0)) -> 12.133105 | M24: =IF(12<Assumptions!$B$36,0,M17/Assumptions!$B$17*Assumptions!$B$31+IF(12<=Assumptions!$B$36+11,Assumptions!$B$34*Assumptions!$B$35/12,0)) -> 12.309109 | N24: =IF(13<Assumptions!$B$36,0,N17/Assumptions!$B$17*Assumptions!$B$31+IF(13<=Assumptions!$B$36+11,Assumptions!$B$34*Assumptions!$B$35/12,0)) -> 12.495674 | O24: =IF(14<Assumptions!$B$36,0,O17/Assumptions!$B$17*Assumptions!$B$31+IF(14<=Assumptions!$B$36+11,Assumptions!$B$34*Assumptions!$B$35/12,0)) -> 12.675 | P24: =IF(15<Assumptions!$B$36,0,P17/Assumptions!$B$17*Assumptions!$B$31+IF(15<=Assumptions!$B$36+11,Assumptions!$B$34*Assumptions!$B$35/12,0)) -> 10.8 | Q24: =IF(16<Assumptions!$B$36,0,Q17/Assumptions!$B$17*Assumptions!$B$31+IF(16<=Assumptions!$B$36+11,Assumptions!$B$34*Assumptions!$B$35/12,0)) -> 10.8 | R24: =IF(17<Assumptions!$B$36,0,R17/Assumptions!$B$17*Assumptions!$B$31+IF(17<=Assumptions!$B$36+11,Assumptions!$B$34*Assumptions!$B$35/12,0)) -> 10.8 | S24: =IF(18<Assumptions!$B$36,0,S17/Assumptions!$B$17*Assumptions!$B$31+IF(18<=Assumptions!$B$36+11,Assumptions!$B$34*Assumptions!$B$35/12,0)) -> 10.8 | T24: =IF(19<Assumptions!$B$36,0,T17/Assumptions!$B$17*Assumptions!$B$31+IF(19<=Assumptions!$B$36+11,Assumptions!$B$34*Assumptions!$B$35/12,0)) -> 10.8 | U24: =IF(20<Assumptions!$B$36,0,U17/Assumptions!$B$17*Assumptions!$B$31+IF(20<=Assumptions!$B$36+11,Assumptions!$B$34*Assumptions!$B$35/12,0)) -> 10.8 | V24: =IF(21<Assumptions!$B$36,0,V17/Assumptions!$B$17*Assumptions!$B$31+IF(21<=Assumptions!$B$36+11,Assumptions!$B$34*Assumptions!$B$35/12,0)) -> 10.8 | W24: =IF(22<Assumptions!$B$36,0,W17/Assumptions!$B$17*Assumptions!$B$31+IF(22<=Assumptions!$B$36+11,Assumptions!$B$34*Assumptions!$B$35/12,0)) -> 10.8 | X24: =IF(23<Assumptions!$B$36,0,X17/Assumptions!$B$17*Assumptions!$B$31+IF(23<=Assumptions!$B$36+11,Assumptions!$B$34*Assumptions!$B$35/12,0)) -> 10.8 | Y24: =IF(24<Assumptions!$B$36,0,Y17/Assumptions!$B$17*Assumptions!$B$31+IF(24<=Assumptions!$B$36+11,Assumptions!$B$34*Assumptions!$B$35/12,0)) -> 10.8 | Z24: =SUM(B24:M24) -> 116.25565 | AA24: =SUM(N24:Y24) -> 133.17067 | AB24: =SUM(B24:Y24) -> 249.42632
A25: Active plans (cumulative, less 8%/yr churn) | B25: =0+B24 -> 0 | C25: =B25*(1-0.08/12)+C24 -> 0 | D25: =C25*(1-0.08/12)+D24 -> 11.040153 | E25: =D25*(1-0.08/12)+E24 -> 22.117133 | F25: =E25*(1-0.08/12)+F24 -> 33.237319 | G25: =F25*(1-0.08/12)+G24 -> 44.407447 | H25: =G25*(1-0.08/12)+H24 -> 55.634628 | I25: =H25*(1-0.08/12)+I24 -> 66.926373 | J25: =I25*(1-0.08/12)+J24 -> 78.290617 | ... Y25: =X25*(1-0.08/12)+Y24 -> 232.47726
A26: Maintenance revenue (visits billed this month) | B26: =B25/12*Assumptions!$B$33*Assumptions!$B$30 -> 0 | C26: =C25/12*Assumptions!$B$33*Assumptions!$B$30 -> 0 | D26: =D25/12*Assumptions!$B$33*Assumptions!$B$30 -> 171.81239 | E26: =E25/12*Assumptions!$B$33*Assumptions!$B$30 -> 344.19788 | F26: =F25/12*Assumptions!$B$33*Assumptions!$B$30 -> 517.25578 | G26: =G25/12*Assumptions!$B$33*Assumptions!$B$30 -> 691.09089 | H26: =H25/12*Assumptions!$B$33*Assumptions!$B$30 -> 865.8139 | I26: =I25/12*Assumptions!$B$33*Assumptions!$B$30 -> 1041.5417 | ... Y26: =Y25/12*Assumptions!$B$33*Assumptions!$B$30 -> 3617.9273 | Z26: =SUM(B26:M26) -> 9579.7241 | AA26: =SUM(N26:Y26) -> 33603.68 | AB26: =SUM(B26:Y26) -> 43183.404
A27: TOTAL REVENUE | B27: =B23+B26 -> 56361.864 | C27: =C23+C26 -> 75508.137 | D27: =D23+D26 -> 76548.09 | E27: =E23+E26 -> 77640.703 | F27: =F23+F26 -> 78789.203 | G27: =G23+G26 -> 79997.007 | H27: =H23+H26 -> 81267.737 | I27: =I23+I26 -> 82605.232 | ... Y27: =Y23+Y26 -> 93617.927 | Z27: =SUM(B27:M27) -> 953996.79 | AA27: =SUM(N27:Y27) -> 1112109.3 | AB27: =SUM(B27:Y27) -> 2066106.1
A28: DIRECT COSTS
A29: Crews active | B29: =1+IF(B7>0,1,0) -> 2 | C29: =1+IF(C7>0,1,0) -> 2 | D29: =1+IF(D7>0,1,0) -> 2 | E29: =1+IF(E7>0,1,0) -> 2 | F29: =1+IF(F7>0,1,0) -> 2 | G29: =1+IF(G7>0,1,0) -> 2 | H29: =1+IF(H7>0,1,0) -> 2 | I29: =1+IF(I7>0,1,0) -> 2 | ... Y29: =1+IF(Y7>0,1,0) -> 2
A30: Crew labor (method 2: crews x wages x hours x burden; method 1: 32% of revenue) | B30: =IF(Assumptions!$B$20=1,B23*Assumptions!$B$21,B29*(Assumptions!$B$26*Assumptions!$B$27*Assumptions!$B$23+Assumptions!$B$27*Assumptions!$B$24+Assumptions!$B$26*Assumptions!$B$28*Assumptions!$B$23*1.5)*(1+Assumptions!$B$25)) -> 27808.02 | C30: =IF(Assumptions!$B$20=1,C23*Assumptions!$B$21,C29*(Assumptions!$B$26*Assumptions!$B$27*Assumptions!$B$23+Assumptions!$B$27*Assumptions!$B$24+Assumptions!$B$26*Assumptions!$B$28*Assumptions!$B$23*1.5)*(1+Assumptions!$B$25)) -> 27808.02 | D30: =IF(Assumptions!$B$20=1,D23*Assumptions!$B$21,D29*(Assumptions!$B$26*Assumptions!$B$27*Assumptions!$B$23+Assumptions!$B$27*Assumptions!$B$24+Assumptions!$B$26*Assumptions!$B$28*Assumptions!$B$23*1.5)*(1+Assumptions!$B$25)) -> 27808.02 | E30: =IF(Assumptions!$B$20=1,E23*Assumptions!$B$21,E29*(Assumptions!$B$26*Assumptions!$B$27*Assumptions!$B$23+Assumptions!$B$27*Assumptions!$B$24+Assumptions!$B$26*Assumptions!$B$28*Assumptions!$B$23*1.5)*(1+Assumptions!$B$25)) -> 27808.02 | F30: =IF(Assumptions!$B$20=1,F23*Assumptions!$B$21,F29*(Assumptions!$B$26*Assumptions!$B$27*Assumptions!$B$23+Assumptions!$B$27*Assumptions!$B$24+Assumptions!$B$26*Assumptions!$B$28*Assumptions!$B$23*1.5)*(1+Assumptions!$B$25)) -> 27808.02 | G30: =IF(Assumptions!$B$20=1,G23*Assumptions!$B$21,G29*(Assumptions!$B$26*Assumptions!$B$27*Assumptions!$B$23+Assumptions!$B$27*Assumptions!$B$24+Assumptions!$B$26*Assumptions!$B$28*Assumptions!$B$23*1.5)*(1+Assumptions!$B$25)) -> 27808.02 | H30: =IF(Assumptions!$B$20=1,H23*Assumptions!$B$21,H29*(Assumptions!$B$26*Assumptions!$B$27*Assumptions!$B$23+Assumptions!$B$27*Assumptions!$B$24+Assumptions!$B$26*Assumptions!$B$28*Assumptions!$B$23*1.5)*(1+Assumptions!$B$25)) -> 27808.02 | I30: =IF(Assumptions!$B$20=1,I23*Assumptions!$B$21,I29*(Assumptions!$B$26*Assumptions!$B$27*Assumptions!$B$23+Assumptions!$B$27*Assumptions!$B$24+Assumptions!$B$26*Assumptions!$B$28*Assumptions!$B$23*1.5)*(1+Assumptions!$B$25)) -> 27808.02 | ... Y30: =IF(Assumptions!$B$20=1,Y23*Assumptions!$B$21,Y29*(Assumptions!$B$26*Assumptions!$B$27*Assumptions!$B$23+Assumptions!$B$27*Assumptions!$B$24+Assumptions!$B$26*Assumptions!$B$28*Assumptions!$B$23*1.5)*(1+Assumptions!$B$25)) -> 27808.02 | Z30: =SUM(B30:M30) -> 333696.24 | AA30: =SUM(N30:Y30) -> 333696.24 | AB30: =SUM(B30:Y30) -> 667392.48
A31: Materials + fuel (20% of install revenue) | B31: =B23*Assumptions!$B$22 -> 11272.373 | C31: =C23*Assumptions!$B$22 -> 15101.627 | D31: =D23*Assumptions!$B$22 -> 15275.255 | E31: =E23*Assumptions!$B$22 -> 15459.301 | F31: =F23*Assumptions!$B$22 -> 15654.39 | G31: =G23*Assumptions!$B$22 -> 15861.183 | H31: =H23*Assumptions!$B$22 -> 16080.385 | I31: =I23*Assumptions!$B$22 -> 16312.738 | ... Y31: =Y23*Assumptions!$B$22 -> 18000 | Z31: =SUM(B31:M31) -> 188883.41 | AA31: =SUM(N31:Y31) -> 215701.12 | AB31: =SUM(B31:Y31) -> 404584.54
A32: Maintenance visit cost | B32: =B25/12*Assumptions!$B$33*Assumptions!$B$37 -> 0 | C32: =C25/12*Assumptions!$B$33*Assumptions!$B$37 -> 0 | D32: =D25/12*Assumptions!$B$33*Assumptions!$B$37 -> 48.30067 | E32: =E25/12*Assumptions!$B$33*Assumptions!$B$37 -> 96.762456 | F32: =F25/12*Assumptions!$B$33*Assumptions!$B$37 -> 145.41327 | G32: =G25/12*Assumptions!$B$33*Assumptions!$B$37 -> 194.28258 | H32: =H25/12*Assumptions!$B$33*Assumptions!$B$37 -> 243.4015 | I32: =I25/12*Assumptions!$B$33*Assumptions!$B$37 -> 292.80288 | ... Y32: =Y25/12*Assumptions!$B$33*Assumptions!$B$37 -> 1017.088 | Z32: =SUM(B32:M32) -> 2693.0951 | AA32: =SUM(N32:Y32) -> 9446.8177 | AB32: =SUM(B32:Y32) -> 12139.913
A33: Total direct costs | B33: =B30+B31+B32 -> 39080.393 | C33: =C30+C31+C32 -> 42909.647 | D33: =D30+D31+D32 -> 43131.576 | E33: =E30+E31+E32 -> 43364.084 | F33: =F30+F31+F32 -> 43607.823 | G33: =G30+G31+G32 -> 43863.486 | H33: =H30+H31+H32 -> 44131.806 | I33: =I30+I31+I32 -> 44413.561 | ... Y33: =Y30+Y31+Y32 -> 46825.108 | Z33: =SUM(B33:M33) -> 525272.75 | AA33: =SUM(N33:Y33) -> 558844.18 | AB33: =SUM(B33:Y33) -> 1084116.9
A34: GROSS PROFIT | B34: =B27-B33 -> 17281.472 | C34: =C27-C33 -> 32598.49 | D34: =D27-D33 -> 33416.513 | E34: =E27-E33 -> 34276.62 | F34: =F27-F33 -> 35181.381 | G34: =G27-G33 -> 36133.521 | H34: =H27-H33 -> 37135.931 | I34: =I27-I33 -> 38191.671 | ... Y34: =Y27-Y33 -> 46792.819 | Z34: =SUM(B34:M34) -> 428724.05 | AA34: =SUM(N34:Y34) -> 553265.12 | AB34: =SUM(B34:Y34) -> 981989.16
A35: Gross margin % | B35: =IF(B27=0,0,B34/B27) -> 0.30661639 | C35: =IF(C27=0,0,C34/C27) -> 0.43172155 | D35: =IF(D27=0,0,D34/D27) -> 0.43654275 | E35: =IF(E27=0,0,E34/E27) -> 0.44147745 | F35: =IF(F27=0,0,F34/F27) -> 0.4465254 | G35: =IF(G27=0,0,G34/G27) -> 0.45168591 | H35: =IF(H27=0,0,H34/H27) -> 0.45695786 | I35: =IF(I27=0,0,I34/I27) -> 0.46233961 | ... Y35: =IF(Y27=0,0,Y34/Y27) -> 0.49982755
A36: OVERHEAD
A37: Owner draw | B37: =Assumptions!$B$78 -> 12500 | C37: =Assumptions!$B$78 -> 12500 | D37: =Assumptions!$B$78 -> 12500 | E37: =Assumptions!$B$78 -> 12500 | F37: =Assumptions!$B$78 -> 12500 | G37: =Assumptions!$B$78 -> 12500 | H37: =Assumptions!$B$78 -> 12500 | I37: =Assumptions!$B$78 -> 12500 | ... Y37: =Assumptions!$B$78 -> 12500 | Z37: =SUM(B37:M37) -> 150000 | AA37: =SUM(N37:Y37) -> 150000 | AB37: =SUM(B37:Y37) -> 300000
A38: Insurance | B38: =Assumptions!$B$79 -> 900 | C38: =Assumptions!$B$79 -> 900 | D38: =Assumptions!$B$79 -> 900 | E38: =Assumptions!$B$79 -> 900 | F38: =Assumptions!$B$79 -> 900 | G38: =Assumptions!$B$79 -> 900 | H38: =Assumptions!$B$79 -> 900 | I38: =Assumptions!$B$79 -> 900 | ... Y38: =Assumptions!$B$79 -> 900 | Z38: =SUM(B38:M38) -> 10800 | AA38: =SUM(N38:Y38) -> 10800 | AB38: =SUM(B38:Y38) -> 21600
A39: Existing truck / equipment payments | B39: =Assumptions!$B$80 -> 1800 | C39: =Assumptions!$B$80 -> 1800 | D39: =Assumptions!$B$80 -> 1800 | E39: =Assumptions!$B$80 -> 1800 | F39: =Assumptions!$B$80 -> 1800 | G39: =Assumptions!$B$80 -> 1800 | H39: =Assumptions!$B$80 -> 1800 | I39: =Assumptions!$B$80 -> 1800 | ... Y39: =Assumptions!$B$80 -> 1800 | Z39: =SUM(B39:M39) -> 21600 | AA39: =SUM(N39:Y39) -> 21600 | AB39: =SUM(B39:Y39) -> 43200
A40: Software, hosting, phone, payment fees | B40: =Assumptions!$B$81 -> 350 | C40: =Assumptions!$B$81 -> 350 | D40: =Assumptions!$B$81 -> 350 | E40: =Assumptions!$B$81 -> 350 | F40: =Assumptions!$B$81 -> 350 | G40: =Assumptions!$B$81 -> 350 | H40: =Assumptions!$B$81 -> 350 | I40: =Assumptions!$B$81 -> 350 | ... Y40: =Assumptions!$B$81 -> 350 | Z40: =SUM(B40:M40) -> 4200 | AA40: =SUM(N40:Y40) -> 4200 | AB40: =SUM(B40:Y40) -> 8400
A41: Bookkeeping / CPA | B41: =Assumptions!$B$82 -> 250 | C41: =Assumptions!$B$82 -> 250 | D41: =Assumptions!$B$82 -> 250 | E41: =Assumptions!$B$82 -> 250 | F41: =Assumptions!$B$82 -> 250 | G41: =Assumptions!$B$82 -> 250 | H41: =Assumptions!$B$82 -> 250 | I41: =Assumptions!$B$82 -> 250 | ... Y41: =Assumptions!$B$82 -> 250 | Z41: =SUM(B41:M41) -> 3000 | AA41: =SUM(N41:Y41) -> 3000 | AB41: =SUM(B41:Y41) -> 6000
A42: Shop, tools, misc | B42: =Assumptions!$B$83 -> 600 | C42: =Assumptions!$B$83 -> 600 | D42: =Assumptions!$B$83 -> 600 | E42: =Assumptions!$B$83 -> 600 | F42: =Assumptions!$B$83 -> 600 | G42: =Assumptions!$B$83 -> 600 | H42: =Assumptions!$B$83 -> 600 | I42: =Assumptions!$B$83 -> 600 | ... Y42: =Assumptions!$B$83 -> 600 | Z42: =SUM(B42:M42) -> 7200 | AA42: =SUM(N42:Y42) -> 7200 | AB42: =SUM(B42:Y42) -> 14400
A43: Yard / shop rent (Cottondale: sq ft used x rate) | B43: =IF(1>=Assumptions!$B$86,Assumptions!$B$87,0) -> 2125 | C43: =IF(2>=Assumptions!$B$86,Assumptions!$B$87,0) -> 2125 | D43: =IF(3>=Assumptions!$B$86,Assumptions!$B$87,0) -> 2125 | E43: =IF(4>=Assumptions!$B$86,Assumptions!$B$87,0) -> 2125 | F43: =IF(5>=Assumptions!$B$86,Assumptions!$B$87,0) -> 2125 | G43: =IF(6>=Assumptions!$B$86,Assumptions!$B$87,0) -> 2125 | H43: =IF(7>=Assumptions!$B$86,Assumptions!$B$87,0) -> 2125 | I43: =IF(8>=Assumptions!$B$86,Assumptions!$B$87,0) -> 2125 | J43: =IF(9>=Assumptions!$B$86,Assumptions!$B$87,0) -> 2125 | K43: =IF(10>=Assumptions!$B$86,Assumptions!$B$87,0) -> 2125 | L43: =IF(11>=Assumptions!$B$86,Assumptions!$B$87,0) -> 2125 | M43: =IF(12>=Assumptions!$B$86,Assumptions!$B$87,0) -> 2125 | N43: =IF(13>=Assumptions!$B$86,Assumptions!$B$87,0) -> 2125 | O43: =IF(14>=Assumptions!$B$86,Assumptions!$B$87,0) -> 2125 | P43: =IF(15>=Assumptions!$B$86,Assumptions!$B$87,0) -> 2125 | Q43: =IF(16>=Assumptions!$B$86,Assumptions!$B$87,0) -> 2125 | R43: =IF(17>=Assumptions!$B$86,Assumptions!$B$87,0) -> 2125 | S43: =IF(18>=Assumptions!$B$86,Assumptions!$B$87,0) -> 2125 | T43: =IF(19>=Assumptions!$B$86,Assumptions!$B$87,0) -> 2125 | U43: =IF(20>=Assumptions!$B$86,Assumptions!$B$87,0) -> 2125 | V43: =IF(21>=Assumptions!$B$86,Assumptions!$B$87,0) -> 2125 | W43: =IF(22>=Assumptions!$B$86,Assumptions!$B$87,0) -> 2125 | X43: =IF(23>=Assumptions!$B$86,Assumptions!$B$87,0) -> 2125 | Y43: =IF(24>=Assumptions!$B$86,Assumptions!$B$87,0) -> 2125 | Z43: =SUM(B43:M43) -> 25500 | AA43: =SUM(N43:Y43) -> 25500 | AB43: =SUM(B43:Y43) -> 51000
A44: Growth & operations lead (TBD) | B44: =Assumptions!$B$88 -> 0 | C44: =Assumptions!$B$88 -> 0 | D44: =Assumptions!$B$88 -> 0 | E44: =Assumptions!$B$88 -> 0 | F44: =Assumptions!$B$88 -> 0 | G44: =Assumptions!$B$88 -> 0 | H44: =Assumptions!$B$88 -> 0 | I44: =Assumptions!$B$88 -> 0 | ... Y44: =Assumptions!$B$88 -> 0 | Z44: =SUM(B44:M44) -> 0 | AA44: =SUM(N44:Y44) -> 0 | AB44: =SUM(B44:Y44) -> 0
A45: Marketing - Google LSA | B45: =Assumptions!$B$64*IF(1>=Assumptions!$B$14,Assumptions!$B$75,1) -> 1440 | C45: =Assumptions!$B$64*IF(2>=Assumptions!$B$14,Assumptions!$B$75,1) -> 1440 | D45: =Assumptions!$B$64*IF(3>=Assumptions!$B$14,Assumptions!$B$75,1) -> 1440 | E45: =Assumptions!$B$64*IF(4>=Assumptions!$B$14,Assumptions!$B$75,1) -> 1440 | F45: =Assumptions!$B$64*IF(5>=Assumptions!$B$14,Assumptions!$B$75,1) -> 1440 | G45: =Assumptions!$B$64*IF(6>=Assumptions!$B$14,Assumptions!$B$75,1) -> 1440 | H45: =Assumptions!$B$64*IF(7>=Assumptions!$B$14,Assumptions!$B$75,1) -> 1440 | I45: =Assumptions!$B$64*IF(8>=Assumptions!$B$14,Assumptions!$B$75,1) -> 1440 | J45: =Assumptions!$B$64*IF(9>=Assumptions!$B$14,Assumptions!$B$75,1) -> 1440 | K45: =Assumptions!$B$64*IF(10>=Assumptions!$B$14,Assumptions!$B$75,1) -> 1440 | L45: =Assumptions!$B$64*IF(11>=Assumptions!$B$14,Assumptions!$B$75,1) -> 1440 | M45: =Assumptions!$B$64*IF(12>=Assumptions!$B$14,Assumptions!$B$75,1) -> 1440 | N45: =Assumptions!$B$64*IF(13>=Assumptions!$B$14,Assumptions!$B$75,1) -> 1440 | O45: =Assumptions!$B$64*IF(14>=Assumptions!$B$14,Assumptions!$B$75,1) -> 1440 | P45: =Assumptions!$B$64*IF(15>=Assumptions!$B$14,Assumptions!$B$75,1) -> 1440 | Q45: =Assumptions!$B$64*IF(16>=Assumptions!$B$14,Assumptions!$B$75,1) -> 1440 | R45: =Assumptions!$B$64*IF(17>=Assumptions!$B$14,Assumptions!$B$75,1) -> 1440 | S45: =Assumptions!$B$64*IF(18>=Assumptions!$B$14,Assumptions!$B$75,1) -> 1440 | T45: =Assumptions!$B$64*IF(19>=Assumptions!$B$14,Assumptions!$B$75,1) -> 1440 | U45: =Assumptions!$B$64*IF(20>=Assumptions!$B$14,Assumptions!$B$75,1) -> 1440 | V45: =Assumptions!$B$64*IF(21>=Assumptions!$B$14,Assumptions!$B$75,1) -> 1440 | W45: =Assumptions!$B$64*IF(22>=Assumptions!$B$14,Assumptions!$B$75,1) -> 1440 | X45: =Assumptions!$B$64*IF(23>=Assumptions!$B$14,Assumptions!$B$75,1) -> 1440 | Y45: =Assumptions!$B$64*IF(24>=Assumptions!$B$14,Assumptions!$B$75,1) -> 1440 | Z45: =SUM(B45:M45) -> 17280 | AA45: =SUM(N45:Y45) -> 17280 | AB45: =SUM(B45:Y45) -> 34560
A46: Marketing - Facebook / Instagram | B46: =IF(1>=2,Assumptions!$B$67*IF(1>=Assumptions!$B$14,Assumptions!$B$75,1),0) -> 0 | C46: =IF(2>=2,Assumptions!$B$67*IF(2>=Assumptions!$B$14,Assumptions!$B$75,1),0) -> 960 | D46: =IF(3>=2,Assumptions!$B$67*IF(3>=Assumptions!$B$14,Assumptions!$B$75,1),0) -> 960 | E46: =IF(4>=2,Assumptions!$B$67*IF(4>=Assumptions!$B$14,Assumptions!$B$75,1),0) -> 960 | F46: =IF(5>=2,Assumptions!$B$67*IF(5>=Assumptions!$B$14,Assumptions!$B$75,1),0) -> 960 | G46: =IF(6>=2,Assumptions!$B$67*IF(6>=Assumptions!$B$14,Assumptions!$B$75,1),0) -> 960 | H46: =IF(7>=2,Assumptions!$B$67*IF(7>=Assumptions!$B$14,Assumptions!$B$75,1),0) -> 960 | I46: =IF(8>=2,Assumptions!$B$67*IF(8>=Assumptions!$B$14,Assumptions!$B$75,1),0) -> 960 | J46: =IF(9>=2,Assumptions!$B$67*IF(9>=Assumptions!$B$14,Assumptions!$B$75,1),0) -> 960 | K46: =IF(10>=2,Assumptions!$B$67*IF(10>=Assumptions!$B$14,Assumptions!$B$75,1),0) -> 960 | L46: =IF(11>=2,Assumptions!$B$67*IF(11>=Assumptions!$B$14,Assumptions!$B$75,1),0) -> 960 | M46: =IF(12>=2,Assumptions!$B$67*IF(12>=Assumptions!$B$14,Assumptions!$B$75,1),0) -> 960 | N46: =IF(13>=2,Assumptions!$B$67*IF(13>=Assumptions!$B$14,Assumptions!$B$75,1),0) -> 960 | O46: =IF(14>=2,Assumptions!$B$67*IF(14>=Assumptions!$B$14,Assumptions!$B$75,1),0) -> 960 | P46: =IF(15>=2,Assumptions!$B$67*IF(15>=Assumptions!$B$14,Assumptions!$B$75,1),0) -> 960 | Q46: =IF(16>=2,Assumptions!$B$67*IF(16>=Assumptions!$B$14,Assumptions!$B$75,1),0) -> 960 | R46: =IF(17>=2,Assumptions!$B$67*IF(17>=Assumptions!$B$14,Assumptions!$B$75,1),0) -> 960 | S46: =IF(18>=2,Assumptions!$B$67*IF(18>=Assumptions!$B$14,Assumptions!$B$75,1),0) -> 960 | T46: =IF(19>=2,Assumptions!$B$67*IF(19>=Assumptions!$B$14,Assumptions!$B$75,1),0) -> 960 | U46: =IF(20>=2,Assumptions!$B$67*IF(20>=Assumptions!$B$14,Assumptions!$B$75,1),0) -> 960 | V46: =IF(21>=2,Assumptions!$B$67*IF(21>=Assumptions!$B$14,Assumptions!$B$75,1),0) -> 960 | W46: =IF(22>=2,Assumptions!$B$67*IF(22>=Assumptions!$B$14,Assumptions!$B$75,1),0) -> 960 | X46: =IF(23>=2,Assumptions!$B$67*IF(23>=Assumptions!$B$14,Assumptions!$B$75,1),0) -> 960 | Y46: =IF(24>=2,Assumptions!$B$67*IF(24>=Assumptions!$B$14,Assumptions!$B$75,1),0) -> 960 | Z46: =SUM(B46:M46) -> 10560 | AA46: =SUM(N46:Y46) -> 11520 | AB46: =SUM(B46:Y46) -> 22080
A47: Marketing - content, reviews, GBP, site | B47: =Assumptions!$B$76 -> 300 | C47: =Assumptions!$B$76 -> 300 | D47: =Assumptions!$B$76 -> 300 | E47: =Assumptions!$B$76 -> 300 | F47: =Assumptions!$B$76 -> 300 | G47: =Assumptions!$B$76 -> 300 | H47: =Assumptions!$B$76 -> 300 | I47: =Assumptions!$B$76 -> 300 | ... Y47: =Assumptions!$B$76 -> 300 | Z47: =SUM(B47:M47) -> 3600 | AA47: =SUM(N47:Y47) -> 3600 | AB47: =SUM(B47:Y47) -> 7200
A48: Crew 2 - equipment rental (before purchase) + hiring | B48: =IF(AND(1>=Assumptions!$B$14,1<Assumptions!$B$14+Assumptions!$B$92),Assumptions!$B$91,0)+IF(AND(1>=Assumptions!$B$14,1<Assumptions!$B$14+Assumptions!$B$95),Assumptions!$B$94,0)+IF(AND(1>=Assumptions!$B$14,1<Assumptions!$B$14+Assumptions!$B$98),Assumptions!$B$97,0)+IF(AND(1>=Assumptions!$B$14,1<Assumptions!$B$14+Assumptions!$B$101),Assumptions!$B$100,0)+IF(AND(1>=Assumptions!$B$14,1<Assumptions!$B$14+Assumptions!$B$104),Assumptions!$B$103,0)+IF(1=Assumptions!$B$14,Assumptions!$B$108,0) -> 8200 | C48: =IF(AND(2>=Assumptions!$B$14,2<Assumptions!$B$14+Assumptions!$B$92),Assumptions!$B$91,0)+IF(AND(2>=Assumptions!$B$14,2<Assumptions!$B$14+Assumptions!$B$95),Assumptions!$B$94,0)+IF(AND(2>=Assumptions!$B$14,2<Assumptions!$B$14+Assumptions!$B$98),Assumptions!$B$97,0)+IF(AND(2>=Assumptions!$B$14,2<Assumptions!$B$14+Assumptions!$B$101),Assumptions!$B$100,0)+IF(AND(2>=Assumptions!$B$14,2<Assumptions!$B$14+Assumptions!$B$104),Assumptions!$B$103,0)+IF(2=Assumptions!$B$14,Assumptions!$B$108,0) -> 3700 | D48: =IF(AND(3>=Assumptions!$B$14,3<Assumptions!$B$14+Assumptions!$B$92),Assumptions!$B$91,0)+IF(AND(3>=Assumptions!$B$14,3<Assumptions!$B$14+Assumptions!$B$95),Assumptions!$B$94,0)+IF(AND(3>=Assumptions!$B$14,3<Assumptions!$B$14+Assumptions!$B$98),Assumptions!$B$97,0)+IF(AND(3>=Assumptions!$B$14,3<Assumptions!$B$14+Assumptions!$B$101),Assumptions!$B$100,0)+IF(AND(3>=Assumptions!$B$14,3<Assumptions!$B$14+Assumptions!$B$104),Assumptions!$B$103,0)+IF(3=Assumptions!$B$14,Assumptions!$B$108,0) -> 3700 | E48: =IF(AND(4>=Assumptions!$B$14,4<Assumptions!$B$14+Assumptions!$B$92),Assumptions!$B$91,0)+IF(AND(4>=Assumptions!$B$14,4<Assumptions!$B$14+Assumptions!$B$95),Assumptions!$B$94,0)+IF(AND(4>=Assumptions!$B$14,4<Assumptions!$B$14+Assumptions!$B$98),Assumptions!$B$97,0)+IF(AND(4>=Assumptions!$B$14,4<Assumptions!$B$14+Assumptions!$B$101),Assumptions!$B$100,0)+IF(AND(4>=Assumptions!$B$14,4<Assumptions!$B$14+Assumptions!$B$104),Assumptions!$B$103,0)+IF(4=Assumptions!$B$14,Assumptions!$B$108,0) -> 0 | F48: =IF(AND(5>=Assumptions!$B$14,5<Assumptions!$B$14+Assumptions!$B$92),Assumptions!$B$91,0)+IF(AND(5>=Assumptions!$B$14,5<Assumptions!$B$14+Assumptions!$B$95),Assumptions!$B$94,0)+IF(AND(5>=Assumptions!$B$14,5<Assumptions!$B$14+Assumptions!$B$98),Assumptions!$B$97,0)+IF(AND(5>=Assumptions!$B$14,5<Assumptions!$B$14+Assumptions!$B$101),Assumptions!$B$100,0)+IF(AND(5>=Assumptions!$B$14,5<Assumptions!$B$14+Assumptions!$B$104),Assumptions!$B$103,0)+IF(5=Assumptions!$B$14,Assumptions!$B$108,0) -> 0 | G48: =IF(AND(6>=Assumptions!$B$14,6<Assumptions!$B$14+Assumptions!$B$92),Assumptions!$B$91,0)+IF(AND(6>=Assumptions!$B$14,6<Assumptions!$B$14+Assumptions!$B$95),Assumptions!$B$94,0)+IF(AND(6>=Assumptions!$B$14,6<Assumptions!$B$14+Assumptions!$B$98),Assumptions!$B$97,0)+IF(AND(6>=Assumptions!$B$14,6<Assumptions!$B$14+Assumptions!$B$101),Assumptions!$B$100,0)+IF(AND(6>=Assumptions!$B$14,6<Assumptions!$B$14+Assumptions!$B$104),Assumptions!$B$103,0)+IF(6=Assumptions!$B$14,Assumptions!$B$108,0) -> 0 | H48: =IF(AND(7>=Assumptions!$B$14,7<Assumptions!$B$14+Assumptions!$B$92),Assumptions!$B$91,0)+IF(AND(7>=Assumptions!$B$14,7<Assumptions!$B$14+Assumptions!$B$95),Assumptions!$B$94,0)+IF(AND(7>=Assumptions!$B$14,7<Assumptions!$B$14+Assumptions!$B$98),Assumptions!$B$97,0)+IF(AND(7>=Assumptions!$B$14,7<Assumptions!$B$14+Assumptions!$B$101),Assumptions!$B$100,0)+IF(AND(7>=Assumptions!$B$14,7<Assumptions!$B$14+Assumptions!$B$104),Assumptions!$B$103,0)+IF(7=Assumptions!$B$14,Assumptions!$B$108,0) -> 0 | I48: =IF(AND(8>=Assumptions!$B$14,8<Assumptions!$B$14+Assumptions!$B$92),Assumptions!$B$91,0)+IF(AND(8>=Assumptions!$B$14,8<Assumptions!$B$14+Assumptions!$B$95),Assumptions!$B$94,0)+IF(AND(8>=Assumptions!$B$14,8<Assumptions!$B$14+Assumptions!$B$98),Assumptions!$B$97,0)+IF(AND(8>=Assumptions!$B$14,8<Assumptions!$B$14+Assumptions!$B$101),Assumptions!$B$100,0)+IF(AND(8>=Assumptions!$B$14,8<Assumptions!$B$14+Assumptions!$B$104),Assumptions!$B$103,0)+IF(8=Assumptions!$B$14,Assumptions!$B$108,0) -> 0 | J48: =IF(AND(9>=Assumptions!$B$14,9<Assumptions!$B$14+Assumptions!$B$92),Assumptions!$B$91,0)+IF(AND(9>=Assumptions!$B$14,9<Assumptions!$B$14+Assumptions!$B$95),Assumptions!$B$94,0)+IF(AND(9>=Assumptions!$B$14,9<Assumptions!$B$14+Assumptions!$B$98),Assumptions!$B$97,0)+IF(AND(9>=Assumptions!$B$14,9<Assumptions!$B$14+Assumptions!$B$101),Assumptions!$B$100,0)+IF(AND(9>=Assumptions!$B$14,9<Assumptions!$B$14+Assumptions!$B$104),Assumptions!$B$103,0)+IF(9=Assumptions!$B$14,Assumptions!$B$108,0) -> 0 | K48: =IF(AND(10>=Assumptions!$B$14,10<Assumptions!$B$14+Assumptions!$B$92),Assumptions!$B$91,0)+IF(AND(10>=Assumptions!$B$14,10<Assumptions!$B$14+Assumptions!$B$95),Assumptions!$B$94,0)+IF(AND(10>=Assumptions!$B$14,10<Assumptions!$B$14+Assumptions!$B$98),Assumptions!$B$97,0)+IF(AND(10>=Assumptions!$B$14,10<Assumptions!$B$14+Assumptions!$B$101),Assumptions!$B$100,0)+IF(AND(10>=Assumptions!$B$14,10<Assumptions!$B$14+Assumptions!$B$104),Assumptions!$B$103,0)+IF(10=Assumptions!$B$14,Assumptions!$B$108,0) -> 0 | L48: =IF(AND(11>=Assumptions!$B$14,11<Assumptions!$B$14+Assumptions!$B$92),Assumptions!$B$91,0)+IF(AND(11>=Assumptions!$B$14,11<Assumptions!$B$14+Assumptions!$B$95),Assumptions!$B$94,0)+IF(AND(11>=Assumptions!$B$14,11<Assumptions!$B$14+Assumptions!$B$98),Assumptions!$B$97,0)+IF(AND(11>=Assumptions!$B$14,11<Assumptions!$B$14+Assumptions!$B$101),Assumptions!$B$100,0)+IF(AND(11>=Assumptions!$B$14,11<Assumptions!$B$14+Assumptions!$B$104),Assumptions!$B$103,0)+IF(11=Assumptions!$B$14,Assumptions!$B$108,0) -> 0 | M48: =IF(AND(12>=Assumptions!$B$14,12<Assumptions!$B$14+Assumptions!$B$92),Assumptions!$B$91,0)+IF(AND(12>=Assumptions!$B$14,12<Assumptions!$B$14+Assumptions!$B$95),Assumptions!$B$94,0)+IF(AND(12>=Assumptions!$B$14,12<Assumptions!$B$14+Assumptions!$B$98),Assumptions!$B$97,0)+IF(AND(12>=Assumptions!$B$14,12<Assumptions!$B$14+Assumptions!$B$101),Assumptions!$B$100,0)+IF(AND(12>=Assumptions!$B$14,12<Assumptions!$B$14+Assumptions!$B$104),Assumptions!$B$103,0)+IF(12=Assumptions!$B$14,Assumptions!$B$108,0) -> 0 | N48: =IF(AND(13>=Assumptions!$B$14,13<Assumptions!$B$14+Assumptions!$B$92),Assumptions!$B$91,0)+IF(AND(13>=Assumptions!$B$14,13<Assumptions!$B$14+Assumptions!$B$95),Assumptions!$B$94,0)+IF(AND(13>=Assumptions!$B$14,13<Assumptions!$B$14+Assumptions!$B$98),Assumptions!$B$97,0)+IF(AND(13>=Assumptions!$B$14,13<Assumptions!$B$14+Assumptions!$B$101),Assumptions!$B$100,0)+IF(AND(13>=Assumptions!$B$14,13<Assumptions!$B$14+Assumptions!$B$104),Assumptions!$B$103,0)+IF(13=Assumptions!$B$14,Assumptions!$B$108,0) -> 0 | O48: =IF(AND(14>=Assumptions!$B$14,14<Assumptions!$B$14+Assumptions!$B$92),Assumptions!$B$91,0)+IF(AND(14>=Assumptions!$B$14,14<Assumptions!$B$14+Assumptions!$B$95),Assumptions!$B$94,0)+IF(AND(14>=Assumptions!$B$14,14<Assumptions!$B$14+Assumptions!$B$98),Assumptions!$B$97,0)+IF(AND(14>=Assumptions!$B$14,14<Assumptions!$B$14+Assumptions!$B$101),Assumptions!$B$100,0)+IF(AND(14>=Assumptions!$B$14,14<Assumptions!$B$14+Assumptions!$B$104),Assumptions!$B$103,0)+IF(14=Assumptions!$B$14,Assumptions!$B$108,0) -> 0 | P48: =IF(AND(15>=Assumptions!$B$14,15<Assumptions!$B$14+Assumptions!$B$92),Assumptions!$B$91,0)+IF(AND(15>=Assumptions!$B$14,15<Assumptions!$B$14+Assumptions!$B$95),Assumptions!$B$94,0)+IF(AND(15>=Assumptions!$B$14,15<Assumptions!$B$14+Assumptions!$B$98),Assumptions!$B$97,0)+IF(AND(15>=Assumptions!$B$14,15<Assumptions!$B$14+Assumptions!$B$101),Assumptions!$B$100,0)+IF(AND(15>=Assumptions!$B$14,15<Assumptions!$B$14+Assumptions!$B$104),Assumptions!$B$103,0)+IF(15=Assumptions!$B$14,Assumptions!$B$108,0) -> 0 | Q48: =IF(AND(16>=Assumptions!$B$14,16<Assumptions!$B$14+Assumptions!$B$92),Assumptions!$B$91,0)+IF(AND(16>=Assumptions!$B$14,16<Assumptions!$B$14+Assumptions!$B$95),Assumptions!$B$94,0)+IF(AND(16>=Assumptions!$B$14,16<Assumptions!$B$14+Assumptions!$B$98),Assumptions!$B$97,0)+IF(AND(16>=Assumptions!$B$14,16<Assumptions!$B$14+Assumptions!$B$101),Assumptions!$B$100,0)+IF(AND(16>=Assumptions!$B$14,16<Assumptions!$B$14+Assumptions!$B$104),Assumptions!$B$103,0)+IF(16=Assumptions!$B$14,Assumptions!$B$108,0) -> 0 | R48: =IF(AND(17>=Assumptions!$B$14,17<Assumptions!$B$14+Assumptions!$B$92),Assumptions!$B$91,0)+IF(AND(17>=Assumptions!$B$14,17<Assumptions!$B$14+Assumptions!$B$95),Assumptions!$B$94,0)+IF(AND(17>=Assumptions!$B$14,17<Assumptions!$B$14+Assumptions!$B$98),Assumptions!$B$97,0)+IF(AND(17>=Assumptions!$B$14,17<Assumptions!$B$14+Assumptions!$B$101),Assumptions!$B$100,0)+IF(AND(17>=Assumptions!$B$14,17<Assumptions!$B$14+Assumptions!$B$104),Assumptions!$B$103,0)+IF(17=Assumptions!$B$14,Assumptions!$B$108,0) -> 0 | S48: =IF(AND(18>=Assumptions!$B$14,18<Assumptions!$B$14+Assumptions!$B$92),Assumptions!$B$91,0)+IF(AND(18>=Assumptions!$B$14,18<Assumptions!$B$14+Assumptions!$B$95),Assumptions!$B$94,0)+IF(AND(18>=Assumptions!$B$14,18<Assumptions!$B$14+Assumptions!$B$98),Assumptions!$B$97,0)+IF(AND(18>=Assumptions!$B$14,18<Assumptions!$B$14+Assumptions!$B$101),Assumptions!$B$100,0)+IF(AND(18>=Assumptions!$B$14,18<Assumptions!$B$14+Assumptions!$B$104),Assumptions!$B$103,0)+IF(18=Assumptions!$B$14,Assumptions!$B$108,0) -> 0 | T48: =IF(AND(19>=Assumptions!$B$14,19<Assumptions!$B$14+Assumptions!$B$92),Assumptions!$B$91,0)+IF(AND(19>=Assumptions!$B$14,19<Assumptions!$B$14+Assumptions!$B$95),Assumptions!$B$94,0)+IF(AND(19>=Assumptions!$B$14,19<Assumptions!$B$14+Assumptions!$B$98),Assumptions!$B$97,0)+IF(AND(19>=Assumptions!$B$14,19<Assumptions!$B$14+Assumptions!$B$101),Assumptions!$B$100,0)+IF(AND(19>=Assumptions!$B$14,19<Assumptions!$B$14+Assumptions!$B$104),Assumptions!$B$103,0)+IF(19=Assumptions!$B$14,Assumptions!$B$108,0) -> 0 | U48: =IF(AND(20>=Assumptions!$B$14,20<Assumptions!$B$14+Assumptions!$B$92),Assumptions!$B$91,0)+IF(AND(20>=Assumptions!$B$14,20<Assumptions!$B$14+Assumptions!$B$95),Assumptions!$B$94,0)+IF(AND(20>=Assumptions!$B$14,20<Assumptions!$B$14+Assumptions!$B$98),Assumptions!$B$97,0)+IF(AND(20>=Assumptions!$B$14,20<Assumptions!$B$14+Assumptions!$B$101),Assumptions!$B$100,0)+IF(AND(20>=Assumptions!$B$14,20<Assumptions!$B$14+Assumptions!$B$104),Assumptions!$B$103,0)+IF(20=Assumptions!$B$14,Assumptions!$B$108,0) -> 0 | V48: =IF(AND(21>=Assumptions!$B$14,21<Assumptions!$B$14+Assumptions!$B$92),Assumptions!$B$91,0)+IF(AND(21>=Assumptions!$B$14,21<Assumptions!$B$14+Assumptions!$B$95),Assumptions!$B$94,0)+IF(AND(21>=Assumptions!$B$14,21<Assumptions!$B$14+Assumptions!$B$98),Assumptions!$B$97,0)+IF(AND(21>=Assumptions!$B$14,21<Assumptions!$B$14+Assumptions!$B$101),Assumptions!$B$100,0)+IF(AND(21>=Assumptions!$B$14,21<Assumptions!$B$14+Assumptions!$B$104),Assumptions!$B$103,0)+IF(21=Assumptions!$B$14,Assumptions!$B$108,0) -> 0 | W48: =IF(AND(22>=Assumptions!$B$14,22<Assumptions!$B$14+Assumptions!$B$92),Assumptions!$B$91,0)+IF(AND(22>=Assumptions!$B$14,22<Assumptions!$B$14+Assumptions!$B$95),Assumptions!$B$94,0)+IF(AND(22>=Assumptions!$B$14,22<Assumptions!$B$14+Assumptions!$B$98),Assumptions!$B$97,0)+IF(AND(22>=Assumptions!$B$14,22<Assumptions!$B$14+Assumptions!$B$101),Assumptions!$B$100,0)+IF(AND(22>=Assumptions!$B$14,22<Assumptions!$B$14+Assumptions!$B$104),Assumptions!$B$103,0)+IF(22=Assumptions!$B$14,Assumptions!$B$108,0) -> 0 | X48: =IF(AND(23>=Assumptions!$B$14,23<Assumptions!$B$14+Assumptions!$B$92),Assumptions!$B$91,0)+IF(AND(23>=Assumptions!$B$14,23<Assumptions!$B$14+Assumptions!$B$95),Assumptions!$B$94,0)+IF(AND(23>=Assumptions!$B$14,23<Assumptions!$B$14+Assumptions!$B$98),Assumptions!$B$97,0)+IF(AND(23>=Assumptions!$B$14,23<Assumptions!$B$14+Assumptions!$B$101),Assumptions!$B$100,0)+IF(AND(23>=Assumptions!$B$14,23<Assumptions!$B$14+Assumptions!$B$104),Assumptions!$B$103,0)+IF(23=Assumptions!$B$14,Assumptions!$B$108,0) -> 0 | Y48: =IF(AND(24>=Assumptions!$B$14,24<Assumptions!$B$14+Assumptions!$B$92),Assumptions!$B$91,0)+IF(AND(24>=Assumptions!$B$14,24<Assumptions!$B$14+Assumptions!$B$95),Assumptions!$B$94,0)+IF(AND(24>=Assumptions!$B$14,24<Assumptions!$B$14+Assumptions!$B$98),Assumptions!$B$97,0)+IF(AND(24>=Assumptions!$B$14,24<Assumptions!$B$14+Assumptions!$B$101),Assumptions!$B$100,0)+IF(AND(24>=Assumptions!$B$14,24<Assumptions!$B$14+Assumptions!$B$104),Assumptions!$B$103,0)+IF(24=Assumptions!$B$14,Assumptions!$B$108,0) -> 0 | Z48: =SUM(B48:M48) -> 15600 | AA48: =SUM(N48:Y48) -> 0 | AB48: =SUM(B48:Y48) -> 15600
A49: Crew 2 - equipment + truck loan payments | B49: =IF(1>=Assumptions!$B$14+Assumptions!$B$92,-PMT(Assumptions!$B$106/12,Assumptions!$B$107,Assumptions!$B$90*Assumptions!$B$105),0)+IF(1>=Assumptions!$B$14+Assumptions!$B$95,-PMT(Assumptions!$B$106/12,Assumptions!$B$107,Assumptions!$B$93*Assumptions!$B$105),0)+IF(1>=Assumptions!$B$14+Assumptions!$B$98,-PMT(Assumptions!$B$106/12,Assumptions!$B$107,Assumptions!$B$96*Assumptions!$B$105),0)+IF(1>=Assumptions!$B$14+Assumptions!$B$101,-PMT(Assumptions!$B$106/12,Assumptions!$B$107,Assumptions!$B$99*Assumptions!$B$105),0)+IF(1>=Assumptions!$B$14+Assumptions!$B$104,-PMT(Assumptions!$B$106/12,Assumptions!$B$107,Assumptions!$B$102*Assumptions!$B$105),0) -> 838.63755 | C49: =IF(2>=Assumptions!$B$14+Assumptions!$B$92,-PMT(Assumptions!$B$106/12,Assumptions!$B$107,Assumptions!$B$90*Assumptions!$B$105),0)+IF(2>=Assumptions!$B$14+Assumptions!$B$95,-PMT(Assumptions!$B$106/12,Assumptions!$B$107,Assumptions!$B$93*Assumptions!$B$105),0)+IF(2>=Assumptions!$B$14+Assumptions!$B$98,-PMT(Assumptions!$B$106/12,Assumptions!$B$107,Assumptions!$B$96*Assumptions!$B$105),0)+IF(2>=Assumptions!$B$14+Assumptions!$B$101,-PMT(Assumptions!$B$106/12,Assumptions!$B$107,Assumptions!$B$99*Assumptions!$B$105),0)+IF(2>=Assumptions!$B$14+Assumptions!$B$104,-PMT(Assumptions!$B$106/12,Assumptions!$B$107,Assumptions!$B$102*Assumptions!$B$105),0) -> 838.63755 | D49: =IF(3>=Assumptions!$B$14+Assumptions!$B$92,-PMT(Assumptions!$B$106/12,Assumptions!$B$107,Assumptions!$B$90*Assumptions!$B$105),0)+IF(3>=Assumptions!$B$14+Assumptions!$B$95,-PMT(Assumptions!$B$106/12,Assumptions!$B$107,Assumptions!$B$93*Assumptions!$B$105),0)+IF(3>=Assumptions!$B$14+Assumptions!$B$98,-PMT(Assumptions!$B$106/12,Assumptions!$B$107,Assumptions!$B$96*Assumptions!$B$105),0)+IF(3>=Assumptions!$B$14+Assumptions!$B$101,-PMT(Assumptions!$B$106/12,Assumptions!$B$107,Assumptions!$B$99*Assumptions!$B$105),0)+IF(3>=Assumptions!$B$14+Assumptions!$B$104,-PMT(Assumptions!$B$106/12,Assumptions!$B$107,Assumptions!$B$102*Assumptions!$B$105),0) -> 838.63755 | E49: =IF(4>=Assumptions!$B$14+Assumptions!$B$92,-PMT(Assumptions!$B$106/12,Assumptions!$B$107,Assumptions!$B$90*Assumptions!$B$105),0)+IF(4>=Assumptions!$B$14+Assumptions!$B$95,-PMT(Assumptions!$B$106/12,Assumptions!$B$107,Assumptions!$B$93*Assumptions!$B$105),0)+IF(4>=Assumptions!$B$14+Assumptions!$B$98,-PMT(Assumptions!$B$106/12,Assumptions!$B$107,Assumptions!$B$96*Assumptions!$B$105),0)+IF(4>=Assumptions!$B$14+Assumptions!$B$101,-PMT(Assumptions!$B$106/12,Assumptions!$B$107,Assumptions!$B$99*Assumptions!$B$105),0)+IF(4>=Assumptions!$B$14+Assumptions!$B$104,-PMT(Assumptions!$B$106/12,Assumptions!$B$107,Assumptions!$B$102*Assumptions!$B$105),0) -> 2300.0258 | F49: =IF(5>=Assumptions!$B$14+Assumptions!$B$92,-PMT(Assumptions!$B$106/12,Assumptions!$B$107,Assumptions!$B$90*Assumptions!$B$105),0)+IF(5>=Assumptions!$B$14+Assumptions!$B$95,-PMT(Assumptions!$B$106/12,Assumptions!$B$107,Assumptions!$B$93*Assumptions!$B$105),0)+IF(5>=Assumptions!$B$14+Assumptions!$B$98,-PMT(Assumptions!$B$106/12,Assumptions!$B$107,Assumptions!$B$96*Assumptions!$B$105),0)+IF(5>=Assumptions!$B$14+Assumptions!$B$101,-PMT(Assumptions!$B$106/12,Assumptions!$B$107,Assumptions!$B$99*Assumptions!$B$105),0)+IF(5>=Assumptions!$B$14+Assumptions!$B$104,-PMT(Assumptions!$B$106/12,Assumptions!$B$107,Assumptions!$B$102*Assumptions!$B$105),0) -> 2300.0258 | G49: =IF(6>=Assumptions!$B$14+Assumptions!$B$92,-PMT(Assumptions!$B$106/12,Assumptions!$B$107,Assumptions!$B$90*Assumptions!$B$105),0)+IF(6>=Assumptions!$B$14+Assumptions!$B$95,-PMT(Assumptions!$B$106/12,Assumptions!$B$107,Assumptions!$B$93*Assumptions!$B$105),0)+IF(6>=Assumptions!$B$14+Assumptions!$B$98,-PMT(Assumptions!$B$106/12,Assumptions!$B$107,Assumptions!$B$96*Assumptions!$B$105),0)+IF(6>=Assumptions!$B$14+Assumptions!$B$101,-PMT(Assumptions!$B$106/12,Assumptions!$B$107,Assumptions!$B$99*Assumptions!$B$105),0)+IF(6>=Assumptions!$B$14+Assumptions!$B$104,-PMT(Assumptions!$B$106/12,Assumptions!$B$107,Assumptions!$B$102*Assumptions!$B$105),0) -> 2300.0258 | H49: =IF(7>=Assumptions!$B$14+Assumptions!$B$92,-PMT(Assumptions!$B$106/12,Assumptions!$B$107,Assumptions!$B$90*Assumptions!$B$105),0)+IF(7>=Assumptions!$B$14+Assumptions!$B$95,-PMT(Assumptions!$B$106/12,Assumptions!$B$107,Assumptions!$B$93*Assumptions!$B$105),0)+IF(7>=Assumptions!$B$14+Assumptions!$B$98,-PMT(Assumptions!$B$106/12,Assumptions!$B$107,Assumptions!$B$96*Assumptions!$B$105),0)+IF(7>=Assumptions!$B$14+Assumptions!$B$101,-PMT(Assumptions!$B$106/12,Assumptions!$B$107,Assumptions!$B$99*Assumptions!$B$105),0)+IF(7>=Assumptions!$B$14+Assumptions!$B$104,-PMT(Assumptions!$B$106/12,Assumptions!$B$107,Assumptions!$B$102*Assumptions!$B$105),0) -> 2300.0258 | I49: =IF(8>=Assumptions!$B$14+Assumptions!$B$92,-PMT(Assumptions!$B$106/12,Assumptions!$B$107,Assumptions!$B$90*Assumptions!$B$105),0)+IF(8>=Assumptions!$B$14+Assumptions!$B$95,-PMT(Assumptions!$B$106/12,Assumptions!$B$107,Assumptions!$B$93*Assumptions!$B$105),0)+IF(8>=Assumptions!$B$14+Assumptions!$B$98,-PMT(Assumptions!$B$106/12,Assumptions!$B$107,Assumptions!$B$96*Assumptions!$B$105),0)+IF(8>=Assumptions!$B$14+Assumptions!$B$101,-PMT(Assumptions!$B$106/12,Assumptions!$B$107,Assumptions!$B$99*Assumptions!$B$105),0)+IF(8>=Assumptions!$B$14+Assumptions!$B$104,-PMT(Assumptions!$B$106/12,Assumptions!$B$107,Assumptions!$B$102*Assumptions!$B$105),0) -> 2300.0258 | J49: =IF(9>=Assumptions!$B$14+Assumptions!$B$92,-PMT(Assumptions!$B$106/12,Assumptions!$B$107,Assumptions!$B$90*Assumptions!$B$105),0)+IF(9>=Assumptions!$B$14+Assumptions!$B$95,-PMT(Assumptions!$B$106/12,Assumptions!$B$107,Assumptions!$B$93*Assumptions!$B$105),0)+IF(9>=Assumptions!$B$14+Assumptions!$B$98,-PMT(Assumptions!$B$106/12,Assumptions!$B$107,Assumptions!$B$96*Assumptions!$B$105),0)+IF(9>=Assumptions!$B$14+Assumptions!$B$101,-PMT(Assumptions!$B$106/12,Assumptions!$B$107,Assumptions!$B$99*Assumptions!$B$105),0)+IF(9>=Assumptions!$B$14+Assumptions!$B$104,-PMT(Assumptions!$B$106/12,Assumptions!$B$107,Assumptions!$B$102*Assumptions!$B$105),0) -> 2300.0258 | K49: =IF(10>=Assumptions!$B$14+Assumptions!$B$92,-PMT(Assumptions!$B$106/12,Assumptions!$B$107,Assumptions!$B$90*Assumptions!$B$105),0)+IF(10>=Assumptions!$B$14+Assumptions!$B$95,-PMT(Assumptions!$B$106/12,Assumptions!$B$107,Assumptions!$B$93*Assumptions!$B$105),0)+IF(10>=Assumptions!$B$14+Assumptions!$B$98,-PMT(Assumptions!$B$106/12,Assumptions!$B$107,Assumptions!$B$96*Assumptions!$B$105),0)+IF(10>=Assumptions!$B$14+Assumptions!$B$101,-PMT(Assumptions!$B$106/12,Assumptions!$B$107,Assumptions!$B$99*Assumptions!$B$105),0)+IF(10>=Assumptions!$B$14+Assumptions!$B$104,-PMT(Assumptions!$B$106/12,Assumptions!$B$107,Assumptions!$B$102*Assumptions!$B$105),0) -> 2300.0258 | L49: =IF(11>=Assumptions!$B$14+Assumptions!$B$92,-PMT(Assumptions!$B$106/12,Assumptions!$B$107,Assumptions!$B$90*Assumptions!$B$105),0)+IF(11>=Assumptions!$B$14+Assumptions!$B$95,-PMT(Assumptions!$B$106/12,Assumptions!$B$107,Assumptions!$B$93*Assumptions!$B$105),0)+IF(11>=Assumptions!$B$14+Assumptions!$B$98,-PMT(Assumptions!$B$106/12,Assumptions!$B$107,Assumptions!$B$96*Assumptions!$B$105),0)+IF(11>=Assumptions!$B$14+Assumptions!$B$101,-PMT(Assumptions!$B$106/12,Assumptions!$B$107,Assumptions!$B$99*Assumptions!$B$105),0)+IF(11>=Assumptions!$B$14+Assumptions!$B$104,-PMT(Assumptions!$B$106/12,Assumptions!$B$107,Assumptions!$B$102*Assumptions!$B$105),0) -> 2300.0258 | M49: =IF(12>=Assumptions!$B$14+Assumptions!$B$92,-PMT(Assumptions!$B$106/12,Assumptions!$B$107,Assumptions!$B$90*Assumptions!$B$105),0)+IF(12>=Assumptions!$B$14+Assumptions!$B$95,-PMT(Assumptions!$B$106/12,Assumptions!$B$107,Assumptions!$B$93*Assumptions!$B$105),0)+IF(12>=Assumptions!$B$14+Assumptions!$B$98,-PMT(Assumptions!$B$106/12,Assumptions!$B$107,Assumptions!$B$96*Assumptions!$B$105),0)+IF(12>=Assumptions!$B$14+Assumptions!$B$101,-PMT(Assumptions!$B$106/12,Assumptions!$B$107,Assumptions!$B$99*Assumptions!$B$105),0)+IF(12>=Assumptions!$B$14+Assumptions!$B$104,-PMT(Assumptions!$B$106/12,Assumptions!$B$107,Assumptions!$B$102*Assumptions!$B$105),0) -> 2300.0258 | N49: =IF(13>=Assumptions!$B$14+Assumptions!$B$92,-PMT(Assumptions!$B$106/12,Assumptions!$B$107,Assumptions!$B$90*Assumptions!$B$105),0)+IF(13>=Assumptions!$B$14+Assumptions!$B$95,-PMT(Assumptions!$B$106/12,Assumptions!$B$107,Assumptions!$B$93*Assumptions!$B$105),0)+IF(13>=Assumptions!$B$14+Assumptions!$B$98,-PMT(Assumptions!$B$106/12,Assumptions!$B$107,Assumptions!$B$96*Assumptions!$B$105),0)+IF(13>=Assumptions!$B$14+Assumptions!$B$101,-PMT(Assumptions!$B$106/12,Assumptions!$B$107,Assumptions!$B$99*Assumptions!$B$105),0)+IF(13>=Assumptions!$B$14+Assumptions!$B$104,-PMT(Assumptions!$B$106/12,Assumptions!$B$107,Assumptions!$B$102*Assumptions!$B$105),0) -> 2300.0258 | O49: =IF(14>=Assumptions!$B$14+Assumptions!$B$92,-PMT(Assumptions!$B$106/12,Assumptions!$B$107,Assumptions!$B$90*Assumptions!$B$105),0)+IF(14>=Assumptions!$B$14+Assumptions!$B$95,-PMT(Assumptions!$B$106/12,Assumptions!$B$107,Assumptions!$B$93*Assumptions!$B$105),0)+IF(14>=Assumptions!$B$14+Assumptions!$B$98,-PMT(Assumptions!$B$106/12,Assumptions!$B$107,Assumptions!$B$96*Assumptions!$B$105),0)+IF(14>=Assumptions!$B$14+Assumptions!$B$101,-PMT(Assumptions!$B$106/12,Assumptions!$B$107,Assumptions!$B$99*Assumptions!$B$105),0)+IF(14>=Assumptions!$B$14+Assumptions!$B$104,-PMT(Assumptions!$B$106/12,Assumptions!$B$107,Assumptions!$B$102*Assumptions!$B$105),0) -> 2300.0258 | P49: =IF(15>=Assumptions!$B$14+Assumptions!$B$92,-PMT(Assumptions!$B$106/12,Assumptions!$B$107,Assumptions!$B$90*Assumptions!$B$105),0)+IF(15>=Assumptions!$B$14+Assumptions!$B$95,-PMT(Assumptions!$B$106/12,Assumptions!$B$107,Assumptions!$B$93*Assumptions!$B$105),0)+IF(15>=Assumptions!$B$14+Assumptions!$B$98,-PMT(Assumptions!$B$106/12,Assumptions!$B$107,Assumptions!$B$96*Assumptions!$B$105),0)+IF(15>=Assumptions!$B$14+Assumptions!$B$101,-PMT(Assumptions!$B$106/12,Assumptions!$B$107,Assumptions!$B$99*Assumptions!$B$105),0)+IF(15>=Assumptions!$B$14+Assumptions!$B$104,-PMT(Assumptions!$B$106/12,Assumptions!$B$107,Assumptions!$B$102*Assumptions!$B$105),0) -> 2300.0258 | Q49: =IF(16>=Assumptions!$B$14+Assumptions!$B$92,-PMT(Assumptions!$B$106/12,Assumptions!$B$107,Assumptions!$B$90*Assumptions!$B$105),0)+IF(16>=Assumptions!$B$14+Assumptions!$B$95,-PMT(Assumptions!$B$106/12,Assumptions!$B$107,Assumptions!$B$93*Assumptions!$B$105),0)+IF(16>=Assumptions!$B$14+Assumptions!$B$98,-PMT(Assumptions!$B$106/12,Assumptions!$B$107,Assumptions!$B$96*Assumptions!$B$105),0)+IF(16>=Assumptions!$B$14+Assumptions!$B$101,-PMT(Assumptions!$B$106/12,Assumptions!$B$107,Assumptions!$B$99*Assumptions!$B$105),0)+IF(16>=Assumptions!$B$14+Assumptions!$B$104,-PMT(Assumptions!$B$106/12,Assumptions!$B$107,Assumptions!$B$102*Assumptions!$B$105),0) -> 2300.0258 | R49: =IF(17>=Assumptions!$B$14+Assumptions!$B$92,-PMT(Assumptions!$B$106/12,Assumptions!$B$107,Assumptions!$B$90*Assumptions!$B$105),0)+IF(17>=Assumptions!$B$14+Assumptions!$B$95,-PMT(Assumptions!$B$106/12,Assumptions!$B$107,Assumptions!$B$93*Assumptions!$B$105),0)+IF(17>=Assumptions!$B$14+Assumptions!$B$98,-PMT(Assumptions!$B$106/12,Assumptions!$B$107,Assumptions!$B$96*Assumptions!$B$105),0)+IF(17>=Assumptions!$B$14+Assumptions!$B$101,-PMT(Assumptions!$B$106/12,Assumptions!$B$107,Assumptions!$B$99*Assumptions!$B$105),0)+IF(17>=Assumptions!$B$14+Assumptions!$B$104,-PMT(Assumptions!$B$106/12,Assumptions!$B$107,Assumptions!$B$102*Assumptions!$B$105),0) -> 2300.0258 | S49: =IF(18>=Assumptions!$B$14+Assumptions!$B$92,-PMT(Assumptions!$B$106/12,Assumptions!$B$107,Assumptions!$B$90*Assumptions!$B$105),0)+IF(18>=Assumptions!$B$14+Assumptions!$B$95,-PMT(Assumptions!$B$106/12,Assumptions!$B$107,Assumptions!$B$93*Assumptions!$B$105),0)+IF(18>=Assumptions!$B$14+Assumptions!$B$98,-PMT(Assumptions!$B$106/12,Assumptions!$B$107,Assumptions!$B$96*Assumptions!$B$105),0)+IF(18>=Assumptions!$B$14+Assumptions!$B$101,-PMT(Assumptions!$B$106/12,Assumptions!$B$107,Assumptions!$B$99*Assumptions!$B$105),0)+IF(18>=Assumptions!$B$14+Assumptions!$B$104,-PMT(Assumptions!$B$106/12,Assumptions!$B$107,Assumptions!$B$102*Assumptions!$B$105),0) -> 2300.0258 | T49: =IF(19>=Assumptions!$B$14+Assumptions!$B$92,-PMT(Assumptions!$B$106/12,Assumptions!$B$107,Assumptions!$B$90*Assumptions!$B$105),0)+IF(19>=Assumptions!$B$14+Assumptions!$B$95,-PMT(Assumptions!$B$106/12,Assumptions!$B$107,Assumptions!$B$93*Assumptions!$B$105),0)+IF(19>=Assumptions!$B$14+Assumptions!$B$98,-PMT(Assumptions!$B$106/12,Assumptions!$B$107,Assumptions!$B$96*Assumptions!$B$105),0)+IF(19>=Assumptions!$B$14+Assumptions!$B$101,-PMT(Assumptions!$B$106/12,Assumptions!$B$107,Assumptions!$B$99*Assumptions!$B$105),0)+IF(19>=Assumptions!$B$14+Assumptions!$B$104,-PMT(Assumptions!$B$106/12,Assumptions!$B$107,Assumptions!$B$102*Assumptions!$B$105),0) -> 2300.0258 | U49: =IF(20>=Assumptions!$B$14+Assumptions!$B$92,-PMT(Assumptions!$B$106/12,Assumptions!$B$107,Assumptions!$B$90*Assumptions!$B$105),0)+IF(20>=Assumptions!$B$14+Assumptions!$B$95,-PMT(Assumptions!$B$106/12,Assumptions!$B$107,Assumptions!$B$93*Assumptions!$B$105),0)+IF(20>=Assumptions!$B$14+Assumptions!$B$98,-PMT(Assumptions!$B$106/12,Assumptions!$B$107,Assumptions!$B$96*Assumptions!$B$105),0)+IF(20>=Assumptions!$B$14+Assumptions!$B$101,-PMT(Assumptions!$B$106/12,Assumptions!$B$107,Assumptions!$B$99*Assumptions!$B$105),0)+IF(20>=Assumptions!$B$14+Assumptions!$B$104,-PMT(Assumptions!$B$106/12,Assumptions!$B$107,Assumptions!$B$102*Assumptions!$B$105),0) -> 2300.0258 | V49: =IF(21>=Assumptions!$B$14+Assumptions!$B$92,-PMT(Assumptions!$B$106/12,Assumptions!$B$107,Assumptions!$B$90*Assumptions!$B$105),0)+IF(21>=Assumptions!$B$14+Assumptions!$B$95,-PMT(Assumptions!$B$106/12,Assumptions!$B$107,Assumptions!$B$93*Assumptions!$B$105),0)+IF(21>=Assumptions!$B$14+Assumptions!$B$98,-PMT(Assumptions!$B$106/12,Assumptions!$B$107,Assumptions!$B$96*Assumptions!$B$105),0)+IF(21>=Assumptions!$B$14+Assumptions!$B$101,-PMT(Assumptions!$B$106/12,Assumptions!$B$107,Assumptions!$B$99*Assumptions!$B$105),0)+IF(21>=Assumptions!$B$14+Assumptions!$B$104,-PMT(Assumptions!$B$106/12,Assumptions!$B$107,Assumptions!$B$102*Assumptions!$B$105),0) -> 2300.0258 | W49: =IF(22>=Assumptions!$B$14+Assumptions!$B$92,-PMT(Assumptions!$B$106/12,Assumptions!$B$107,Assumptions!$B$90*Assumptions!$B$105),0)+IF(22>=Assumptions!$B$14+Assumptions!$B$95,-PMT(Assumptions!$B$106/12,Assumptions!$B$107,Assumptions!$B$93*Assumptions!$B$105),0)+IF(22>=Assumptions!$B$14+Assumptions!$B$98,-PMT(Assumptions!$B$106/12,Assumptions!$B$107,Assumptions!$B$96*Assumptions!$B$105),0)+IF(22>=Assumptions!$B$14+Assumptions!$B$101,-PMT(Assumptions!$B$106/12,Assumptions!$B$107,Assumptions!$B$99*Assumptions!$B$105),0)+IF(22>=Assumptions!$B$14+Assumptions!$B$104,-PMT(Assumptions!$B$106/12,Assumptions!$B$107,Assumptions!$B$102*Assumptions!$B$105),0) -> 2300.0258 | X49: =IF(23>=Assumptions!$B$14+Assumptions!$B$92,-PMT(Assumptions!$B$106/12,Assumptions!$B$107,Assumptions!$B$90*Assumptions!$B$105),0)+IF(23>=Assumptions!$B$14+Assumptions!$B$95,-PMT(Assumptions!$B$106/12,Assumptions!$B$107,Assumptions!$B$93*Assumptions!$B$105),0)+IF(23>=Assumptions!$B$14+Assumptions!$B$98,-PMT(Assumptions!$B$106/12,Assumptions!$B$107,Assumptions!$B$96*Assumptions!$B$105),0)+IF(23>=Assumptions!$B$14+Assumptions!$B$101,-PMT(Assumptions!$B$106/12,Assumptions!$B$107,Assumptions!$B$99*Assumptions!$B$105),0)+IF(23>=Assumptions!$B$14+Assumptions!$B$104,-PMT(Assumptions!$B$106/12,Assumptions!$B$107,Assumptions!$B$102*Assumptions!$B$105),0) -> 2300.0258 | Y49: =IF(24>=Assumptions!$B$14+Assumptions!$B$92,-PMT(Assumptions!$B$106/12,Assumptions!$B$107,Assumptions!$B$90*Assumptions!$B$105),0)+IF(24>=Assumptions!$B$14+Assumptions!$B$95,-PMT(Assumptions!$B$106/12,Assumptions!$B$107,Assumptions!$B$93*Assumptions!$B$105),0)+IF(24>=Assumptions!$B$14+Assumptions!$B$98,-PMT(Assumptions!$B$106/12,Assumptions!$B$107,Assumptions!$B$96*Assumptions!$B$105),0)+IF(24>=Assumptions!$B$14+Assumptions!$B$101,-PMT(Assumptions!$B$106/12,Assumptions!$B$107,Assumptions!$B$99*Assumptions!$B$105),0)+IF(24>=Assumptions!$B$14+Assumptions!$B$104,-PMT(Assumptions!$B$106/12,Assumptions!$B$107,Assumptions!$B$102*Assumptions!$B$105),0) -> 2300.0258 | Z49: =SUM(B49:M49) -> 23216.144 | AA49: =SUM(N49:Y49) -> 27600.309 | AB49: =SUM(B49:Y49) -> 50816.454
A50: Total overhead | B50: =SUM(B37:B49) -> 29303.638 | C50: =SUM(C37:C49) -> 25763.638 | D50: =SUM(D37:D49) -> 25763.638 | E50: =SUM(E37:E49) -> 23525.026 | F50: =SUM(F37:F49) -> 23525.026 | G50: =SUM(G37:G49) -> 23525.026 | H50: =SUM(H37:H49) -> 23525.026 | I50: =SUM(I37:I49) -> 23525.026 | ... Y50: =SUM(Y37:Y49) -> 23525.026 | Z50: =SUM(B50:M50) -> 292556.14 | AA50: =SUM(N50:Y50) -> 282300.31 | AB50: =SUM(B50:Y50) -> 574856.45
A51: OPERATING PROFIT (before owner taxes) | B51: =B34-B50 -> -12022.166 | C51: =C34-C50 -> 6834.8522 | D51: =D34-D50 -> 7652.8759 | E51: =E34-E50 -> 10751.594 | F51: =F34-F50 -> 11656.355 | G51: =G34-G50 -> 12608.496 | H51: =H34-H50 -> 13610.905 | I51: =I34-I50 -> 14666.645 | ... Y51: =Y34-Y50 -> 23267.794 | Z51: =SUM(B51:M51) -> 136167.9 | AA51: =SUM(N51:Y51) -> 270964.81 | AB51: =SUM(B51:Y51) -> 407132.71
A52: Operating margin % | B52: =IF(B27=0,0,B51/B27) -> -0.2133032 | C52: =IF(C27=0,0,C51/C27) -> 0.090518087 | D52: =IF(D27=0,0,D51/D27) -> 0.099974747 | E52: =IF(E27=0,0,E51/E27) -> 0.13847883 | F52: =IF(F27=0,0,F51/F27) -> 0.14794356 | G52: =IF(G27=0,0,G51/G27) -> 0.15761209 | H52: =IF(H27=0,0,H51/H27) -> 0.16748227 | I52: =IF(I27=0,0,I51/I27) -> 0.17755104 | ... Y52: =IF(Y27=0,0,Y51/Y27) -> 0.24853993
A53: CASH FLOW
A54: Cash in - deposits + balances + plans | B54: =B23*Assumptions!$B$59+B23*(1-Assumptions!$B$59)*Assumptions!$B$60+0+B26 -> 52416.534 | C54: =C23*Assumptions!$B$59+C23*(1-Assumptions!$B$59)*Assumptions!$B$60+B23*(1-Assumptions!$B$59)*(1-Assumptions!$B$60)+C26 -> 74167.898 | D54: =D23*Assumptions!$B$59+D23*(1-Assumptions!$B$59)*Assumptions!$B$60+C23*(1-Assumptions!$B$59)*(1-Assumptions!$B$60)+D26 -> 76487.32 | E54: =E23*Assumptions!$B$59+E23*(1-Assumptions!$B$59)*Assumptions!$B$60+D23*(1-Assumptions!$B$59)*(1-Assumptions!$B$60)+E26 -> 77576.287 | F54: =F23*Assumptions!$B$59+F23*(1-Assumptions!$B$59)*Assumptions!$B$60+E23*(1-Assumptions!$B$59)*(1-Assumptions!$B$60)+F26 -> 78720.922 | G54: =G23*Assumptions!$B$59+G23*(1-Assumptions!$B$59)*Assumptions!$B$60+F23*(1-Assumptions!$B$59)*(1-Assumptions!$B$60)+G26 -> 79924.629 | H54: =H23*Assumptions!$B$59+H23*(1-Assumptions!$B$59)*Assumptions!$B$60+G23*(1-Assumptions!$B$59)*(1-Assumptions!$B$60)+H26 -> 81191.016 | I54: =I23*Assumptions!$B$59+I23*(1-Assumptions!$B$59)*Assumptions!$B$60+H23*(1-Assumptions!$B$59)*(1-Assumptions!$B$60)+I26 -> 82523.908 | J54: =J23*Assumptions!$B$59+J23*(1-Assumptions!$B$59)*Assumptions!$B$60+I23*(1-Assumptions!$B$59)*(1-Assumptions!$B$60)+J26 -> 83927.358 | ... Y54: =Y23*Assumptions!$B$59+Y23*(1-Assumptions!$B$59)*Assumptions!$B$60+X23*(1-Assumptions!$B$59)*(1-Assumptions!$B$60)+Y26 -> 93617.927 | Z54: =SUM(B54:M54) -> 947910.23 | AA54: =SUM(N54:Y54) -> 1111895.9 | AB54: =SUM(B54:Y54) -> 2059806.1
A55: Cash out - direct costs + overhead | B55: =B33+B50 -> 68384.03 | C55: =C33+C50 -> 68673.285 | D55: =D33+D50 -> 68895.214 | E55: =E33+E50 -> 66889.109 | F55: =F33+F50 -> 67132.849 | G55: =G33+G50 -> 67388.512 | H55: =H33+H50 -> 67656.832 | I55: =I33+I50 -> 67938.587 | ... Y55: =Y33+Y50 -> 70350.134 | Z55: =SUM(B55:M55) -> 817828.89 | AA55: =SUM(N55:Y55) -> 841144.49 | AB55: =SUM(B55:Y55) -> 1658973.4
A56: Cash out - Crew 2 down payments (20% of each purchase) | B56: =IF(1=Assumptions!$B$14+Assumptions!$B$92,Assumptions!$B$90*(1-Assumptions!$B$105),0)+IF(1=Assumptions!$B$14+Assumptions!$B$95,Assumptions!$B$93*(1-Assumptions!$B$105),0)+IF(1=Assumptions!$B$14+Assumptions!$B$98,Assumptions!$B$96*(1-Assumptions!$B$105),0)+IF(1=Assumptions!$B$14+Assumptions!$B$101,Assumptions!$B$99*(1-Assumptions!$B$105),0)+IF(1=Assumptions!$B$14+Assumptions!$B$104,Assumptions!$B$102*(1-Assumptions!$B$105),0) -> 10100 | C56: =IF(2=Assumptions!$B$14+Assumptions!$B$92,Assumptions!$B$90*(1-Assumptions!$B$105),0)+IF(2=Assumptions!$B$14+Assumptions!$B$95,Assumptions!$B$93*(1-Assumptions!$B$105),0)+IF(2=Assumptions!$B$14+Assumptions!$B$98,Assumptions!$B$96*(1-Assumptions!$B$105),0)+IF(2=Assumptions!$B$14+Assumptions!$B$101,Assumptions!$B$99*(1-Assumptions!$B$105),0)+IF(2=Assumptions!$B$14+Assumptions!$B$104,Assumptions!$B$102*(1-Assumptions!$B$105),0) -> 0 | D56: =IF(3=Assumptions!$B$14+Assumptions!$B$92,Assumptions!$B$90*(1-Assumptions!$B$105),0)+IF(3=Assumptions!$B$14+Assumptions!$B$95,Assumptions!$B$93*(1-Assumptions!$B$105),0)+IF(3=Assumptions!$B$14+Assumptions!$B$98,Assumptions!$B$96*(1-Assumptions!$B$105),0)+IF(3=Assumptions!$B$14+Assumptions!$B$101,Assumptions!$B$99*(1-Assumptions!$B$105),0)+IF(3=Assumptions!$B$14+Assumptions!$B$104,Assumptions!$B$102*(1-Assumptions!$B$105),0) -> 0 | E56: =IF(4=Assumptions!$B$14+Assumptions!$B$92,Assumptions!$B$90*(1-Assumptions!$B$105),0)+IF(4=Assumptions!$B$14+Assumptions!$B$95,Assumptions!$B$93*(1-Assumptions!$B$105),0)+IF(4=Assumptions!$B$14+Assumptions!$B$98,Assumptions!$B$96*(1-Assumptions!$B$105),0)+IF(4=Assumptions!$B$14+Assumptions!$B$101,Assumptions!$B$99*(1-Assumptions!$B$105),0)+IF(4=Assumptions!$B$14+Assumptions!$B$104,Assumptions!$B$102*(1-Assumptions!$B$105),0) -> 17600 | F56: =IF(5=Assumptions!$B$14+Assumptions!$B$92,Assumptions!$B$90*(1-Assumptions!$B$105),0)+IF(5=Assumptions!$B$14+Assumptions!$B$95,Assumptions!$B$93*(1-Assumptions!$B$105),0)+IF(5=Assumptions!$B$14+Assumptions!$B$98,Assumptions!$B$96*(1-Assumptions!$B$105),0)+IF(5=Assumptions!$B$14+Assumptions!$B$101,Assumptions!$B$99*(1-Assumptions!$B$105),0)+IF(5=Assumptions!$B$14+Assumptions!$B$104,Assumptions!$B$102*(1-Assumptions!$B$105),0) -> 0 | G56: =IF(6=Assumptions!$B$14+Assumptions!$B$92,Assumptions!$B$90*(1-Assumptions!$B$105),0)+IF(6=Assumptions!$B$14+Assumptions!$B$95,Assumptions!$B$93*(1-Assumptions!$B$105),0)+IF(6=Assumptions!$B$14+Assumptions!$B$98,Assumptions!$B$96*(1-Assumptions!$B$105),0)+IF(6=Assumptions!$B$14+Assumptions!$B$101,Assumptions!$B$99*(1-Assumptions!$B$105),0)+IF(6=Assumptions!$B$14+Assumptions!$B$104,Assumptions!$B$102*(1-Assumptions!$B$105),0) -> 0 | H56: =IF(7=Assumptions!$B$14+Assumptions!$B$92,Assumptions!$B$90*(1-Assumptions!$B$105),0)+IF(7=Assumptions!$B$14+Assumptions!$B$95,Assumptions!$B$93*(1-Assumptions!$B$105),0)+IF(7=Assumptions!$B$14+Assumptions!$B$98,Assumptions!$B$96*(1-Assumptions!$B$105),0)+IF(7=Assumptions!$B$14+Assumptions!$B$101,Assumptions!$B$99*(1-Assumptions!$B$105),0)+IF(7=Assumptions!$B$14+Assumptions!$B$104,Assumptions!$B$102*(1-Assumptions!$B$105),0) -> 0 | I56: =IF(8=Assumptions!$B$14+Assumptions!$B$92,Assumptions!$B$90*(1-Assumptions!$B$105),0)+IF(8=Assumptions!$B$14+Assumptions!$B$95,Assumptions!$B$93*(1-Assumptions!$B$105),0)+IF(8=Assumptions!$B$14+Assumptions!$B$98,Assumptions!$B$96*(1-Assumptions!$B$105),0)+IF(8=Assumptions!$B$14+Assumptions!$B$101,Assumptions!$B$99*(1-Assumptions!$B$105),0)+IF(8=Assumptions!$B$14+Assumptions!$B$104,Assumptions!$B$102*(1-Assumptions!$B$105),0) -> 0 | J56: =IF(9=Assumptions!$B$14+Assumptions!$B$92,Assumptions!$B$90*(1-Assumptions!$B$105),0)+IF(9=Assumptions!$B$14+Assumptions!$B$95,Assumptions!$B$93*(1-Assumptions!$B$105),0)+IF(9=Assumptions!$B$14+Assumptions!$B$98,Assumptions!$B$96*(1-Assumptions!$B$105),0)+IF(9=Assumptions!$B$14+Assumptions!$B$101,Assumptions!$B$99*(1-Assumptions!$B$105),0)+IF(9=Assumptions!$B$14+Assumptions!$B$104,Assumptions!$B$102*(1-Assumptions!$B$105),0) -> 0 | K56: =IF(10=Assumptions!$B$14+Assumptions!$B$92,Assumptions!$B$90*(1-Assumptions!$B$105),0)+IF(10=Assumptions!$B$14+Assumptions!$B$95,Assumptions!$B$93*(1-Assumptions!$B$105),0)+IF(10=Assumptions!$B$14+Assumptions!$B$98,Assumptions!$B$96*(1-Assumptions!$B$105),0)+IF(10=Assumptions!$B$14+Assumptions!$B$101,Assumptions!$B$99*(1-Assumptions!$B$105),0)+IF(10=Assumptions!$B$14+Assumptions!$B$104,Assumptions!$B$102*(1-Assumptions!$B$105),0) -> 0 | L56: =IF(11=Assumptions!$B$14+Assumptions!$B$92,Assumptions!$B$90*(1-Assumptions!$B$105),0)+IF(11=Assumptions!$B$14+Assumptions!$B$95,Assumptions!$B$93*(1-Assumptions!$B$105),0)+IF(11=Assumptions!$B$14+Assumptions!$B$98,Assumptions!$B$96*(1-Assumptions!$B$105),0)+IF(11=Assumptions!$B$14+Assumptions!$B$101,Assumptions!$B$99*(1-Assumptions!$B$105),0)+IF(11=Assumptions!$B$14+Assumptions!$B$104,Assumptions!$B$102*(1-Assumptions!$B$105),0) -> 0 | M56: =IF(12=Assumptions!$B$14+Assumptions!$B$92,Assumptions!$B$90*(1-Assumptions!$B$105),0)+IF(12=Assumptions!$B$14+Assumptions!$B$95,Assumptions!$B$93*(1-Assumptions!$B$105),0)+IF(12=Assumptions!$B$14+Assumptions!$B$98,Assumptions!$B$96*(1-Assumptions!$B$105),0)+IF(12=Assumptions!$B$14+Assumptions!$B$101,Assumptions!$B$99*(1-Assumptions!$B$105),0)+IF(12=Assumptions!$B$14+Assumptions!$B$104,Assumptions!$B$102*(1-Assumptions!$B$105),0) -> 0 | N56: =IF(13=Assumptions!$B$14+Assumptions!$B$92,Assumptions!$B$90*(1-Assumptions!$B$105),0)+IF(13=Assumptions!$B$14+Assumptions!$B$95,Assumptions!$B$93*(1-Assumptions!$B$105),0)+IF(13=Assumptions!$B$14+Assumptions!$B$98,Assumptions!$B$96*(1-Assumptions!$B$105),0)+IF(13=Assumptions!$B$14+Assumptions!$B$101,Assumptions!$B$99*(1-Assumptions!$B$105),0)+IF(13=Assumptions!$B$14+Assumptions!$B$104,Assumptions!$B$102*(1-Assumptions!$B$105),0) -> 0 | O56: =IF(14=Assumptions!$B$14+Assumptions!$B$92,Assumptions!$B$90*(1-Assumptions!$B$105),0)+IF(14=Assumptions!$B$14+Assumptions!$B$95,Assumptions!$B$93*(1-Assumptions!$B$105),0)+IF(14=Assumptions!$B$14+Assumptions!$B$98,Assumptions!$B$96*(1-Assumptions!$B$105),0)+IF(14=Assumptions!$B$14+Assumptions!$B$101,Assumptions!$B$99*(1-Assumptions!$B$105),0)+IF(14=Assumptions!$B$14+Assumptions!$B$104,Assumptions!$B$102*(1-Assumptions!$B$105),0) -> 0 | P56: =IF(15=Assumptions!$B$14+Assumptions!$B$92,Assumptions!$B$90*(1-Assumptions!$B$105),0)+IF(15=Assumptions!$B$14+Assumptions!$B$95,Assumptions!$B$93*(1-Assumptions!$B$105),0)+IF(15=Assumptions!$B$14+Assumptions!$B$98,Assumptions!$B$96*(1-Assumptions!$B$105),0)+IF(15=Assumptions!$B$14+Assumptions!$B$101,Assumptions!$B$99*(1-Assumptions!$B$105),0)+IF(15=Assumptions!$B$14+Assumptions!$B$104,Assumptions!$B$102*(1-Assumptions!$B$105),0) -> 0 | Q56: =IF(16=Assumptions!$B$14+Assumptions!$B$92,Assumptions!$B$90*(1-Assumptions!$B$105),0)+IF(16=Assumptions!$B$14+Assumptions!$B$95,Assumptions!$B$93*(1-Assumptions!$B$105),0)+IF(16=Assumptions!$B$14+Assumptions!$B$98,Assumptions!$B$96*(1-Assumptions!$B$105),0)+IF(16=Assumptions!$B$14+Assumptions!$B$101,Assumptions!$B$99*(1-Assumptions!$B$105),0)+IF(16=Assumptions!$B$14+Assumptions!$B$104,Assumptions!$B$102*(1-Assumptions!$B$105),0) -> 0 | R56: =IF(17=Assumptions!$B$14+Assumptions!$B$92,Assumptions!$B$90*(1-Assumptions!$B$105),0)+IF(17=Assumptions!$B$14+Assumptions!$B$95,Assumptions!$B$93*(1-Assumptions!$B$105),0)+IF(17=Assumptions!$B$14+Assumptions!$B$98,Assumptions!$B$96*(1-Assumptions!$B$105),0)+IF(17=Assumptions!$B$14+Assumptions!$B$101,Assumptions!$B$99*(1-Assumptions!$B$105),0)+IF(17=Assumptions!$B$14+Assumptions!$B$104,Assumptions!$B$102*(1-Assumptions!$B$105),0) -> 0 | S56: =IF(18=Assumptions!$B$14+Assumptions!$B$92,Assumptions!$B$90*(1-Assumptions!$B$105),0)+IF(18=Assumptions!$B$14+Assumptions!$B$95,Assumptions!$B$93*(1-Assumptions!$B$105),0)+IF(18=Assumptions!$B$14+Assumptions!$B$98,Assumptions!$B$96*(1-Assumptions!$B$105),0)+IF(18=Assumptions!$B$14+Assumptions!$B$101,Assumptions!$B$99*(1-Assumptions!$B$105),0)+IF(18=Assumptions!$B$14+Assumptions!$B$104,Assumptions!$B$102*(1-Assumptions!$B$105),0) -> 0 | T56: =IF(19=Assumptions!$B$14+Assumptions!$B$92,Assumptions!$B$90*(1-Assumptions!$B$105),0)+IF(19=Assumptions!$B$14+Assumptions!$B$95,Assumptions!$B$93*(1-Assumptions!$B$105),0)+IF(19=Assumptions!$B$14+Assumptions!$B$98,Assumptions!$B$96*(1-Assumptions!$B$105),0)+IF(19=Assumptions!$B$14+Assumptions!$B$101,Assumptions!$B$99*(1-Assumptions!$B$105),0)+IF(19=Assumptions!$B$14+Assumptions!$B$104,Assumptions!$B$102*(1-Assumptions!$B$105),0) -> 0 | U56: =IF(20=Assumptions!$B$14+Assumptions!$B$92,Assumptions!$B$90*(1-Assumptions!$B$105),0)+IF(20=Assumptions!$B$14+Assumptions!$B$95,Assumptions!$B$93*(1-Assumptions!$B$105),0)+IF(20=Assumptions!$B$14+Assumptions!$B$98,Assumptions!$B$96*(1-Assumptions!$B$105),0)+IF(20=Assumptions!$B$14+Assumptions!$B$101,Assumptions!$B$99*(1-Assumptions!$B$105),0)+IF(20=Assumptions!$B$14+Assumptions!$B$104,Assumptions!$B$102*(1-Assumptions!$B$105),0) -> 0 | V56: =IF(21=Assumptions!$B$14+Assumptions!$B$92,Assumptions!$B$90*(1-Assumptions!$B$105),0)+IF(21=Assumptions!$B$14+Assumptions!$B$95,Assumptions!$B$93*(1-Assumptions!$B$105),0)+IF(21=Assumptions!$B$14+Assumptions!$B$98,Assumptions!$B$96*(1-Assumptions!$B$105),0)+IF(21=Assumptions!$B$14+Assumptions!$B$101,Assumptions!$B$99*(1-Assumptions!$B$105),0)+IF(21=Assumptions!$B$14+Assumptions!$B$104,Assumptions!$B$102*(1-Assumptions!$B$105),0) -> 0 | W56: =IF(22=Assumptions!$B$14+Assumptions!$B$92,Assumptions!$B$90*(1-Assumptions!$B$105),0)+IF(22=Assumptions!$B$14+Assumptions!$B$95,Assumptions!$B$93*(1-Assumptions!$B$105),0)+IF(22=Assumptions!$B$14+Assumptions!$B$98,Assumptions!$B$96*(1-Assumptions!$B$105),0)+IF(22=Assumptions!$B$14+Assumptions!$B$101,Assumptions!$B$99*(1-Assumptions!$B$105),0)+IF(22=Assumptions!$B$14+Assumptions!$B$104,Assumptions!$B$102*(1-Assumptions!$B$105),0) -> 0 | X56: =IF(23=Assumptions!$B$14+Assumptions!$B$92,Assumptions!$B$90*(1-Assumptions!$B$105),0)+IF(23=Assumptions!$B$14+Assumptions!$B$95,Assumptions!$B$93*(1-Assumptions!$B$105),0)+IF(23=Assumptions!$B$14+Assumptions!$B$98,Assumptions!$B$96*(1-Assumptions!$B$105),0)+IF(23=Assumptions!$B$14+Assumptions!$B$101,Assumptions!$B$99*(1-Assumptions!$B$105),0)+IF(23=Assumptions!$B$14+Assumptions!$B$104,Assumptions!$B$102*(1-Assumptions!$B$105),0) -> 0 | Y56: =IF(24=Assumptions!$B$14+Assumptions!$B$92,Assumptions!$B$90*(1-Assumptions!$B$105),0)+IF(24=Assumptions!$B$14+Assumptions!$B$95,Assumptions!$B$93*(1-Assumptions!$B$105),0)+IF(24=Assumptions!$B$14+Assumptions!$B$98,Assumptions!$B$96*(1-Assumptions!$B$105),0)+IF(24=Assumptions!$B$14+Assumptions!$B$101,Assumptions!$B$99*(1-Assumptions!$B$105),0)+IF(24=Assumptions!$B$14+Assumptions!$B$104,Assumptions!$B$102*(1-Assumptions!$B$105),0) -> 0 | Z56: =SUM(B56:M56) -> 27700 | AA56: =SUM(N56:Y56) -> 0 | AB56: =SUM(B56:Y56) -> 27700
A57: NET CASH FLOW | B57: =B54-B55-B56 -> -26067.497 | C57: =C54-C55-C56 -> 5494.6131 | D57: =D54-D55-D56 -> 7592.1061 | E57: =E54-E55-E56 -> -6912.8219 | F57: =F54-F55-F56 -> 11588.074 | G57: =G54-G55-G56 -> 12536.118 | H57: =H54-H55-H56 -> 13534.185 | I57: =I54-I55-I56 -> 14585.321 | ... Y57: =Y54-Y55-Y56 -> 23267.794 | Z57: =SUM(B57:M57) -> 102381.34 | AA57: =SUM(N57:Y57) -> 270751.37 | AB57: =SUM(B57:Y57) -> 373132.71
A58: Cash balance (end of month) | B58: =Assumptions!$B$62+Assumptions!$B$7+B57 -> 23932.503 | C58: =B58+C57 -> 29427.117 | D58: =C58+D57 -> 37019.223 | E58: =D58+E57 -> 30106.401 | F58: =E58+F57 -> 41694.475 | G58: =F58+G57 -> 54230.592 | H58: =G58+H57 -> 67764.777 | I58: =H58+I57 -> 82350.098 | J58: =I58+J57 -> 98042.857 | ... Y58: =X58+Y57 -> 423132.71
A59: KPIs THE DASHBOARD SHOWS EVERY MONDAY
A60: Revenue per crew-month | B60: =IF(B8=0,0,B23/IF(B7>0,2,1)) -> 28180.932 | C60: =IF(C8=0,0,C23/IF(C7>0,2,1)) -> 37754.069 | D60: =IF(D8=0,0,D23/IF(D7>0,2,1)) -> 38188.139 | E60: =IF(E8=0,0,E23/IF(E7>0,2,1)) -> 38648.253 | F60: =IF(F8=0,0,F23/IF(F7>0,2,1)) -> 39135.974 | G60: =IF(G8=0,0,G23/IF(G7>0,2,1)) -> 39652.958 | H60: =IF(H8=0,0,H23/IF(H7>0,2,1)) -> 40200.962 | I60: =IF(I8=0,0,I23/IF(I7>0,2,1)) -> 40781.845 | ... Y60: =IF(Y8=0,0,Y23/IF(Y7>0,2,1)) -> 45000
A61: Blended cost per lead | B61: =IF(B13=0,0,(B45+B46+B47)/B13) -> 57.22408 | C61: =IF(C13=0,0,(C45+C46+C47)/C13) -> 55.991825 | D61: =IF(D13=0,0,(D45+D46+D47)/D13) -> 55.552212 | E61: =IF(E13=0,0,(E45+E46+E47)/E13) -> 55.093697 | F61: =IF(F13=0,0,(F45+F46+F47)/F13) -> 54.615863 | G61: =IF(G13=0,0,(G45+G46+G47)/G13) -> 54.118326 | H61: =IF(H13=0,0,(H45+H46+H47)/H13) -> 53.600739 | I61: =IF(I13=0,0,(I45+I46+I47)/I13) -> 53.062798 | ... Y61: =IF(Y13=0,0,(Y45+Y46+Y47)/Y13) -> 41.679645
A62: Marketing cost per job sold | B62: =IF(B15=0,0,(B45+B46+B47)/B15) -> 154.35969 | C62: =IF(C15=0,0,(C45+C46+C47)/C15) -> 178.78868 | D62: =IF(D15=0,0,(D45+D46+D47)/D15) -> 176.75646 | E62: =IF(E15=0,0,(E45+E46+E47)/E15) -> 174.65214 | F62: =IF(F15=0,0,(F45+F46+F47)/F15) -> 172.47559 | G62: =IF(G15=0,0,(G45+G46+G47)/G15) -> 170.2269 | H62: =IF(H15=0,0,(H45+H46+H47)/H15) -> 167.90643 | I62: =IF(I15=0,0,(I45+I46+I47)/I15) -> 165.51483 | ... Y62: =IF(Y15=0,0,(Y45+Y46+Y47)/Y15) -> 119.28037
A63: Close rate in use (from Assumptions) | B63: =Assumptions!$B$74 -> 0.7 | C63: =Assumptions!$B$74 -> 0.7 | D63: =Assumptions!$B$74 -> 0.7 | E63: =Assumptions!$B$74 -> 0.7 | F63: =Assumptions!$B$74 -> 0.7 | G63: =Assumptions!$B$74 -> 0.7 | H63: =Assumptions!$B$74 -> 0.7 | I63: =Assumptions!$B$74 -> 0.7 | ... Y63: =Assumptions!$B$74 -> 0.7
A64: Maintenance share of revenue | B64: =IF(B27=0,0,B26/B27) -> 0 | C64: =IF(C27=0,0,C26/C27) -> 0 | D64: =IF(D27=0,0,D26/D27) -> 0.0022445026 | E64: =IF(E27=0,0,E26/E27) -> 0.0044332144 | F64: =IF(F27=0,0,F26/F27) -> 0.0065650591 | G64: =IF(G27=0,0,G26/G27) -> 0.0086389593 | H64: =IF(H27=0,0,H26/H27) -> 0.010653845 | I64: =IF(I27=0,0,I26/I27) -> 0.012608665 | ... Y64: =IF(Y27=0,0,Y26/Y27) -> 0.038645668
A65: Labor as % of revenue | B65: =IF(B27=0,0,B30/B27) -> 0.49338361 | C65: =IF(C27=0,0,C30/C27) -> 0.36827845 | D65: =IF(D27=0,0,D30/D27) -> 0.36327517 | E65: =IF(E27=0,0,E30/E27) -> 0.35816291 | F65: =IF(F27=0,0,F30/F27) -> 0.35294201 | G65: =IF(G27=0,0,G30/G27) -> 0.34761325 | H65: =IF(H27=0,0,H30/H27) -> 0.34217786 | I65: =IF(I27=0,0,I30/I27) -> 0.33663752 | ... Y65: =IF(Y27=0,0,Y30/Y27) -> 0.29703734
A66: Revenue per crew-day (vs Charlie's $1,500 today) | B66: =IF(B29=0,0,B23/B29/Assumptions!$B$10) -> 1341.9492 | C66: =IF(C29=0,0,C23/C29/Assumptions!$B$10) -> 1797.8128 | D66: =IF(D29=0,0,D23/D29/Assumptions!$B$10) -> 1818.4828 | E66: =IF(E29=0,0,E23/E29/Assumptions!$B$10) -> 1840.393 | F66: =IF(F29=0,0,F23/F29/Assumptions!$B$10) -> 1863.6178 | G66: =IF(G29=0,0,G23/G29/Assumptions!$B$10) -> 1888.2361 | H66: =IF(H29=0,0,H23/H29/Assumptions!$B$10) -> 1914.3315 | I66: =IF(I29=0,0,I23/I29/Assumptions!$B$10) -> 1941.9926 | ... Y66: =IF(Y29=0,0,Y23/Y29/Assumptions!$B$10) -> 2142.8571
A67: Break-even LF/month at this overhead (one crew) | B67: =IF(Assumptions!$B$20=1,B50/(Assumptions!$B$5*(1-Assumptions!$B$21-Assumptions!$B$22)),(B50+(Assumptions!$B$26*Assumptions!$B$27*Assumptions!$B$23+Assumptions!$B$27*Assumptions!$B$24+Assumptions!$B$26*Assumptions!$B$28*Assumptions!$B$23*1.5)*(1+Assumptions!$B$25))/(Assumptions!$B$5*(1-Assumptions!$B$22))) -> 1080.1912 | C67: =IF(Assumptions!$B$20=1,C50/(Assumptions!$B$5*(1-Assumptions!$B$21-Assumptions!$B$22)),(C50+(Assumptions!$B$26*Assumptions!$B$27*Assumptions!$B$23+Assumptions!$B$27*Assumptions!$B$24+Assumptions!$B$26*Assumptions!$B$28*Assumptions!$B$23*1.5)*(1+Assumptions!$B$25))/(Assumptions!$B$5*(1-Assumptions!$B$22))) -> 991.69119 | D67: =IF(Assumptions!$B$20=1,D50/(Assumptions!$B$5*(1-Assumptions!$B$21-Assumptions!$B$22)),(D50+(Assumptions!$B$26*Assumptions!$B$27*Assumptions!$B$23+Assumptions!$B$27*Assumptions!$B$24+Assumptions!$B$26*Assumptions!$B$28*Assumptions!$B$23*1.5)*(1+Assumptions!$B$25))/(Assumptions!$B$5*(1-Assumptions!$B$22))) -> 991.69119 | E67: =IF(Assumptions!$B$20=1,E50/(Assumptions!$B$5*(1-Assumptions!$B$21-Assumptions!$B$22)),(E50+(Assumptions!$B$26*Assumptions!$B$27*Assumptions!$B$23+Assumptions!$B$27*Assumptions!$B$24+Assumptions!$B$26*Assumptions!$B$28*Assumptions!$B$23*1.5)*(1+Assumptions!$B$25))/(Assumptions!$B$5*(1-Assumptions!$B$22))) -> 935.72589 | F67: =IF(Assumptions!$B$20=1,F50/(Assumptions!$B$5*(1-Assumptions!$B$21-Assumptions!$B$22)),(F50+(Assumptions!$B$26*Assumptions!$B$27*Assumptions!$B$23+Assumptions!$B$27*Assumptions!$B$24+Assumptions!$B$26*Assumptions!$B$28*Assumptions!$B$23*1.5)*(1+Assumptions!$B$25))/(Assumptions!$B$5*(1-Assumptions!$B$22))) -> 935.72589 | G67: =IF(Assumptions!$B$20=1,G50/(Assumptions!$B$5*(1-Assumptions!$B$21-Assumptions!$B$22)),(G50+(Assumptions!$B$26*Assumptions!$B$27*Assumptions!$B$23+Assumptions!$B$27*Assumptions!$B$24+Assumptions!$B$26*Assumptions!$B$28*Assumptions!$B$23*1.5)*(1+Assumptions!$B$25))/(Assumptions!$B$5*(1-Assumptions!$B$22))) -> 935.72589 | H67: =IF(Assumptions!$B$20=1,H50/(Assumptions!$B$5*(1-Assumptions!$B$21-Assumptions!$B$22)),(H50+(Assumptions!$B$26*Assumptions!$B$27*Assumptions!$B$23+Assumptions!$B$27*Assumptions!$B$24+Assumptions!$B$26*Assumptions!$B$28*Assumptions!$B$23*1.5)*(1+Assumptions!$B$25))/(Assumptions!$B$5*(1-Assumptions!$B$22))) -> 935.72589 | I67: =IF(Assumptions!$B$20=1,I50/(Assumptions!$B$5*(1-Assumptions!$B$21-Assumptions!$B$22)),(I50+(Assumptions!$B$26*Assumptions!$B$27*Assumptions!$B$23+Assumptions!$B$27*Assumptions!$B$24+Assumptions!$B$26*Assumptions!$B$28*Assumptions!$B$23*1.5)*(1+Assumptions!$B$25))/(Assumptions!$B$5*(1-Assumptions!$B$22))) -> 935.72589 | ... Y67: =IF(Assumptions!$B$20=1,Y50/(Assumptions!$B$5*(1-Assumptions!$B$21-Assumptions!$B$22)),(Y50+(Assumptions!$B$26*Assumptions!$B$27*Assumptions!$B$23+Assumptions!$B$27*Assumptions!$B$24+Assumptions!$B$26*Assumptions!$B$28*Assumptions!$B$23*1.5)*(1+Assumptions!$B$25))/(Assumptions!$B$5*(1-Assumptions!$B$22))) -> 935.72589

Sheet Unit economics
A1: Unit economics - one job, one crew-month, one maintenance customer
A2: ONE JOB (average)
A3: Linear feet | B3: =Assumptions!$B$17 -> 100
A4: Price to customer | B4: =B3*Assumptions!$B$5 -> 5000
A5: Crew labor (share of one crew-month, at target LF) | B5: =B3/Assumptions!$B$13*(Assumptions!$B$26*Assumptions!$B$27*Assumptions!$B$23+Assumptions!$B$27*Assumptions!$B$24+Assumptions!$B$26*Assumptions!$B$28*Assumptions!$B$23*1.5)*(1+Assumptions!$B$25) -> 1544.89
A6: Materials + fuel (20%) | B6: =B4*Assumptions!$B$22 -> 1000
A7: Gross profit per job | B7: =B4-B5-B6 -> 2455.11
A8: Gross margin | B8: =B7/B4 -> 0.491022
A9: Crew days per job (at target LF/month) | B9: =B3/(Assumptions!$B$13/Assumptions!$B$10) -> 2.3333333
A10: ONE CREW-MONTH (at target)
A11: LF per month | B11: =Assumptions!$B$13 -> 900
A12: Revenue per crew-month | B12: =B11*Assumptions!$B$5 -> 45000
A13: Crew wages before burden (size x hours x $/hr + lead premium + OT) | B13: =Assumptions!$B$26*Assumptions!$B$27*Assumptions!$B$23+Assumptions!$B$27*Assumptions!$B$24+Assumptions!$B$26*Assumptions!$B$28*Assumptions!$B$23*1.5 -> 12196.5
A14: Crew wages with burden (the fixed cost of a crew) | B14: =B13*(1+Assumptions!$B$25) -> 13904.01
A15: Labor as % of revenue at target (Charlie's rule of thumb: 32%) | B15: =B14/B12 -> 0.308978 | C15: Fixed crew cost divided by revenue: the crew costs the same at 400 LF or 900 LF, so every extra foot per day drops straight to margin.
A16: Gross profit per crew-month | B16: =B12*(1-Assumptions!$B$22)-B14 -> 22095.99
A17: ONE MAINTENANCE CUSTOMER
A18: Plan price per visit | B18: =Assumptions!$B$30 -> 249
A19: Cost per visit | B19: =Assumptions!$B$37 -> 70
A20: Gross profit per visit | B20: =B18-B19 -> 179
A21: Gross margin per visit | B21: =B20/B18 -> 0.7188755
A22: Visits over 5 years | B22: =5*Assumptions!$B$33 -> 3.75
A23: 5-year gross profit per plan customer | B23: =B20*B22 -> 671.25
A24: Referral value: 1 in 4 plan customers refers one job | B24: =0.25*B7 -> 613.7775 | C24: Not in the proforma - upside only.
A25: TODAY vs TARGET (productivity is the margin)
A26: Today: LF per month (Charlie, before Ned) | B26: =Assumptions!$B$6 -> 400
A27: Today: revenue per crew-month (drain LF x $/LF + other-work days x $/day) | B27: =B26*Assumptions!$B$5+MAX(0,Assumptions!$B$10-B26/Assumptions!$B$11)*Assumptions!$B$12 -> 31697.674
A28: Today: revenue per crew-day (model) vs Charlie's $1,500 | B28: =B27/Assumptions!$B$10 -> 1509.4131 | C28: Charlie today: about 9 crew-days on drains, 12 on other work to fill the month - matches his $1,500/day. The plan below replaces those 12 other-work days with drains too.
A29: Today: labor as % of revenue | B29: =B14/B27 -> 0.43864448 | C29: At today's 400 LF the crew is expensive relative to revenue; at 900 LF it is not. That gap is the whole growth case.
A30: Target: labor as % of revenue | B30: =B15 -> 0.308978
A31: Fixed monthly overhead before any crew (owner draw, existing payments, software, bookkeeping, shop) | B31: =Assumptions!$B$78+Assumptions!$B$80+Assumptions!$B$81+Assumptions!$B$82+Assumptions!$B$83 -> 15500
A32: Break-even LF per month, one crew (fixed overhead + one crew's cost + its insurance, after materials) | B32: =(B31+B14+Assumptions!$B$79)/(Assumptions!$B$5*(1-Assumptions!$B$22)) -> 757.60025
A33: Break-even as % of one crew's target | B33: =B32/Assumptions!$B$13 -> 0.84177806

Sheet Scenarios
A1: Three scenarios - year-2 run rate (month 24) and 24-month totals
A2: Change the blue cells; everything below recalculates using the same cost structure as the proforma.
B4: Conservative | C4: Base (Charlie's goal) | D4: Stretch
A5: LF per crew per month | B5: 700 | C5: 900 | D5: 1000
A6: Crews running by month 24 | B6: 1 | C6: 2 | D6: 2
A7: Average $/LF | B7: 45 | C7: 50 | D7: 55
A8: Active Drain Check plans at month 24 | B8: 40 | C8: 90 | D8: 140
A9: Monthly install revenue | B9: =B5*B6*B7 -> 31500 | C9: =C5*C6*C7 -> 90000 | D9: =D5*D6*D7 -> 110000
A10: Monthly maintenance revenue | B10: =B8/12*Assumptions!$B$33*Assumptions!$B$30 -> 622.5 | C10: =C8/12*Assumptions!$B$33*Assumptions!$B$30 -> 1400.625 | D10: =D8/12*Assumptions!$B$33*Assumptions!$B$30 -> 2178.75
A11: Monthly revenue | B11: =B9+B10 -> 32122.5 | C11: =C9+C10 -> 91400.625 | D11: =D9+D10 -> 112178.75
A12: Gross profit (installs less materials and crew wages; plans at plan margin) | B12: =B9*(1-Assumptions!$B$22)-B6*(Assumptions!$B$26*Assumptions!$B$27*Assumptions!$B$23+Assumptions!$B$27*Assumptions!$B$24+Assumptions!$B$26*Assumptions!$B$28*Assumptions!$B$23*1.5)*(1+Assumptions!$B$25)+B10*(1-Assumptions!$B$37/Assumptions!$B$30) -> 11743.49 | C12: =C9*(1-Assumptions!$B$22)-C6*(Assumptions!$B$26*Assumptions!$B$27*Assumptions!$B$23+Assumptions!$B$27*Assumptions!$B$24+Assumptions!$B$26*Assumptions!$B$28*Assumptions!$B$23*1.5)*(1+Assumptions!$B$25)+C10*(1-Assumptions!$B$37/Assumptions!$B$30) -> 45198.855 | D12: =D9*(1-Assumptions!$B$22)-D6*(Assumptions!$B$26*Assumptions!$B$27*Assumptions!$B$23+Assumptions!$B$27*Assumptions!$B$24+Assumptions!$B$26*Assumptions!$B$28*Assumptions!$B$23*1.5)*(1+Assumptions!$B$25)+D10*(1-Assumptions!$B$37/Assumptions!$B$30) -> 61758.23
A13: Overhead (one crew) / (two crews incl. loan) | B13: =IF(B6=1,'Proforma 24 mo'!D50,'Proforma 24 mo'!Y50) -> 25763.638 | C13: =IF(C6=1,'Proforma 24 mo'!D50,'Proforma 24 mo'!Y50) -> 23525.026 | D13: =IF(D6=1,'Proforma 24 mo'!D50,'Proforma 24 mo'!Y50) -> 23525.026
A14: Operating profit per month | B14: =B12-B13 -> -14020.148 | C14: =C12-C13 -> 21673.829 | D14: =D12-D13 -> 38233.204
A15: Operating profit per year (run rate) | B15: =B14*12 -> -168241.77 | C15: =C14*12 -> 260085.95 | D15: =D14*12 -> 458798.45
A16: Operating margin | B16: =IF(B11=0,0,B14/B11) -> -0.43645879 | C16: =IF(C11=0,0,C14/C11) -> 0.23712999 | D16: =IF(D11=0,0,D14/D11) -> 0.34082395
A17: Estimates needed per month (jobs / Charlie's close rate) | B17: =B5*B6/Assumptions!$B$17/Assumptions!$B$74 -> 10 | C17: =C5*C6/Assumptions!$B$17/Assumptions!$B$74 -> 25.714286 | D17: =D5*D6/Assumptions!$B$17/Assumptions!$B$74 -> 28.571429
A18: Leads needed per month (at ~45% of leads booking an estimate) | B18: =B17/0.45 -> 22.222222 | C18: =C17/0.45 -> 57.142857 | D18: =D17/0.45 -> 63.492063
A19: What has to be true
A20: Conservative: one crew at 700 LF and $45/LF still clears overhead - the plan fails safe.
A21: Base: two crews at 900 LF, $50/LF, 90 plan customers - Charlie's stated goal, reached in month 10-12 of the proforma. Close rate on estimates is Charlie's 70% (Assumptions, yellow cell).
A22: Stretch: pricing power from reviews + Moasure proposals lifts $/LF to $55; 140 plan customers = the sellable recurring book.

Sheet Equipment plan
A1: Path to owning Crew 2's equipment - rent first, buy on proof
A2: Crew 1 already owns a big trailer, a skid steer and a mini excavator (no capex in this plan). Crew 2 needs its own set. Rent-to-prove, then buy; every date is driven by the Crew 2 start month on Assumptions.
A4: Item | B4: Purchase price | C4: Rent / month | D4: Months rented | E4: Rent paid before buying | F4: Purchase month | G4: Down payment (20%) | H4: Loan payment / mo | I4: Loan paid off (month) | J4: Own-vs-rent break-even (months)
A5: Mini excavator (used) | B5: =Assumptions!$B$90 -> 50000 | C5: =Assumptions!$B$91 -> 2000 | D5: =Assumptions!$B$92 -> 3 | E5: =C5*D5 -> 6000 | F5: =Assumptions!$B$14+D5 -> 4 | G5: =B5*(1-Assumptions!$B$105) -> 10000 | H5: =-PMT(Assumptions!$B$106/12,Assumptions!$B$107,B5*Assumptions!$B$105) -> 830.33421 | I5: =F5+Assumptions!$B$107 -> 64 | J5: =IF(C5=0,"n/a",B5/C5) -> 25
A6: Skid steer / CTL (used) | B6: =Assumptions!$B$93 -> 38000 | C6: =Assumptions!$B$94 -> 1700 | D6: =Assumptions!$B$95 -> 3 | E6: =C6*D6 -> 5100 | F6: =Assumptions!$B$14+D6 -> 4 | G6: =B6*(1-Assumptions!$B$105) -> 7600 | H6: =-PMT(Assumptions!$B$106/12,Assumptions!$B$107,B6*Assumptions!$B$105) -> 631.054 | I6: =F6+Assumptions!$B$107 -> 64 | J6: =IF(C6=0,"n/a",B6/C6) -> 22.352941
A7: Dump trailer 7x14 (new) | B7: =Assumptions!$B$96 -> 9500 | C7: =Assumptions!$B$97 -> 600 | D7: =Assumptions!$B$98 -> 0 | E7: =C7*D7 -> 0 | F7: =Assumptions!$B$14+D7 -> 1 | G7: =B7*(1-Assumptions!$B$105) -> 1900 | H7: =-PMT(Assumptions!$B$106/12,Assumptions!$B$107,B7*Assumptions!$B$105) -> 157.7635 | I7: =F7+Assumptions!$B$107 -> 61 | J7: =IF(C7=0,"n/a",B7/C7) -> 15.833333
A8: Truck 3/4-ton (used) | B8: =Assumptions!$B$99 -> 35000 | C8: =Assumptions!$B$100 -> 0 | D8: =Assumptions!$B$101 -> 0 | E8: =C8*D8 -> 0 | F8: =Assumptions!$B$14+D8 -> 1 | G8: =B8*(1-Assumptions!$B$105) -> 7000 | H8: =-PMT(Assumptions!$B$106/12,Assumptions!$B$107,B8*Assumptions!$B$105) -> 581.23395 | I8: =F8+Assumptions!$B$107 -> 61 | J8: =IF(C8=0,"n/a",B8/C8) -> n/a
A9: Tools, laser, compactor, PPE | B9: =Assumptions!$B$102 -> 6000 | C9: =Assumptions!$B$103 -> 0 | D9: =Assumptions!$B$104 -> 0 | E9: =C9*D9 -> 0 | F9: =Assumptions!$B$14+D9 -> 1 | G9: =B9*(1-Assumptions!$B$105) -> 1200 | H9: =-PMT(Assumptions!$B$106/12,Assumptions!$B$107,B9*Assumptions!$B$105) -> 99.640105 | I9: =F9+Assumptions!$B$107 -> 61 | J9: =IF(C9=0,"n/a",B9/C9) -> n/a
A10: Total | B10: =SUM(B5:B9) -> 138500 | E10: =SUM(E5:E9) -> 11100 | G10: =SUM(G5:G9) -> 27700 | H10: =SUM(H5:H9) -> 2300.0258
A12: How to read it
A13: Own-vs-rent break-even: purchase price / monthly rent. A mini-ex at $50,000 vs $2,000/month breaks even at 25 months of use - so anything Crew 2 will run for more than two years should be owned; the 3-month rental is insurance against Crew 2 not working out, not a long-term plan.
A14: The purchase month is the Crew 2 start month plus the months rented. Decision rule for pulling the trigger early or late: buy when Crew 2 has installed its target LF in two consecutive months; keep renting if it has not.
A15: Down payments hit cash in the purchase month (Proforma: 'Cash out - Crew 2 down payments'); loan payments run 60 months from there. Rent paid before buying is money spent to de-risk the purchase - budgeted, not wasted.
A16: Crew 1's set is already owned: no purchases are modeled for it. Its existing payments, if any, sit in 'Existing truck / equipment payments' on Assumptions.
A17: Time to full ownership of Crew 2's set: trailer, truck and tools on day one; mini-ex and skid steer bought in month start+3; all loans paid off 60 months after that (month 64 in the base case, since both crews now launch in month 1). Equity builds from the first payment; the machines outlast the loans.

Sheet 5-year plan
A1: Five-year plan - annual, safe-scaling (Year 1-2 pull from the 24-month proforma; Years 3-5 from the blue inputs below)
A2: Blue = input. Every year is gated: the next crew is added only when the previous one has run at target for 3 months, backlog > 4 weeks, and cash > 2 months of overhead.
B4: Today (run rate) | C4: Year 1 | D4: Year 2 | E4: Year 3 | F4: Year 4 | G4: Year 5 | H4: Notes
A5: CAPACITY
A6: Crews at year end | B6: 1 | C6: 2 | D6: 2 | E6: 3 | F6: 4 | G6: 4 | H6: Today = Charlie's one crew before Ned. Both crews launch together in year 1, funded by the initial investment; Crew 3 in year 3, Crew 4 in year 4, then consolidate. Change to test a slower or faster path.
A7: Average crews running during the year | B7: 1 | C7: 2 | D7: 2 | E7: 2.5 | F7: 3.5 | G7: 4 | H7: Both crews run the whole of year 1 - no ramp. Crew 3 starts mid-year 3; Crew 4 mid-year 4.
A8: LF per crew per year at target x utilization | B8: 4800 | C8: ='Proforma 24 mo'!Z17/C7 -> 9444.1707 | D8: ='Proforma 24 mo'!AA17/D7 -> 10785.056 | E8: =Assumptions!$B$13*12*0.95 -> 10260 | F8: =Assumptions!$B$13*12*0.95 -> 10260 | G8: =Assumptions!$B$13*12*0.95 -> 10260 | H8: Today = 400 LF x 12. Years 3-5: 900 LF x 12 x 95% utilization.
A9: Total LF installed | B9: =B7*B8 -> 4800 | C9: ='Proforma 24 mo'!Z17 -> 18888.341 | D9: ='Proforma 24 mo'!AA17 -> 21570.112 | E9: =E7*E8 -> 25650 | F9: =F7*F8 -> 35910 | G9: =G7*G8 -> 41040
A10: REVENUE
A11: Average $/LF (3% a year after year 2 - reviews and the map justify it) | B11: =Assumptions!$B$5 -> 50 | C11: =Assumptions!$B$5 -> 50 | D11: =Assumptions!$B$5 -> 50 | E11: =D11*1.03 -> 51.5 | F11: =E11*1.03 -> 53.045 | G11: =F11*1.03 -> 54.63635
A12: Drainage install revenue (french drains only) | B12: ='Unit economics'!B27*12 -> 380372.09 | C12: ='Proforma 24 mo'!Z23 -> 944417.07 | D12: ='Proforma 24 mo'!AA23 -> 1078505.6 | E12: =E9*E11 -> 1320975 | F12: =F9*F11 -> 1904845.9 | G12: =G9*G11 -> 2242275.8 | H12: Today's column is Charlie's actual mix of drain and other work (Unit economics tab); years 1-5 of the plan are drains only.
A13: Drain Check active plans at year end | B13: 0 | C13: ='Proforma 24 mo'!M25 -> 112.90458 | D13: ='Proforma 24 mo'!Y25 -> 232.47726 | E13: 355 | F13: 540 | G13: 745 | H13: 60% of customers take a cleaning plan (half yearly, half every two years); about 8%/yr churn. Years 1-2 come from the 24-month proforma.
A14: Drain Check revenue | B14: 0 | C14: ='Proforma 24 mo'!Z26 -> 9579.7241 | D14: ='Proforma 24 mo'!AA26 -> 33603.68 | E14: =(D13+E13)/2*Assumptions!$B$30 -> 73140.918 | F14: =(E13+F13)/2*Assumptions!$B$30*1.03 -> 114770.32 | G14: =(F13+G13)/2*Assumptions!$B$30*1.06 -> 169581.45
A15: TOTAL REVENUE | B15: =B12+B14 -> 380372.09 | C15: =C12+C14 -> 953996.79 | D15: =D12+D14 -> 1112109.3 | E15: =E12+E14 -> 1394115.9 | F15: =F12+F14 -> 2019616.3 | G15: =G12+G14 -> 2411857.3
A16: DIRECT COSTS
A17: Crew labor (crews x fixed crew cost; wages +3%/yr from year 3) | B17: =B7*(Assumptions!$B$26*Assumptions!$B$27*Assumptions!$B$23+Assumptions!$B$27*Assumptions!$B$24)*(1+Assumptions!$B$25)*12 -> 166848.12 | C17: ='Proforma 24 mo'!Z30 -> 333696.24 | D17: ='Proforma 24 mo'!AA30 -> 333696.24 | E17: =E7*(Assumptions!$B$26*Assumptions!$B$27*Assumptions!$B$23+Assumptions!$B$27*Assumptions!$B$24)*(1+Assumptions!$B$25)*12*1.03 -> 429633.91 | F17: =F7*(Assumptions!$B$26*Assumptions!$B$27*Assumptions!$B$23+Assumptions!$B$27*Assumptions!$B$24)*(1+Assumptions!$B$25)*12*1.03^2 -> 619532.1 | G17: =G7*(Assumptions!$B$26*Assumptions!$B$27*Assumptions!$B$23+Assumptions!$B$27*Assumptions!$B$24)*(1+Assumptions!$B$25)*12*1.03^3 -> 729277.78 | H17: Change the wage on Assumptions and every year moves.
A18: Materials + fuel (20% of install revenue) | B18: =B12*Assumptions!$B$22 -> 76074.419 | C18: ='Proforma 24 mo'!Z31 -> 188883.41 | D18: ='Proforma 24 mo'!AA31 -> 215701.12 | E18: =E12*Assumptions!$B$22 -> 264195 | F18: =F12*Assumptions!$B$22 -> 380969.19 | G18: =G12*Assumptions!$B$22 -> 448455.16
A19: Drain Check visit costs | B19: 0 | C19: ='Proforma 24 mo'!Z32 -> 2693.0951 | D19: ='Proforma 24 mo'!AA32 -> 9446.8177 | E19: =E14/Assumptions!$B$30*Assumptions!$B$37 -> 20561.704 | F19: =F14/Assumptions!$B$30/1.03*Assumptions!$B$37 -> 31325 | G19: =G14/Assumptions!$B$30/1.06*Assumptions!$B$37 -> 44975
A20: GROSS PROFIT | B20: =B15-B17-B18-B19 -> 137449.55 | C20: =C15-C17-C18-C19 -> 428724.05 | D20: =D15-D17-D18-D19 -> 553265.12 | E20: =E15-E17-E18-E19 -> 679725.31 | F20: =F15-F17-F18-F19 -> 987789.99 | G20: =G15-G17-G18-G19 -> 1189149.3
A21: Gross margin | B21: =IF(B15=0,0,B20/B15) -> 0.36135552 | C21: =IF(C15=0,0,C20/C15) -> 0.44939778 | D21: =IF(D15=0,0,D20/D15) -> 0.49749167 | E21: =IF(E15=0,0,E20/E15) -> 0.48756728 | F21: =IF(F15=0,0,F20/F15) -> 0.48909786 | G21: =IF(G15=0,0,G20/G15) -> 0.49304299
A22: OVERHEAD - the layers that let the company handle the volume
A23: Owner draw (years 3-5 step up with the company, proportional to the year-1 draw) | B23: =Assumptions!$B$78*12 -> 150000 | C23: =Assumptions!$B$78*12 -> 150000 | D23: =Assumptions!$B$78*12 -> 150000 | E23: =Assumptions!$B$78*12*1.16667 -> 175000.5 | F23: =Assumptions!$B$78*12*1.33333 -> 199999.5 | G23: =Assumptions!$B$78*12*1.5 -> 225000 | H23: Charlie's pay rises with the company - change the Owner draw cell on Assumptions and all six years move together, in the same proportion. Before write-offs - see the Write-offs and taxes tab for what this actually costs him after deductions.
A24: Office admin / bookkeeper (part-time year 2, full-time year 3) | B24: 0 | C24: 0 | D24: 24000 | E24: 42000 | F24: 48000 | G24: 50000 | H24: Answers the phone the software cannot, books, AP/AR, reviews, scheduling. Hire when two crews are running.
A25: Operations manager (runs crews, purchasing, quality) | B25: 0 | C25: 0 | D25: 0 | E25: 48750 | F25: 70000 | G25: 72000 | H25: Hired in month 4 of year 3 (about $65K/yr), before Crew 3 starts, so Charlie is not the bottleneck at three crews. Usually the best crew lead, promoted.
A26: Estimator / sales (runs Moasure surveys and quotes) | B26: 0 | C26: 0 | D26: 0 | E26: 0 | F26: 55000 | G26: 58000 | H26: At four crews Charlie cannot run 40+ estimates a month alone. Base + commission.
A27: Crew-lead bonus pool (LF/day and callbacks) | B27: 0 | C27: 0 | D27: 6000 | E27: 12000 | F27: 18000 | G27: 20000 | H27: $500/quarter per lead when the crew beats 43 LF/day with no callbacks.
A28: Insurance - GL, auto, equipment, WC excess (per crew) | B28: =Assumptions!$B$79*12 -> 10800 | C28: ='Proforma 24 mo'!Z38 -> 10800 | D28: ='Proforma 24 mo'!AA38 -> 10800 | E28: =Assumptions!$B$79*12+9000*(E6-1) -> 28800 | F28: =Assumptions!$B$79*12+9000*(F6-1) -> 37800 | G28: =Assumptions!$B$79*12+9000*(G6-1) -> 37800 | H28: Today's premium plus about $9K per additional crew (auto, equipment, WC); get quotes before each hire.
A29: Truck + equipment loan payments (existing + one set per crew) | B29: =Assumptions!$B$80*12 -> 21600 | C29: ='Proforma 24 mo'!Z39+'Proforma 24 mo'!Z49 -> 44816.144 | D29: ='Proforma 24 mo'!AA39+'Proforma 24 mo'!AA49 -> 49200.309 | E29: =Assumptions!$B$80*12+'Equipment plan'!H10*12*(E6-1) -> 76800.618 | F29: =Assumptions!$B$80*12+'Equipment plan'!H10*12*(F6-1) -> 104400.93 | G29: =Assumptions!$B$80*12+'Equipment plan'!H10*12*(G6-1) -> 104400.93 | H29: Each new crew carries its own set (Equipment plan tab); rent-first 3 months before each purchase.
A30: Yard space used (sq ft) - Cottondale | B30: 0 | C30: =Assumptions!$B$84 -> 2500 | D30: =Assumptions!$B$84 -> 2500 | E30: 3000 | F30: 4000 | G30: 4000 | H30: About 1,000 sq ft more per crew for its set and material bins. Years 1-2 follow the Assumptions tab.
A31: Yard rent rate ($ per sq ft per month) | B31: 0 | C31: =Assumptions!$B$85 -> 0.85 | D31: =Assumptions!$B$85 -> 0.85 | E31: =D31*1.05 -> 0.8925 | F31: =E31*1.05 -> 0.937125 | G31: =F31*1.05 -> 0.98398125 | H31: Steps up 5%/yr from year 3 (change the multiplier); market in 70815 is about $1.19.
A32: Yard / shop rent (sq ft x rate x 12) | B32: =B30*B31*12 -> 0 | C32: ='Proforma 24 mo'!Z43 -> 25500 | D32: ='Proforma 24 mo'!AA43 -> 25500 | E32: =E30*E31*12 -> 32130 | F32: =F30*F31*12 -> 44982 | G32: =G30*G31*12 -> 47231.1 | H32: Years 1-2 from the proforma (start month applies).
A33: Software, phones, hosting, payment fees (+ per crew) | B33: =Assumptions!$B$81*12 -> 4200 | C33: ='Proforma 24 mo'!Z40 -> 4200 | D33: ='Proforma 24 mo'!AA40 -> 4200 | E33: =4200+1200*E6 -> 7800 | F33: =4200+1200*F6 -> 9000 | G33: =4200+1200*G6 -> 9000
A34: Bookkeeping / CPA / payroll service | B34: =Assumptions!$B$82*12 -> 3000 | C34: ='Proforma 24 mo'!Z41 -> 3000 | D34: ='Proforma 24 mo'!AA41 -> 3000 | E34: 7200 | F34: 9000 | G34: 9600 | H34: QuickBooks Online + payroll service + monthly close; CPA quarterly. Grows with headcount.
A35: Marketing (Google LSA, Meta, content) - ~5% of revenue from year 3 | B35: =(Assumptions!$B$64+Assumptions!$B$67+Assumptions!$B$76)*12 -> 21600 | C35: ='Proforma 24 mo'!Z45+'Proforma 24 mo'!Z46+'Proforma 24 mo'!Z47 -> 31440 | D35: ='Proforma 24 mo'!AA45+'Proforma 24 mo'!AA46+'Proforma 24 mo'!AA47 -> 32400 | E35: =E15*0.05 -> 69705.796 | F35: =F15*0.05 -> 100980.81 | G35: =G15*0.045 -> 108533.58 | H35: Falls as a % of revenue as reviews, referrals and the plan book compound.
A36: Shop, tools, uniforms, training, misc (+ per crew) | B36: =Assumptions!$B$83*12 -> 7200 | C36: ='Proforma 24 mo'!Z42 -> 7200 | D36: ='Proforma 24 mo'!AA42 -> 7200 | E36: =7200+3000*E6 -> 16200 | F36: =7200+3000*F6 -> 19200 | G36: =7200+3000*G6 -> 19200
A37: Crew hiring, training and rent-first equipment months (per new crew) | B37: 0 | C37: ='Proforma 24 mo'!Z48 -> 15600 | D37: ='Proforma 24 mo'!AA48 -> 0 | E37: =(E6-D6)*('Equipment plan'!E10+Assumptions!$B$108) -> 15600 | F37: =(F6-E6)*('Equipment plan'!E10+Assumptions!$B$108) -> 15600 | G37: =(G6-F6)*('Equipment plan'!E10+Assumptions!$B$108) -> 0
A38: GROWTH & OPERATIONS LEAD (Ned) - proposed, for discussion
A39: Base ($/yr) - fractional, about 25 hours a week | B39: 0 | C39: =Assumptions!$B$144 -> 60000 | D39: =Assumptions!$B$144 -> 60000 | E39: =Assumptions!$B$145 -> 66000 | F39: =Assumptions!$B$146 -> 72000 | G39: =Assumptions!$B$146 -> 72000 | H39: Pulled straight from the Ned assumptions above - change those cells and this tab and the Ned proforma tab move together. For scale: Baton Rouge general/operations managers average $129,840 full-time (BLS OEWS).
A40: Growth share - % of operating profit above the baseline year | B40: 0 | C40: =Assumptions!$B$121 -> 0.1 | D40: =Assumptions!$B$121 -> 0.1 | E40: =Assumptions!$B$121 -> 0.1 | F40: =Assumptions!$B$121 -> 0.1 | G40: =Assumptions!$B$121 -> 0.1 | H40: Paid only on profit above what the business makes today; nothing on the baseline. Same cell as the Ned proforma tab.
A41: Baseline operating profit (today's run rate after owner draw, floored at 0) | B41: =MAX(0,B45) -> 0 | C41: =MAX(0,B45) -> 0 | D41: =MAX(0,B45) -> 0 | E41: =MAX(0,B45) -> 0 | F41: =MAX(0,B45) -> 0 | G41: =MAX(0,B45) -> 0 | H41: Today's column, computed below. The share is earned only on profit the growth creates.
A42: Growth lead cost (base + share) | B42: 0 | C42: =C39+C40*MAX(0,C44-C41) -> 73616.79 | D42: =D39+D40*MAX(0,D44-D41) -> 84096.481 | E42: =E39+E40*MAX(0,E44-E41) -> 80773.839 | F42: =F39+F40*MAX(0,F44-F41) -> 97582.675 | G42: =G39+G40*MAX(0,G44-G41) -> 114838.37 | H42: Share is computed on operating profit before the share itself.
A43: TOTAL OVERHEAD (excl. growth lead) | B43: =SUM(B23:B37)-B30-B31 -> 218400 | C43: =SUM(C23:C37)-C30-C31 -> 292556.14 | D43: =SUM(D23:D37)-D30-D31 -> 312300.31 | E43: =SUM(E23:E37)-E30-E31 -> 531986.91 | F43: =SUM(F23:F37)-F30-F31 -> 731963.24 | G43: =SUM(G23:G37)-G30-G31 -> 760765.6
A44: Operating profit before growth lead | B44: =B20-B43 -> -80950.446 | C44: =C20-C43 -> 136167.9 | D44: =D20-D43 -> 240964.81 | E44: =E20-E43 -> 147738.39 | F44: =F20-F43 -> 255826.75 | G44: =G20-G43 -> 428383.71
A45: OPERATING PROFIT after growth lead (owner draw already deducted) | B45: =B44-B42 -> -80950.446 | C45: =C44-C42 -> 62551.111 | D45: =D44-D42 -> 156868.33 | E45: =E44-E42 -> 66964.552 | F45: =F44-F42 -> 158244.07 | G45: =G44-G42 -> 313545.34
A46: Operating margin | B46: =IF(B15=0,0,B45/B15) -> -0.2128191 | C46: =IF(C15=0,0,C45/C15) -> 0.065567422 | D46: =IF(D15=0,0,D45/D15) -> 0.14105478 | E46: =IF(E15=0,0,E45/E15) -> 0.048033705 | F46: =IF(F15=0,0,F45/F15) -> 0.078353534 | G46: =IF(G15=0,0,G45/G15) -> 0.13000161
A47: CASH AND SAFETY
A48: Equipment down payments (20% per new crew set) | B48: 0 | C48: ='Proforma 24 mo'!Z56 -> 27700 | D48: ='Proforma 24 mo'!AA56 -> 0 | E48: =(E6-D6)*'Equipment plan'!G10 -> 27700 | F48: =(F6-E6)*'Equipment plan'!G10 -> 27700 | G48: =(G6-F6)*'Equipment plan'!G10 -> 0
A49: Cash at year end (opening + profit - down payments) | B49: =Assumptions!$B$62 -> 25000 | C49: =B49+C45-C48 -> 59851.111 | D49: =C49+D45-D48 -> 216719.44 | E49: =D49+E45-E48 -> 255983.99 | F49: =E49+F45-F48 -> 386528.06 | G49: =F49+G45-G48 -> 700073.4 | H49: Before distributions beyond the owner draw and before income tax.
A50: Reserve rule: 2 months of overhead | B50: =B43/6 -> 36400 | C50: =C43/6 -> 48759.357 | D50: =D43/6 -> 52050.052 | E50: =E43/6 -> 88664.486 | F50: =F43/6 -> 121993.87 | G50: =G43/6 -> 126794.27 | H50: Cash must stay above this before any hire or purchase.
A51: Reserve met? | B51: =IF(B49>=B50,"yes","NO") -> NO | C51: =IF(C49>=C50,"yes","NO") -> yes | D51: =IF(D49>=D50,"yes","NO") -> yes | E51: =IF(E49>=E50,"yes","NO") -> yes | F51: =IF(F49>=F50,"yes","NO") -> yes | G51: =IF(G49>=G50,"yes","NO") -> yes
A52: WHAT THE COMPANY IS WORTH (indicative)
A53: Seller's discretionary earnings (operating profit + owner draw) | B53: =B45+B23 -> 69049.554 | C53: =C45+C23 -> 212551.11 | D53: =D45+D23 -> 306868.33 | E53: =E45+E23 -> 241965.05 | F53: =F45+F23 -> 358243.57 | G53: =G45+G23 -> 538545.34
A54: SDE multiple (BizBuySell landscaping median 2021-25: 2.46x) | B54: 2.46 | C54: 2.46 | D54: 2.46 | E54: 2.46 | F54: 2.46 | G54: 2.46 | H54: Recurring Drain Check revenue, documented systems and a manager who is not the owner all push toward the top of the range.
A55: Indicative enterprise value | B55: =B53*B54 -> 169861.9 | C55: =C53*C54 -> 522875.73 | D55: =D53*D54 -> 754896.09 | E55: =E53*E54 -> 595234.03 | F55: =F53*F54 -> 881279.19 | G55: =G53*G54 -> 1324821.5 | H55: Cross-check: revenue x 0.70 (BizBuySell). Not a promise; a benchmark.

Sheet Three cases 5-yr
A1: Worst case, conservative, strong - the same business run three ways
A2: Blue = change it. The middle block is the plan in the blueprint. Today's run rate is on the '5-year plan' tab and is the same in all three cases; what differs is only how fast crews fill their days, what a foot sells for, how many plans attach, and when a crew is added.
A4: Side by side
B5: Worst case | C5: Conservative | D5: Strong
A6: Revenue - year 1 | B6: =B37 -> 879315.75 | C6: =B69 -> 1101154.5 | D6: =B101 -> 1282261.5
A7: Revenue - year 5 | B7: =F37 -> 1135327.5 | C7: =F69 -> 2578331.4 | D7: =F101 -> 3717092.7
A8: Linear feet installed - year 5 | B8: =F34 -> 22680 | C8: =F66 -> 43344 | D8: =F98 -> 60480
A9: Gross margin - year 5 | B9: =F41 -> 0.38315105 | C9: =F73 -> 0.50428826 | D9: =F105 -> 0.543526
A10: Operating profit before the growth lead - year 1 | B10: =B43 -> 16025.62 | C10: =B75 -> 207645.23 | D10: =B107 -> 337341.38
A11: Operating profit after the growth lead - year 1 | B11: =B47 -> -576.94232 | C11: =B79 -> 126880.7 | D11: =B111 -> 243607.25
A12: Operating profit after the growth lead - year 5 | B12: =F47 -> -7048.0986 | C12: =F79 -> 458104.31 | D12: =F111 -> 946049.49
A13: What the growth lead costs - year 1 | B13: =B46 -> 16602.562 | C13: =B78 -> 80764.523 | D13: =B110 -> 93734.138
A14: What the growth lead costs - year 5 | B14: =F46 -> 0 | C14: =F78 -> 130900.48 | D14: =F110 -> 185116.61
A15: Owner's cash from the business - year 5 | B15: =F51 -> 142951.9 | C15: =F83 -> 608104.31 | D15: =F115 -> 1096049.5
A16: Cash at the end of year 5 | B16: =F50 -> -25205.336 | C16: =F82 -> 1148879.1 | D16: =F114 -> 3005513.9
A17: Indicative value at the end of year 5 | B17: =F52 -> 351661.68 | C17: =F84 -> 1495936.6 | D17: =F116 -> 2696281.7
A19: Read it this way: plan around the worst case. There the 90-day gate ends the growth-lead arrangement for $15,000 and the company ends up roughly where it is today - that is the floor. The middle block is what the blueprint commits to. The right-hand block is the same plan with the levers landing.
A22: WORST CASE - most of it does not work | H22: Both crews still launch together in month 1 on the initial investment, but leads cost more, close worse, and crews never beat 36 LF a day - few plans attach. The 90-day gate is missed, so the growth lead is ended after three months (that is the $15,000 in year 1 - the whole exposure) and no share is ever earned. The company still runs two full crews on drains; it just runs them at a lower gear than Charlie's target.
A23: Drivers - change any blue cell | B23: Year 1 | C23: Year 2 | D23: Year 3 | E23: Year 4 | F23: Year 5
A24: Average crews running during the year | B24: 2 | C24: 2 | D24: 2 | E24: 2.5 | F24: 2.5 | H24: Both crews launch together in year 1, funded by the initial investment. A third or fourth crew is added only after the last one runs at target for three months, backlog over four weeks and cash above two months of overhead - half a crew = started mid-year.
A25: LF a crew installs per working day - 100% on french drains | B25: 36 | C25: 36 | D25: 36 | E25: 36 | F25: 36 | H25: Charlie's target is 43 (900 LF / 21 days). No other work is modeled - every working day is a drain day.
A26: Average $/LF | B26: 48 | C26: =B26*(1+$B$27) -> 48 | D26: =C26*(1+$B$27) -> 48 | E26: =D26*(1+$B$27) -> 48 | F26: =E26*(1+$B$27) -> 48
A27: Annual price change from year 2 | B27: 0 | C27: 0 | D27: 0 | E27: 0 | F27: 0
A28: Drain Check plans active at year end | B28: 45 | C28: 95 | D28: 150 | E28: 200 | F28: 250
A29: Marketing as a share of revenue | B29: 0.075 | C29: 0.075 | D29: 0.075 | E29: 0.075 | F29: 0.075
A30: Overhead per crew per year (insurance, tools, uniforms, phones) | B30: 24000 | C30: 24000 | D30: 24000 | E30: 24000 | F30: 24000
A31: Office admin, operations manager, estimator, bonus pool | B31: 0 | C31: 0 | D31: 24000 | E31: 42000 | F31: 44000 | H31: Hired in that order, each before the crew that needs it.
A32: Results
A33: Crew days worked | B33: =B24*Assumptions!$B$10*12 -> 504 | C33: =C24*Assumptions!$B$10*12 -> 504 | D33: =D24*Assumptions!$B$10*12 -> 504 | E33: =E24*Assumptions!$B$10*12 -> 630 | F33: =F24*Assumptions!$B$10*12 -> 630
A34: Linear feet installed | B34: =B33*B25 -> 18144 | C34: =C33*C25 -> 18144 | D34: =D33*D25 -> 18144 | E34: =E33*E25 -> 22680 | F34: =F33*F25 -> 22680
A35: Drainage revenue | B35: =B34*B26 -> 870912 | C35: =C34*C26 -> 870912 | D35: =D34*D26 -> 870912 | E35: =E34*E26 -> 1088640 | F35: =F34*F26 -> 1088640
A36: Drain Check revenue | B36: =B28*Assumptions!$B$30*Assumptions!$B$33 -> 8403.75 | C36: =C28*Assumptions!$B$30*Assumptions!$B$33 -> 17741.25 | D36: =D28*Assumptions!$B$30*Assumptions!$B$33 -> 28012.5 | E36: =E28*Assumptions!$B$30*Assumptions!$B$33 -> 37350 | F36: =F28*Assumptions!$B$30*Assumptions!$B$33 -> 46687.5
A37: TOTAL REVENUE | B37: =B35+B36 -> 879315.75 | C37: =C35+C36 -> 888653.25 | D37: =D35+D36 -> 898924.5 | E37: =E35+E36 -> 1125990 | F37: =F35+F36 -> 1135327.5
A38: Crew labor (wages from the Assumptions tab, +3% a year from year 2) | B38: =B24*(Assumptions!$B$26*Assumptions!$B$27*Assumptions!$B$23+Assumptions!$B$27*Assumptions!$B$24)*(1+Assumptions!$B$25)*12*1.03^MAX(0,COLUMN(B1)-2) -> 333696.24 | C38: =C24*(Assumptions!$B$26*Assumptions!$B$27*Assumptions!$B$23+Assumptions!$B$27*Assumptions!$B$24)*(1+Assumptions!$B$25)*12*1.03^MAX(0,COLUMN(C1)-2) -> 343707.13 | D38: =D24*(Assumptions!$B$26*Assumptions!$B$27*Assumptions!$B$23+Assumptions!$B$27*Assumptions!$B$24)*(1+Assumptions!$B$25)*12*1.03^MAX(0,COLUMN(D1)-2) -> 354018.34 | E38: =E24*(Assumptions!$B$26*Assumptions!$B$27*Assumptions!$B$23+Assumptions!$B$27*Assumptions!$B$24)*(1+Assumptions!$B$25)*12*1.03^MAX(0,COLUMN(E1)-2) -> 455798.61 | F38: =F24*(Assumptions!$B$26*Assumptions!$B$27*Assumptions!$B$23+Assumptions!$B$27*Assumptions!$B$24)*(1+Assumptions!$B$25)*12*1.03^MAX(0,COLUMN(F1)-2) -> 469472.57
A39: Materials, fuel and plan visit costs | B39: =B35*Assumptions!$B$22+B28*Assumptions!$B$33*Assumptions!$B$37 -> 176544.9 | C39: =C35*Assumptions!$B$22+C28*Assumptions!$B$33*Assumptions!$B$37 -> 179169.9 | D39: =D35*Assumptions!$B$22+D28*Assumptions!$B$33*Assumptions!$B$37 -> 182057.4 | E39: =E35*Assumptions!$B$22+E28*Assumptions!$B$33*Assumptions!$B$37 -> 228228 | F39: =F35*Assumptions!$B$22+F28*Assumptions!$B$33*Assumptions!$B$37 -> 230853
A40: GROSS PROFIT | B40: =B37-B38-B39 -> 369074.61 | C40: =C37-C38-C39 -> 365776.22 | D40: =D37-D38-D39 -> 362848.76 | E40: =E37-E38-E39 -> 441963.39 | F40: =F37-F38-F39 -> 435001.93
A41: Gross margin | B41: =IF(B37=0,0,B40/B37) -> 0.41972933 | C41: =IF(C37=0,0,C40/C37) -> 0.41160737 | D41: =IF(D37=0,0,D40/D37) -> 0.40364765 | E41: =IF(E37=0,0,E40/E37) -> 0.39251093 | F41: =IF(F37=0,0,F40/F37) -> 0.38315105
A42: Overhead (owner draw, fixed costs, per crew, staff, marketing, yard, equipment loans) | B42: =(Assumptions!$B$78+Assumptions!$B$80+Assumptions!$B$81+Assumptions!$B$82+Assumptions!$B$83)*12+B24*B30+B31+B37*B29+Assumptions!$B$84*Assumptions!$B$85*12+'Equipment plan'!$H$10*12*MAX(0,B24-1) -> 353048.99 | C42: =(Assumptions!$B$78+Assumptions!$B$80+Assumptions!$B$81+Assumptions!$B$82+Assumptions!$B$83)*12+C24*C30+C31+C37*C29+Assumptions!$B$84*Assumptions!$B$85*12+'Equipment plan'!$H$10*12*MAX(0,C24-1) -> 353749.3 | D42: =(Assumptions!$B$78+Assumptions!$B$80+Assumptions!$B$81+Assumptions!$B$82+Assumptions!$B$83)*12+D24*D30+D31+D37*D29+Assumptions!$B$84*Assumptions!$B$85*12+'Equipment plan'!$H$10*12*MAX(0,D24-1) -> 378519.65 | E42: =(Assumptions!$B$78+Assumptions!$B$80+Assumptions!$B$81+Assumptions!$B$82+Assumptions!$B$83)*12+E24*E30+E31+E37*E29+Assumptions!$B$84*Assumptions!$B$85*12+'Equipment plan'!$H$10*12*MAX(0,E24-1) -> 439349.71 | F42: =(Assumptions!$B$78+Assumptions!$B$80+Assumptions!$B$81+Assumptions!$B$82+Assumptions!$B$83)*12+F24*F30+F31+F37*F29+Assumptions!$B$84*Assumptions!$B$85*12+'Equipment plan'!$H$10*12*MAX(0,F24-1) -> 442050.03 | H42: Owner draw, existing payments, software, CPA, shop and the yard (sq ft x rate) all come from the Assumptions tab.
A43: Operating profit before the growth lead | B43: =B40-B42 -> 16025.62 | C43: =C40-C42 -> 12026.92 | D43: =D40-D42 -> -15670.888 | E43: =E40-E42 -> 2613.6723 | F43: =F40-F42 -> -7048.0986
A44: Growth lead - base for the year | B44: 15000 | C44: 0 | D44: 0 | E44: 0 | F44: 0 | H44: Set any year to 0 to see the plan without it.
A45: Growth lead - share of profit above today's baseline | B45: 0.1 | C45: 0.1 | D45: 0.1 | E45: 0.1 | F45: 0.1 | H45: Earned only on profit above what the business makes today.
A46: Growth lead - total cost | B46: =B44+IF(B44=0,0,B45*MAX(0,B43-MAX(0,'5-year plan'!$B$44))) -> 16602.562 | C46: =C44+IF(C44=0,0,C45*MAX(0,C43-MAX(0,'5-year plan'!$B$44))) -> 0 | D46: =D44+IF(D44=0,0,D45*MAX(0,D43-MAX(0,'5-year plan'!$B$44))) -> 0 | E46: =E44+IF(E44=0,0,E45*MAX(0,E43-MAX(0,'5-year plan'!$B$44))) -> 0 | F46: =F44+IF(F44=0,0,F45*MAX(0,F43-MAX(0,'5-year plan'!$B$44))) -> 0
A47: OPERATING PROFIT after the growth lead | B47: =B43-B46 -> -576.94232 | C47: =C43-C46 -> 12026.92 | D47: =D43-D46 -> -15670.888 | E47: =E43-E46 -> 2613.6723 | F47: =F43-F46 -> -7048.0986
A48: Operating margin (the owner draw is already paid) | B48: =IF(B37=0,0,B47/B37) -> -0.00065612645 | C48: =IF(C37=0,0,C47/C37) -> 0.013533873 | D48: =IF(D37=0,0,D47/D37) -> -0.01743293 | E48: =IF(E37=0,0,E47/E37) -> 0.0023212216 | F48: =IF(F37=0,0,F47/F37) -> -0.0062079872
A49: Equipment down payments for new crews | B49: =MAX(0,B24-1)*'Equipment plan'!$G$10 -> 27700 | C49: =MAX(0,C24-B24)*'Equipment plan'!$G$10 -> 0 | D49: =MAX(0,D24-C24)*'Equipment plan'!$G$10 -> 0 | E49: =MAX(0,E24-D24)*'Equipment plan'!$G$10 -> 13850 | F49: =MAX(0,F24-E24)*'Equipment plan'!$G$10 -> 0
A50: Cash at year end | B50: =Assumptions!$B$62+B47-B49 -> -3276.9423 | C50: =B50+C47-C49 -> 8749.9776 | D50: =C50+D47-D49 -> -6920.91 | E50: =D50+E47-E49 -> -18157.238 | F50: =E50+F47-F49 -> -25205.336 | H50: Before income tax and before any distribution beyond the owner draw. A falling line means the owner draw is larger than the business earns - the draw is a blue cell.
A51: Owner's cash from the business (operating profit + owner draw) | B51: =B47+Assumptions!$B$78*12 -> 149423.06 | C51: =C47+Assumptions!$B$78*12 -> 162026.92 | D51: =D47+Assumptions!$B$78*12 -> 134329.11 | E51: =E47+Assumptions!$B$78*12 -> 152613.67 | F51: =F47+Assumptions!$B$78*12 -> 142951.9
A52: Indicative value at 2.46x SDE | B52: =MAX(0,B51)*2.46 -> 367580.72 | C52: =MAX(0,C51)*2.46 -> 398586.22 | D52: =MAX(0,D51)*2.46 -> 330449.62 | E52: =MAX(0,E51)*2.46 -> 375429.63 | F52: =MAX(0,F51)*2.46 -> 351661.68 | H52: BizBuySell landscaping median, 945 sales 2021-2025. A benchmark, not a promise.
A54: CONSERVATIVE - the plan in the blueprint | H54: Two crews at Charlie's own target from month 1: 900 LF a crew a month, 70% close on estimates, 60% plan close, Crew 3 in year 3 and Crew 4 in year 4 - each only after its gate. This is an annual approximation of the 24-month proforma and lands within about 4% of it.
A55: Drivers - change any blue cell | B55: Year 1 | C55: Year 2 | D55: Year 3 | E55: Year 4 | F55: Year 5
A56: Average crews running during the year | B56: 2 | C56: 2 | D56: 2.5 | E56: 3.5 | F56: 4 | H56: Both crews launch together in year 1, funded by the initial investment. A third or fourth crew is added only after the last one runs at target for three months, backlog over four weeks and cash above two months of overhead - half a crew = started mid-year.
A57: LF a crew installs per working day - 100% on french drains | B57: 43 | C57: 43 | D57: 43 | E57: 43 | F57: 43 | H57: Charlie's target is 43 (900 LF / 21 days). No other work is modeled - every working day is a drain day.
A58: Average $/LF | B58: 50 | C58: =B58*(1+$B$59) -> 51.5 | D58: =C58*(1+$B$59) -> 53.045 | E58: =D58*(1+$B$59) -> 54.63635 | F58: =E58*(1+$B$59) -> 56.275441
A59: Annual price change from year 2 | B59: 0.03 | C59: 0.03 | D59: 0.03 | E59: 0.03 | F59: 0.03
A60: Drain Check plans active at year end | B60: 94 | C60: 216 | D60: 355 | E60: 540 | F60: 745
A61: Marketing as a share of revenue | B61: 0.05 | C61: 0.05 | D61: 0.05 | E61: 0.05 | F61: 0.05
A62: Overhead per crew per year (insurance, tools, uniforms, phones) | B62: 22000 | C62: 22000 | D62: 22000 | E62: 22000 | F62: 22000
A63: Office admin, operations manager, estimator, bonus pool | B63: 0 | C63: 30000 | D63: 102750 | E63: 191000 | F63: 200000 | H63: Hired in that order, each before the crew that needs it.
A64: Results
A65: Crew days worked | B65: =B56*Assumptions!$B$10*12 -> 504 | C65: =C56*Assumptions!$B$10*12 -> 504 | D65: =D56*Assumptions!$B$10*12 -> 630 | E65: =E56*Assumptions!$B$10*12 -> 882 | F65: =F56*Assumptions!$B$10*12 -> 1008
A66: Linear feet installed | B66: =B65*B57 -> 21672 | C66: =C65*C57 -> 21672 | D66: =D65*D57 -> 27090 | E66: =E65*E57 -> 37926 | F66: =F65*F57 -> 43344
A67: Drainage revenue | B67: =B66*B58 -> 1083600 | C67: =C66*C58 -> 1116108 | D67: =D66*D58 -> 1436989.1 | E67: =E66*E58 -> 2072138.2 | F67: =F66*F58 -> 2439202.7
A68: Drain Check revenue | B68: =B60*Assumptions!$B$30*Assumptions!$B$33 -> 17554.5 | C68: =C60*Assumptions!$B$30*Assumptions!$B$33 -> 40338 | D68: =D60*Assumptions!$B$30*Assumptions!$B$33 -> 66296.25 | E68: =E60*Assumptions!$B$30*Assumptions!$B$33 -> 100845 | F68: =F60*Assumptions!$B$30*Assumptions!$B$33 -> 139128.75
A69: TOTAL REVENUE | B69: =B67+B68 -> 1101154.5 | C69: =C67+C68 -> 1156446 | D69: =D67+D68 -> 1503285.3 | E69: =E67+E68 -> 2172983.2 | F69: =F67+F68 -> 2578331.4
A70: Crew labor (wages from the Assumptions tab, +3% a year from year 2) | B70: =B56*(Assumptions!$B$26*Assumptions!$B$27*Assumptions!$B$23+Assumptions!$B$27*Assumptions!$B$24)*(1+Assumptions!$B$25)*12*1.03^MAX(0,COLUMN(B1)-2) -> 333696.24 | C70: =C56*(Assumptions!$B$26*Assumptions!$B$27*Assumptions!$B$23+Assumptions!$B$27*Assumptions!$B$24)*(1+Assumptions!$B$25)*12*1.03^MAX(0,COLUMN(C1)-2) -> 343707.13 | D70: =D56*(Assumptions!$B$26*Assumptions!$B$27*Assumptions!$B$23+Assumptions!$B$27*Assumptions!$B$24)*(1+Assumptions!$B$25)*12*1.03^MAX(0,COLUMN(D1)-2) -> 442522.93 | E70: =E56*(Assumptions!$B$26*Assumptions!$B$27*Assumptions!$B$23+Assumptions!$B$27*Assumptions!$B$24)*(1+Assumptions!$B$25)*12*1.03^MAX(0,COLUMN(E1)-2) -> 638118.06 | F70: =F56*(Assumptions!$B$26*Assumptions!$B$27*Assumptions!$B$23+Assumptions!$B$27*Assumptions!$B$24)*(1+Assumptions!$B$25)*12*1.03^MAX(0,COLUMN(F1)-2) -> 751156.12
A71: Materials, fuel and plan visit costs | B71: =B67*Assumptions!$B$22+B60*Assumptions!$B$33*Assumptions!$B$37 -> 221655 | C71: =C67*Assumptions!$B$22+C60*Assumptions!$B$33*Assumptions!$B$37 -> 234561.6 | D71: =D67*Assumptions!$B$22+D60*Assumptions!$B$33*Assumptions!$B$37 -> 306035.31 | E71: =E67*Assumptions!$B$22+E60*Assumptions!$B$33*Assumptions!$B$37 -> 442777.64 | F71: =F67*Assumptions!$B$22+F60*Assumptions!$B$33*Assumptions!$B$37 -> 526953.04
A72: GROSS PROFIT | B72: =B69-B70-B71 -> 545803.26 | C72: =C69-C70-C71 -> 578177.27 | D72: =D69-D70-D71 -> 754727.06 | E72: =E69-E70-E71 -> 1092087.5 | F72: =F69-F70-F71 -> 1300222.3
A73: Gross margin | B73: =IF(B69=0,0,B72/B69) -> 0.49566456 | C73: =IF(C69=0,0,C72/C69) -> 0.49996046 | D73: =IF(D69=0,0,D72/D69) -> 0.50205178 | E73: =IF(E69=0,0,E72/E69) -> 0.50257522 | F73: =IF(F69=0,0,F72/F69) -> 0.50428826
A74: Overhead (owner draw, fixed costs, per crew, staff, marketing, yard, equipment loans) | B74: =(Assumptions!$B$78+Assumptions!$B$80+Assumptions!$B$81+Assumptions!$B$82+Assumptions!$B$83)*12+B56*B62+B63+B69*B61+Assumptions!$B$84*Assumptions!$B$85*12+'Equipment plan'!$H$10*12*MAX(0,B56-1) -> 338158.03 | C74: =(Assumptions!$B$78+Assumptions!$B$80+Assumptions!$B$81+Assumptions!$B$82+Assumptions!$B$83)*12+C56*C62+C63+C69*C61+Assumptions!$B$84*Assumptions!$B$85*12+'Equipment plan'!$H$10*12*MAX(0,C56-1) -> 370922.61 | D74: =(Assumptions!$B$78+Assumptions!$B$80+Assumptions!$B$81+Assumptions!$B$82+Assumptions!$B$83)*12+D56*D62+D63+D69*D61+Assumptions!$B$84*Assumptions!$B$85*12+'Equipment plan'!$H$10*12*MAX(0,D56-1) -> 485814.73 | E74: =(Assumptions!$B$78+Assumptions!$B$80+Assumptions!$B$81+Assumptions!$B$82+Assumptions!$B$83)*12+E56*E62+E63+E69*E61+Assumptions!$B$84*Assumptions!$B$85*12+'Equipment plan'!$H$10*12*MAX(0,E56-1) -> 657149.93 | F74: =(Assumptions!$B$78+Assumptions!$B$80+Assumptions!$B$81+Assumptions!$B$82+Assumptions!$B$83)*12+F56*F62+F63+F69*F61+Assumptions!$B$84*Assumptions!$B$85*12+'Equipment plan'!$H$10*12*MAX(0,F56-1) -> 711217.5 | H74: Owner draw, existing payments, software, CPA, shop and the yard (sq ft x rate) all come from the Assumptions tab.
A75: Operating profit before the growth lead | B75: =B72-B74 -> 207645.23 | C75: =C72-C74 -> 207254.66 | D75: =D72-D74 -> 268912.34 | E75: =E72-E74 -> 434937.58 | F75: =F72-F74 -> 589004.79
A76: Growth lead - base for the year | B76: 60000 | C76: 60000 | D76: 66000 | E76: 72000 | F76: 72000 | H76: Set any year to 0 to see the plan without it.
A77: Growth lead - share of profit above today's baseline | B77: 0.1 | C77: 0.1 | D77: 0.1 | E77: 0.1 | F77: 0.1 | H77: Earned only on profit above what the business makes today.
A78: Growth lead - total cost | B78: =B76+IF(B76=0,0,B77*MAX(0,B75-MAX(0,'5-year plan'!$B$44))) -> 80764.523 | C78: =C76+IF(C76=0,0,C77*MAX(0,C75-MAX(0,'5-year plan'!$B$44))) -> 80725.466 | D78: =D76+IF(D76=0,0,D77*MAX(0,D75-MAX(0,'5-year plan'!$B$44))) -> 92891.234 | E78: =E76+IF(E76=0,0,E77*MAX(0,E75-MAX(0,'5-year plan'!$B$44))) -> 115493.76 | F78: =F76+IF(F76=0,0,F77*MAX(0,F75-MAX(0,'5-year plan'!$B$44))) -> 130900.48
A79: OPERATING PROFIT after the growth lead | B79: =B75-B78 -> 126880.7 | C79: =C75-C78 -> 126529.2 | D79: =D75-D78 -> 176021.1 | E79: =E75-E78 -> 319443.82 | F79: =F75-F78 -> 458104.31
A80: Operating margin (the owner draw is already paid) | B80: =IF(B69=0,0,B79/B69) -> 0.11522516 | C80: =IF(C69=0,0,C79/C69) -> 0.10941211 | D80: =IF(D69=0,0,D79/D69) -> 0.11709095 | E80: =IF(E69=0,0,E79/E69) -> 0.14700703 | F80: =IF(F69=0,0,F79/F69) -> 0.17767472
A81: Equipment down payments for new crews | B81: =MAX(0,B56-1)*'Equipment plan'!$G$10 -> 27700 | C81: =MAX(0,C56-B56)*'Equipment plan'!$G$10 -> 0 | D81: =MAX(0,D56-C56)*'Equipment plan'!$G$10 -> 13850 | E81: =MAX(0,E56-D56)*'Equipment plan'!$G$10 -> 27700 | F81: =MAX(0,F56-E56)*'Equipment plan'!$G$10 -> 13850
A82: Cash at year end | B82: =Assumptions!$B$62+B79-B81 -> 124180.7 | C82: =B82+C79-C81 -> 250709.9 | D82: =C82+D79-D81 -> 412881 | E82: =D82+E79-E81 -> 704624.82 | F82: =E82+F79-F81 -> 1148879.1 | H82: Before income tax and before any distribution beyond the owner draw. A falling line means the owner draw is larger than the business earns - the draw is a blue cell.
A83: Owner's cash from the business (operating profit + owner draw) | B83: =B79+Assumptions!$B$78*12 -> 276880.7 | C83: =C79+Assumptions!$B$78*12 -> 276529.2 | D83: =D79+Assumptions!$B$78*12 -> 326021.1 | E83: =E79+Assumptions!$B$78*12 -> 469443.82 | F83: =F79+Assumptions!$B$78*12 -> 608104.31
A84: Indicative value at 2.46x SDE | B84: =MAX(0,B83)*2.46 -> 681126.53 | C84: =MAX(0,C83)*2.46 -> 680261.83 | D84: =MAX(0,D83)*2.46 -> 802011.91 | E84: =MAX(0,E83)*2.46 -> 1154831.8 | F84: =MAX(0,F83)*2.46 -> 1495936.6 | H84: BizBuySell landscaping median, 945 sales 2021-2025. A benchmark, not a promise.
A86: STRONG - the levers work | H86: Reviews, referrals and the Moasure map support a 3% price step each year, crews settle at 48 LF a day, the plan book compounds and HOA / property-manager work fills the winter faster than the base case. Note the gross margin runs above Charlie's 50% rule - that is what productivity does to a fixed crew cost.
A87: Drivers - change any blue cell | B87: Year 1 | C87: Year 2 | D87: Year 3 | E87: Year 4 | F87: Year 5
A88: Average crews running during the year | B88: 2 | C88: 3 | D88: 4 | E88: 4.5 | F88: 5 | H88: Both crews launch together in year 1, funded by the initial investment. A third or fourth crew is added only after the last one runs at target for three months, backlog over four weeks and cash above two months of overhead - half a crew = started mid-year.
A89: LF a crew installs per working day - 100% on french drains | B89: 48 | C89: 48 | D89: 48 | E89: 48 | F89: 48 | H89: Charlie's target is 43 (900 LF / 21 days). No other work is modeled - every working day is a drain day.
A90: Average $/LF | B90: 52 | C90: =B90*(1+$B$91) -> 53.56 | D90: =C90*(1+$B$91) -> 55.1668 | E90: =D90*(1+$B$91) -> 56.821804 | F90: =E90*(1+$B$91) -> 58.526458
A91: Annual price change from year 2 | B91: 0.03 | C91: 0.03 | D91: 0.03 | E91: 0.03 | F91: 0.03
A92: Drain Check plans active at year end | B92: 130 | C92: 300 | D92: 500 | E92: 720 | F92: 950
A93: Marketing as a share of revenue | B93: 0.045 | C93: 0.045 | D93: 0.045 | E93: 0.045 | F93: 0.045
A94: Overhead per crew per year (insurance, tools, uniforms, phones) | B94: 22000 | C94: 22000 | D94: 22000 | E94: 22000 | F94: 22000
A95: Office admin, operations manager, estimator, bonus pool | B95: 12000 | C95: 54000 | D95: 191000 | E95: 265000 | F95: 290000 | H95: Hired in that order, each before the crew that needs it.
A96: Results
A97: Crew days worked | B97: =B88*Assumptions!$B$10*12 -> 504 | C97: =C88*Assumptions!$B$10*12 -> 756 | D97: =D88*Assumptions!$B$10*12 -> 1008 | E97: =E88*Assumptions!$B$10*12 -> 1134 | F97: =F88*Assumptions!$B$10*12 -> 1260
A98: Linear feet installed | B98: =B97*B89 -> 24192 | C98: =C97*C89 -> 36288 | D98: =D97*D89 -> 48384 | E98: =E97*E89 -> 54432 | F98: =F97*F89 -> 60480
A99: Drainage revenue | B99: =B98*B90 -> 1257984 | C99: =C98*C90 -> 1943585.3 | D99: =D98*D90 -> 2669190.5 | E99: =E98*E90 -> 3092924.4 | F99: =F98*F90 -> 3539680.2
A100: Drain Check revenue | B100: =B92*Assumptions!$B$30*Assumptions!$B$33 -> 24277.5 | C100: =C92*Assumptions!$B$30*Assumptions!$B$33 -> 56025 | D100: =D92*Assumptions!$B$30*Assumptions!$B$33 -> 93375 | E100: =E92*Assumptions!$B$30*Assumptions!$B$33 -> 134460 | F100: =F92*Assumptions!$B$30*Assumptions!$B$33 -> 177412.5
A101: TOTAL REVENUE | B101: =B99+B100 -> 1282261.5 | C101: =C99+C100 -> 1999610.3 | D101: =D99+D100 -> 2762565.5 | E101: =E99+E100 -> 3227384.4 | F101: =F99+F100 -> 3717092.7
A102: Crew labor (wages from the Assumptions tab, +3% a year from year 2) | B102: =B88*(Assumptions!$B$26*Assumptions!$B$27*Assumptions!$B$23+Assumptions!$B$27*Assumptions!$B$24)*(1+Assumptions!$B$25)*12*1.03^MAX(0,COLUMN(B1)-2) -> 333696.24 | C102: =C88*(Assumptions!$B$26*Assumptions!$B$27*Assumptions!$B$23+Assumptions!$B$27*Assumptions!$B$24)*(1+Assumptions!$B$25)*12*1.03^MAX(0,COLUMN(C1)-2) -> 515560.69 | D102: =D88*(Assumptions!$B$26*Assumptions!$B$27*Assumptions!$B$23+Assumptions!$B$27*Assumptions!$B$24)*(1+Assumptions!$B$25)*12*1.03^MAX(0,COLUMN(D1)-2) -> 708036.68 | E102: =E88*(Assumptions!$B$26*Assumptions!$B$27*Assumptions!$B$23+Assumptions!$B$27*Assumptions!$B$24)*(1+Assumptions!$B$25)*12*1.03^MAX(0,COLUMN(E1)-2) -> 820437.51 | F102: =F88*(Assumptions!$B$26*Assumptions!$B$27*Assumptions!$B$23+Assumptions!$B$27*Assumptions!$B$24)*(1+Assumptions!$B$25)*12*1.03^MAX(0,COLUMN(F1)-2) -> 938945.14
A103: Materials, fuel and plan visit costs | B103: =B99*Assumptions!$B$22+B92*Assumptions!$B$33*Assumptions!$B$37 -> 258421.8 | C103: =C99*Assumptions!$B$22+C92*Assumptions!$B$33*Assumptions!$B$37 -> 404467.06 | D103: =D99*Assumptions!$B$22+D92*Assumptions!$B$33*Assumptions!$B$37 -> 560088.09 | E103: =E99*Assumptions!$B$22+E92*Assumptions!$B$33*Assumptions!$B$37 -> 656384.89 | F103: =F99*Assumptions!$B$22+F92*Assumptions!$B$33*Assumptions!$B$37 -> 757811.04
A104: GROSS PROFIT | B104: =B101-B102-B103 -> 690143.46 | C104: =C101-C102-C103 -> 1079582.5 | D104: =D101-D102-D103 -> 1494440.7 | E104: =E101-E102-E103 -> 1750562 | F104: =F101-F102-F103 -> 2020336.5
A105: Gross margin | B105: =IF(B101=0,0,B104/B101) -> 0.53822365 | C105: =IF(C101=0,0,C104/C101) -> 0.53989647 | D105: =IF(D101=0,0,D104/D101) -> 0.54096118 | E105: =IF(E101=0,0,E104/E101) -> 0.5424089 | F105: =IF(F101=0,0,F104/F101) -> 0.543526
A106: Overhead (owner draw, fixed costs, per crew, staff, marketing, yard, equipment loans) | B106: =(Assumptions!$B$78+Assumptions!$B$80+Assumptions!$B$81+Assumptions!$B$82+Assumptions!$B$83)*12+B88*B94+B95+B101*B93+Assumptions!$B$84*Assumptions!$B$85*12+'Equipment plan'!$H$10*12*MAX(0,B88-1) -> 352802.08 | C106: =(Assumptions!$B$78+Assumptions!$B$80+Assumptions!$B$81+Assumptions!$B$82+Assumptions!$B$83)*12+C88*C94+C95+C101*C93+Assumptions!$B$84*Assumptions!$B$85*12+'Equipment plan'!$H$10*12*MAX(0,C88-1) -> 476683.08 | D106: =(Assumptions!$B$78+Assumptions!$B$80+Assumptions!$B$81+Assumptions!$B$82+Assumptions!$B$83)*12+D88*D94+D95+D101*D93+Assumptions!$B$84*Assumptions!$B$85*12+'Equipment plan'!$H$10*12*MAX(0,D88-1) -> 697616.37 | E106: =(Assumptions!$B$78+Assumptions!$B$80+Assumptions!$B$81+Assumptions!$B$82+Assumptions!$B$83)*12+E88*E94+E95+E101*E93+Assumptions!$B$84*Assumptions!$B$85*12+'Equipment plan'!$H$10*12*MAX(0,E88-1) -> 817333.38 | F106: =(Assumptions!$B$78+Assumptions!$B$80+Assumptions!$B$81+Assumptions!$B$82+Assumptions!$B$83)*12+F88*F94+F95+F101*F93+Assumptions!$B$84*Assumptions!$B$85*12+'Equipment plan'!$H$10*12*MAX(0,F88-1) -> 889170.41 | H106: Owner draw, existing payments, software, CPA, shop and the yard (sq ft x rate) all come from the Assumptions tab.
...

Sheet Long range 15-yr
A1: The long view - the same roadmap run out fifteen years
A2: Blue = change it. Years 1-5 follow the five-year plan; from year 6 the company adds crews at the rate set on the Assumptions tab until it hits the ceiling one yard and one owner can run. Set 'Years to show' on the Assumptions tab to 1 through 15 and the summary at the top follows it.
A4: At the end of the year you choose on the Assumptions tab
A5: Year shown (change it on Assumptions) | E5: Crews running | I5: People on board | M5: Revenue
A6: =Assumptions!$B$39 -> 10 | E6: =INDEX(B17:P17,Assumptions!$B$39) -> 6.5 | I6: =INDEX(B34:P34,Assumptions!$B$39) -> 30 | M6: =INDEX(B36:P36,Assumptions!$B$39) -> 4952082.9
A7: Plan customers under contract | E7: Operating profit after the owner draw | I7: Cash on hand | M7: Equipment at book value
A8: =INDEX(B31:P31,Assumptions!$B$39) -> 2075.0737 | E8: =INDEX(B51:P51,Assumptions!$B$39) -> 879166.34 | I8: =INDEX(B59:P59,Assumptions!$B$39) -> 1576508.8 | M8: =INDEX(B55:P55,Assumptions!$B$39) -> 360470.91
A9: Taken out along the way (tax and distributions) | E9: VALUE WITH the service book | I9: VALUE WITHOUT it | M9: What the service book adds
A10: =INDEX(B58:P58,Assumptions!$B$39) -> 2555788.2 | E10: =INDEX(B62:P62,Assumptions!$B$39) -> 3964469.5 | I10: =INDEX(B63:P63,Assumptions!$B$39) -> 2750692.4 | M10: =INDEX(B64:P64,Assumptions!$B$39) -> 1213777
A12: Every figure below is a formula. Change a blue cell on Assumptions - the plan close rate, the yearly / two-yearly split, crews added per year, the multiples - and all fifteen years move.
A15: Year | B15: 1 | C15: 2 | D15: 3 | E15: 4 | F15: 5 | G15: 6 | H15: 7 | I15: 8 | J15: 9 | K15: 10 | L15: 11 | M15: 12 | N15: 13 | O15: 14 | P15: 15 | R15: Notes
A16: CAPACITY AND PEOPLE
A17: Crews running | B17: ='5-year plan'!C7 -> 2 | C17: ='5-year plan'!D7 -> 2 | D17: ='5-year plan'!E7 -> 2.5 | E17: ='5-year plan'!F7 -> 3.5 | F17: ='5-year plan'!G7 -> 4 | G17: =MIN(Assumptions!$B$41,F17+Assumptions!$B$40) -> 4.5 | H17: =MIN(Assumptions!$B$41,G17+Assumptions!$B$40) -> 5 | I17: =MIN(Assumptions!$B$41,H17+Assumptions!$B$40) -> 5.5 | J17: =MIN(Assumptions!$B$41,I17+Assumptions!$B$40) -> 6 | K17: =MIN(Assumptions!$B$41,J17+Assumptions!$B$40) -> 6.5 | L17: =MIN(Assumptions!$B$41,K17+Assumptions!$B$40) -> 7 | M17: =MIN(Assumptions!$B$41,L17+Assumptions!$B$40) -> 7.5 | N17: =MIN(Assumptions!$B$41,M17+Assumptions!$B$40) -> 8 | ... P17: =MIN(Assumptions!$B$41,O17+Assumptions!$B$40) -> 8 | R17: Years 1-5 from the five-year plan; after that the rate and the ceiling are both blue cells on Assumptions.
A18: LF a crew installs per working day - 100% on french drains | B18: =Assumptions!$B$11 -> 43 | C18: =B18 -> 43 | D18: =C18 -> 43 | E18: =D18 -> 43 | F18: =E18 -> 43 | G18: =F18 -> 43 | H18: =G18 -> 43 | I18: =H18 -> 43 | J18: =I18 -> 43 | ... P18: =O18 -> 43 | R18: Held flat at Charlie's target. Every working day is a drain day - no other work is modeled.
A19: Crew days worked | B19: =B17*Assumptions!$B$10*12 -> 504 | C19: =C17*Assumptions!$B$10*12 -> 504 | D19: =D17*Assumptions!$B$10*12 -> 630 | E19: =E17*Assumptions!$B$10*12 -> 882 | F19: =F17*Assumptions!$B$10*12 -> 1008 | G19: =G17*Assumptions!$B$10*12 -> 1134 | H19: =H17*Assumptions!$B$10*12 -> 1260 | I19: =I17*Assumptions!$B$10*12 -> 1386 | ... P19: =P17*Assumptions!$B$10*12 -> 2016
A20: Linear feet installed | B20: =B19*B18 -> 21672 | C20: =C19*C18 -> 21672 | D20: =D19*D18 -> 27090 | E20: =E19*E18 -> 37926 | F20: =F19*F18 -> 43344 | G20: =G19*G18 -> 48762 | H20: =H19*H18 -> 54180 | I20: =I19*I18 -> 59598 | ... P20: =P19*P18 -> 86688
A21: PEOPLE ON BOARD
A22: Crew members in the field | B22: =ROUND(B17*Assumptions!$B$26,0) -> 6 | C22: =ROUND(C17*Assumptions!$B$26,0) -> 6 | D22: =ROUND(D17*Assumptions!$B$26,0) -> 8 | E22: =ROUND(E17*Assumptions!$B$26,0) -> 11 | F22: =ROUND(F17*Assumptions!$B$26,0) -> 12 | G22: =ROUND(G17*Assumptions!$B$26,0) -> 14 | H22: =ROUND(H17*Assumptions!$B$26,0) -> 15 | I22: =ROUND(I17*Assumptions!$B$26,0) -> 17 | ... P22: =ROUND(P17*Assumptions!$B$26,0) -> 24
A23: Office admin | B23: =IF(B17>=2,ROUNDUP(B17/(Assumptions!$B$51+(Assumptions!$B$180-Assumptions!$B$51)*0),0),0) -> 1 | C23: =IF(C17>=2,ROUNDUP(C17/(Assumptions!$B$51+(Assumptions!$B$180-Assumptions!$B$51)*0.071429),0),0) -> 1 | D23: =IF(D17>=2,ROUNDUP(D17/(Assumptions!$B$51+(Assumptions!$B$180-Assumptions!$B$51)*0.142857),0),0) -> 2 | E23: =IF(E17>=2,ROUNDUP(E17/(Assumptions!$B$51+(Assumptions!$B$180-Assumptions!$B$51)*0.214286),0),0) -> 2 | F23: =IF(F17>=2,ROUNDUP(F17/(Assumptions!$B$51+(Assumptions!$B$180-Assumptions!$B$51)*0.285714),0),0) -> 2 | G23: =IF(G17>=2,ROUNDUP(G17/(Assumptions!$B$51+(Assumptions!$B$180-Assumptions!$B$51)*0.357143),0),0) -> 2 | H23: =IF(H17>=2,ROUNDUP(H17/(Assumptions!$B$51+(Assumptions!$B$180-Assumptions!$B$51)*0.428571),0),0) -> 2 | I23: =IF(I17>=2,ROUNDUP(I17/(Assumptions!$B$51+(Assumptions!$B$180-Assumptions!$B$51)*0.5),0),0) -> 2 | J23: =IF(J17>=2,ROUNDUP(J17/(Assumptions!$B$51+(Assumptions!$B$180-Assumptions!$B$51)*0.571429),0),0) -> 3 | K23: =IF(K17>=2,ROUNDUP(K17/(Assumptions!$B$51+(Assumptions!$B$180-Assumptions!$B$51)*0.642857),0),0) -> 3 | L23: =IF(L17>=2,ROUNDUP(L17/(Assumptions!$B$51+(Assumptions!$B$180-Assumptions!$B$51)*0.714286),0),0) -> 3 | M23: =IF(M17>=2,ROUNDUP(M17/(Assumptions!$B$51+(Assumptions!$B$180-Assumptions!$B$51)*0.785714),0),0) -> 3 | N23: =IF(N17>=2,ROUNDUP(N17/(Assumptions!$B$51+(Assumptions!$B$180-Assumptions!$B$51)*0.857143),0),0) -> 3 | O23: =IF(O17>=2,ROUNDUP(O17/(Assumptions!$B$51+(Assumptions!$B$180-Assumptions!$B$51)*0.928571),0),0) -> 3 | P23: =IF(P17>=2,ROUNDUP(P17/(Assumptions!$B$51+(Assumptions!$B$180-Assumptions!$B$51)*1),0),0) -> 3 | R23: The number of crews one admin covers walks from today's figure to the year-15 figure on Assumptions, because AI takes the data entry and the phone triage. The role does not vanish - it becomes an operations coordinator.
A24: Operations managers | B24: =IF(B17>=3,ROUNDUP(B17/Assumptions!$B$52,0),0) -> 0 | C24: =IF(C17>=3,ROUNDUP(C17/Assumptions!$B$52,0),0) -> 0 | D24: =IF(D17>=3,ROUNDUP(D17/Assumptions!$B$52,0),0) -> 0 | E24: =IF(E17>=3,ROUNDUP(E17/Assumptions!$B$52,0),0) -> 1 | F24: =IF(F17>=3,ROUNDUP(F17/Assumptions!$B$52,0),0) -> 1 | G24: =IF(G17>=3,ROUNDUP(G17/Assumptions!$B$52,0),0) -> 2 | H24: =IF(H17>=3,ROUNDUP(H17/Assumptions!$B$52,0),0) -> 2 | I24: =IF(I17>=3,ROUNDUP(I17/Assumptions!$B$52,0),0) -> 2 | ... P24: =IF(P17>=3,ROUNDUP(P17/Assumptions!$B$52,0),0) -> 2
A25: Estimators | B25: =IF(B17>=4,ROUNDUP(B17/(Assumptions!$B$53+(Assumptions!$B$181-Assumptions!$B$53)*0),0),0) -> 0 | C25: =IF(C17>=4,ROUNDUP(C17/(Assumptions!$B$53+(Assumptions!$B$181-Assumptions!$B$53)*0.071429),0),0) -> 0 | D25: =IF(D17>=4,ROUNDUP(D17/(Assumptions!$B$53+(Assumptions!$B$181-Assumptions!$B$53)*0.142857),0),0) -> 0 | E25: =IF(E17>=4,ROUNDUP(E17/(Assumptions!$B$53+(Assumptions!$B$181-Assumptions!$B$53)*0.214286),0),0) -> 0 | F25: =IF(F17>=4,ROUNDUP(F17/(Assumptions!$B$53+(Assumptions!$B$181-Assumptions!$B$53)*0.285714),0),0) -> 2 | G25: =IF(G17>=4,ROUNDUP(G17/(Assumptions!$B$53+(Assumptions!$B$181-Assumptions!$B$53)*0.357143),0),0) -> 2 | H25: =IF(H17>=4,ROUNDUP(H17/(Assumptions!$B$53+(Assumptions!$B$181-Assumptions!$B$53)*0.428571),0),0) -> 2 | I25: =IF(I17>=4,ROUNDUP(I17/(Assumptions!$B$53+(Assumptions!$B$181-Assumptions!$B$53)*0.5),0),0) -> 2 | J25: =IF(J17>=4,ROUNDUP(J17/(Assumptions!$B$53+(Assumptions!$B$181-Assumptions!$B$53)*0.571429),0),0) -> 2 | K25: =IF(K17>=4,ROUNDUP(K17/(Assumptions!$B$53+(Assumptions!$B$181-Assumptions!$B$53)*0.642857),0),0) -> 2 | L25: =IF(L17>=4,ROUNDUP(L17/(Assumptions!$B$53+(Assumptions!$B$181-Assumptions!$B$53)*0.714286),0),0) -> 2 | M25: =IF(M17>=4,ROUNDUP(M17/(Assumptions!$B$53+(Assumptions!$B$181-Assumptions!$B$53)*0.785714),0),0) -> 2 | N25: =IF(N17>=4,ROUNDUP(N17/(Assumptions!$B$53+(Assumptions!$B$181-Assumptions!$B$53)*0.857143),0),0) -> 2 | O25: =IF(O17>=4,ROUNDUP(O17/(Assumptions!$B$53+(Assumptions!$B$181-Assumptions!$B$53)*0.928571),0),0) -> 2 | P25: =IF(P17>=4,ROUNDUP(P17/(Assumptions!$B$53+(Assumptions!$B$181-Assumptions!$B$53)*1),0),0) -> 2 | R25: Same ratchet as the admin line. Operations managers below are deliberately NOT ratcheted - running crews in the field is the least AI-exposed job in the company, and pretending otherwise would flatter the plan.
A26: REVENUE
A27: Average $/LF | B27: =Assumptions!$B$5 -> 50 | C27: =B27 -> 50 | D27: =C27*(1+Assumptions!$B$131) -> 51.5 | E27: =D27*(1+Assumptions!$B$131) -> 53.045 | F27: =E27*(1+Assumptions!$B$131) -> 54.63635 | G27: =F27*(1+Assumptions!$B$131) -> 56.275441 | H27: =G27*(1+Assumptions!$B$131) -> 57.963704 | I27: =H27*(1+Assumptions!$B$131) -> 59.702615 | J27: =I27*(1+Assumptions!$B$131) -> 61.493693 | K27: =J27*(1+Assumptions!$B$131) -> 63.338504 | ... P27: =O27*(1+Assumptions!$B$131) -> 73.426686 | R27: Rises at the price escalator on Assumptions from year 3. Whether it keeps up with costs is the question the margin rows below answer.
A28: Drainage revenue | B28: =B20*B27 -> 1083600 | C28: =C20*C27 -> 1083600 | D28: =D20*D27 -> 1395135 | E28: =E20*E27 -> 2011784.7 | F28: =F20*F27 -> 2368158 | G28: =G20*G27 -> 2744103 | H28: =H20*H27 -> 3140473.5 | I28: =I20*I27 -> 3558156.4 | ... P28: =P20*P27 -> 6365212.5
A29: Jobs completed | B29: =B20/Assumptions!$B$17 -> 216.72 | C29: =C20/Assumptions!$B$17 -> 216.72 | D29: =D20/Assumptions!$B$17 -> 270.9 | E29: =E20/Assumptions!$B$17 -> 379.26 | F29: =F20/Assumptions!$B$17 -> 433.44 | G29: =G20/Assumptions!$B$17 -> 487.62 | H29: =H20/Assumptions!$B$17 -> 541.8 | I29: =I20/Assumptions!$B$17 -> 595.98 | ... P29: =P20/Assumptions!$B$17 -> 866.88
A30: New plan customers (jobs x plan close rate) | B30: =B29*Assumptions!$B$31 -> 130.032 | C30: =C29*Assumptions!$B$31 -> 130.032 | D30: =D29*Assumptions!$B$31 -> 162.54 | E30: =E29*Assumptions!$B$31 -> 227.556 | F30: =F29*Assumptions!$B$31 -> 260.064 | G30: =G29*Assumptions!$B$31 -> 292.572 | H30: =H29*Assumptions!$B$31 -> 325.08 | I30: =I29*Assumptions!$B$31 -> 357.588 | ... P30: =P29*Assumptions!$B$31 -> 520.128
A31: Plan customers under contract at year end | B31: =B30 -> 130.032 | C31: =B31*(1-Assumptions!$B$43)+C30 -> 249.66144 | D31: =C31*(1-Assumptions!$B$43)+D30 -> 392.22852 | E31: =D31*(1-Assumptions!$B$43)+E30 -> 588.40624 | F31: =E31*(1-Assumptions!$B$43)+F30 -> 801.39774 | G31: =F31*(1-Assumptions!$B$43)+G30 -> 1029.8579 | H31: =G31*(1-Assumptions!$B$43)+H30 -> 1272.5493 | I31: =H31*(1-Assumptions!$B$43)+I30 -> 1528.3333 | J31: =I31*(1-Assumptions!$B$43)+J30 -> 1796.1627 | ... P31: =O31*(1-Assumptions!$B$43)+P30 -> 3512.2677 | R31: Every year's installs add to the book and the book keeps paying. This is the line that turns a job shop into a company.
A32: Plan price per visit | B32: =Assumptions!$B$30 -> 249 | C32: =B32 -> 249 | D32: =C32*(1+Assumptions!$B$131) -> 256.47 | E32: =D32*(1+Assumptions!$B$131) -> 264.1641 | F32: =E32*(1+Assumptions!$B$131) -> 272.08902 | G32: =F32*(1+Assumptions!$B$131) -> 280.25169 | H32: =G32*(1+Assumptions!$B$131) -> 288.65924 | I32: =H32*(1+Assumptions!$B$131) -> 297.31902 | J32: =I32*(1+Assumptions!$B$131) -> 306.23859 | K32: =J32*(1+Assumptions!$B$131) -> 315.42575 | ... P32: =O32*(1+Assumptions!$B$131) -> 365.66489
A33: Maintenance technicians needed | B33: =ROUNDUP(B31*Assumptions!$B$33/Assumptions!$B$54,0) -> 1 | C33: =ROUNDUP(C31*Assumptions!$B$33/Assumptions!$B$54,0) -> 1 | D33: =ROUNDUP(D31*Assumptions!$B$33/Assumptions!$B$54,0) -> 1 | E33: =ROUNDUP(E31*Assumptions!$B$33/Assumptions!$B$54,0) -> 1 | F33: =ROUNDUP(F31*Assumptions!$B$33/Assumptions!$B$54,0) -> 1 | G33: =ROUNDUP(G31*Assumptions!$B$33/Assumptions!$B$54,0) -> 1 | H33: =ROUNDUP(H31*Assumptions!$B$33/Assumptions!$B$54,0) -> 2 | I33: =ROUNDUP(I31*Assumptions!$B$33/Assumptions!$B$54,0) -> 2 | ... P33: =ROUNDUP(P31*Assumptions!$B$33/Assumptions!$B$54,0) -> 3 | R33: Their time and fuel are already inside the cost per visit, so they are not charged again below. Until there is a full load, the cleanings fill the crews' slow weeks - the jetter is already owned.
A34: TOTAL PEOPLE ON BOARD (including Charlie) | B34: =1+B22+B23+B24+B25+B33 -> 9 | C34: =1+C22+C23+C24+C25+C33 -> 9 | D34: =1+D22+D23+D24+D25+D33 -> 12 | E34: =1+E22+E23+E24+E25+E33 -> 16 | F34: =1+F22+F23+F24+F25+F33 -> 19 | G34: =1+G22+G23+G24+G25+G33 -> 22 | H34: =1+H22+H23+H24+H25+H33 -> 24 | I34: =1+I22+I23+I24+I25+I33 -> 26 | ... P34: =1+P22+P23+P24+P25+P33 -> 35
A35: Plan revenue | B35: =B31*Assumptions!$B$33*B32 -> 24283.476 | C35: =C31*Assumptions!$B$33*C32 -> 46624.274 | D35: =D31*Assumptions!$B$33*D32 -> 75446.137 | E35: =E31*Assumptions!$B$33*E32 -> 116576.85 | F35: =F31*Assumptions!$B$33*F32 -> 163538.65 | G35: =G31*Assumptions!$B$33*G32 -> 216464.57 | H35: =H31*Assumptions!$B$33*H32 -> 275499.84 | I35: =I31*Assumptions!$B$33*I32 -> 340801.93 | ... P35: =P31*Assumptions!$B$33*P32 -> 963234.75
A36: TOTAL REVENUE | B36: =B28+B35 -> 1107883.5 | C36: =C28+C35 -> 1130224.3 | D36: =D28+D35 -> 1470581.1 | E36: =E28+E35 -> 2128361.5 | F36: =F28+F35 -> 2531696.6 | G36: =G28+G35 -> 2960567.6 | H36: =H28+H35 -> 3415973.3 | I36: =I28+I35 -> 3898958.4 | ... P36: =P28+P35 -> 7328447.3
A37: COSTS
A38: Crew labor | B38: =B17*(Assumptions!$B$26*Assumptions!$B$27*Assumptions!$B$23+Assumptions!$B$27*Assumptions!$B$24)*(1+Assumptions!$B$25)*12 -> 333696.24 | C38: =C17*(Assumptions!$B$26*Assumptions!$B$27*Assumptions!$B$23+Assumptions!$B$27*Assumptions!$B$24)*(1+Assumptions!$B$25)*12*(1+Assumptions!$B$137)^1 -> 345375.61 | D38: =D17*(Assumptions!$B$26*Assumptions!$B$27*Assumptions!$B$23+Assumptions!$B$27*Assumptions!$B$24)*(1+Assumptions!$B$25)*12*(1+Assumptions!$B$137)^2 -> 446829.69 | E38: =E17*(Assumptions!$B$26*Assumptions!$B$27*Assumptions!$B$23+Assumptions!$B$27*Assumptions!$B$24)*(1+Assumptions!$B$25)*12*(1+Assumptions!$B$137)^3 -> 647456.23 | F38: =F17*(Assumptions!$B$26*Assumptions!$B$27*Assumptions!$B$23+Assumptions!$B$27*Assumptions!$B$24)*(1+Assumptions!$B$25)*12*(1+Assumptions!$B$137)^4 -> 765848.22 | G38: =G17*(Assumptions!$B$26*Assumptions!$B$27*Assumptions!$B$23+Assumptions!$B$27*Assumptions!$B$24)*(1+Assumptions!$B$25)*12*(1+Assumptions!$B$137)^5 -> 891734.52 | H38: =H17*(Assumptions!$B$26*Assumptions!$B$27*Assumptions!$B$23+Assumptions!$B$27*Assumptions!$B$24)*(1+Assumptions!$B$25)*12*(1+Assumptions!$B$137)^6 -> 1025494.7 | I38: =I17*(Assumptions!$B$26*Assumptions!$B$27*Assumptions!$B$23+Assumptions!$B$27*Assumptions!$B$24)*(1+Assumptions!$B$25)*12*(1+Assumptions!$B$137)^7 -> 1167525.7 | J38: =J17*(Assumptions!$B$26*Assumptions!$B$27*Assumptions!$B$23+Assumptions!$B$27*Assumptions!$B$24)*(1+Assumptions!$B$25)*12*(1+Assumptions!$B$137)^8 -> 1318242.7 | K38: =K17*(Assumptions!$B$26*Assumptions!$B$27*Assumptions!$B$23+Assumptions!$B$27*Assumptions!$B$24)*(1+Assumptions!$B$25)*12*(1+Assumptions!$B$137)^9 -> 1478079.6 | L38: =L17*(Assumptions!$B$26*Assumptions!$B$27*Assumptions!$B$23+Assumptions!$B$27*Assumptions!$B$24)*(1+Assumptions!$B$25)*12*(1+Assumptions!$B$137)^10 -> 1647490.3 | M38: =M17*(Assumptions!$B$26*Assumptions!$B$27*Assumptions!$B$23+Assumptions!$B$27*Assumptions!$B$24)*(1+Assumptions!$B$25)*12*(1+Assumptions!$B$137)^11 -> 1826949 | N38: =N17*(Assumptions!$B$26*Assumptions!$B$27*Assumptions!$B$23+Assumptions!$B$27*Assumptions!$B$24)*(1+Assumptions!$B$25)*12*(1+Assumptions!$B$137)^12 -> 2016951.7 | O38: =O17*(Assumptions!$B$26*Assumptions!$B$27*Assumptions!$B$23+Assumptions!$B$27*Assumptions!$B$24)*(1+Assumptions!$B$25)*12*(1+Assumptions!$B$137)^13 -> 2087545 | P38: =P17*(Assumptions!$B$26*Assumptions!$B$27*Assumptions!$B$23+Assumptions!$B$27*Assumptions!$B$24)*(1+Assumptions!$B$25)*12*(1+Assumptions!$B$137)^14 -> 2160609.1 | R38: Wages rise at their own rate, not at the price rate. Louisiana construction wages have grown about half as fast as the national average, which is the only reason the margin holds up here.
A39: Aggregate and stone | B39: =B20*(Assumptions!$B$5*Assumptions!$B$22)*(1-Assumptions!$B$135)*Assumptions!$B$134 -> 95356.8 | C39: =C20*(Assumptions!$B$5*Assumptions!$B$22)*(1-Assumptions!$B$135)*Assumptions!$B$134*(1+Assumptions!$B$132)^1 -> 100363.03 | D39: =D20*(Assumptions!$B$5*Assumptions!$B$22)*(1-Assumptions!$B$135)*Assumptions!$B$134*(1+Assumptions!$B$132)^2 -> 132040.11 | E39: =E20*(Assumptions!$B$5*Assumptions!$B$22)*(1-Assumptions!$B$135)*Assumptions!$B$134*(1+Assumptions!$B$132)^3 -> 194561.11 | F39: =F20*(Assumptions!$B$5*Assumptions!$B$22)*(1-Assumptions!$B$135)*Assumptions!$B$134*(1+Assumptions!$B$132)^4 -> 234029.22 | G39: =G20*(Assumptions!$B$5*Assumptions!$B$22)*(1-Assumptions!$B$135)*Assumptions!$B$134*(1+Assumptions!$B$132)^5 -> 277105.22 | H39: =H20*(Assumptions!$B$5*Assumptions!$B$22)*(1-Assumptions!$B$135)*Assumptions!$B$134*(1+Assumptions!$B$132)^6 -> 324059.16 | I39: =I20*(Assumptions!$B$5*Assumptions!$B$22)*(1-Assumptions!$B$135)*Assumptions!$B$134*(1+Assumptions!$B$132)^7 -> 375179.49 | J39: =J20*(Assumptions!$B$5*Assumptions!$B$22)*(1-Assumptions!$B$135)*Assumptions!$B$134*(1+Assumptions!$B$132)^8 -> 430774.27 | K39: =K20*(Assumptions!$B$5*Assumptions!$B$22)*(1-Assumptions!$B$135)*Assumptions!$B$134*(1+Assumptions!$B$132)^9 -> 491172.42 | L39: =L20*(Assumptions!$B$5*Assumptions!$B$22)*(1-Assumptions!$B$135)*Assumptions!$B$134*(1+Assumptions!$B$132)^10 -> 556725.04 | M39: =M20*(Assumptions!$B$5*Assumptions!$B$22)*(1-Assumptions!$B$135)*Assumptions!$B$134*(1+Assumptions!$B$132)^11 -> 627806.9 | N39: =N20*(Assumptions!$B$5*Assumptions!$B$22)*(1-Assumptions!$B$135)*Assumptions!$B$134*(1+Assumptions!$B$132)^12 -> 704817.88 | O39: =O20*(Assumptions!$B$5*Assumptions!$B$22)*(1-Assumptions!$B$135)*Assumptions!$B$134*(1+Assumptions!$B$132)^13 -> 741820.82 | P39: =P20*(Assumptions!$B$5*Assumptions!$B$22)*(1-Assumptions!$B$135)*Assumptions!$B$134*(1+Assumptions!$B$132)^14 -> 780766.41 | R39: The heaviest material and the fastest-rising. Priced per linear foot installed, not as a share of revenue - that is what lets it outrun the price.
A40: Pipe, fabric and catch basins | B40: =B20*(Assumptions!$B$5*Assumptions!$B$22)*(1-Assumptions!$B$135)*(1-Assumptions!$B$134) -> 78019.2 | C40: =C20*(Assumptions!$B$5*Assumptions!$B$22)*(1-Assumptions!$B$135)*(1-Assumptions!$B$134)*(1+Assumptions!$B$133)^1 -> 79969.68 | D40: =D20*(Assumptions!$B$5*Assumptions!$B$22)*(1-Assumptions!$B$135)*(1-Assumptions!$B$134)*(1+Assumptions!$B$133)^2 -> 102461.15 | E40: =E20*(Assumptions!$B$5*Assumptions!$B$22)*(1-Assumptions!$B$135)*(1-Assumptions!$B$134)*(1+Assumptions!$B$133)^3 -> 147031.75 | F40: =F20*(Assumptions!$B$5*Assumptions!$B$22)*(1-Assumptions!$B$135)*(1-Assumptions!$B$134)*(1+Assumptions!$B$133)^4 -> 172237.2 | G40: =G20*(Assumptions!$B$5*Assumptions!$B$22)*(1-Assumptions!$B$135)*(1-Assumptions!$B$134)*(1+Assumptions!$B$133)^5 -> 198611.02 | H40: =H20*(Assumptions!$B$5*Assumptions!$B$22)*(1-Assumptions!$B$135)*(1-Assumptions!$B$134)*(1+Assumptions!$B$133)^6 -> 226195.88 | I40: =I20*(Assumptions!$B$5*Assumptions!$B$22)*(1-Assumptions!$B$135)*(1-Assumptions!$B$134)*(1+Assumptions!$B$133)^7 -> 255035.86 | J40: =J20*(Assumptions!$B$5*Assumptions!$B$22)*(1-Assumptions!$B$135)*(1-Assumptions!$B$134)*(1+Assumptions!$B$133)^8 -> 285176.46 | K40: =K20*(Assumptions!$B$5*Assumptions!$B$22)*(1-Assumptions!$B$135)*(1-Assumptions!$B$134)*(1+Assumptions!$B$133)^9 -> 316664.69 | L40: =L20*(Assumptions!$B$5*Assumptions!$B$22)*(1-Assumptions!$B$135)*(1-Assumptions!$B$134)*(1+Assumptions!$B$133)^10 -> 349549.1 | M40: =M20*(Assumptions!$B$5*Assumptions!$B$22)*(1-Assumptions!$B$135)*(1-Assumptions!$B$134)*(1+Assumptions!$B$133)^11 -> 383879.82 | N40: =N20*(Assumptions!$B$5*Assumptions!$B$22)*(1-Assumptions!$B$135)*(1-Assumptions!$B$134)*(1+Assumptions!$B$133)^12 -> 419708.6 | O40: =O20*(Assumptions!$B$5*Assumptions!$B$22)*(1-Assumptions!$B$135)*(1-Assumptions!$B$134)*(1+Assumptions!$B$133)^13 -> 430201.32 | P40: =P20*(Assumptions!$B$5*Assumptions!$B$22)*(1-Assumptions!$B$135)*(1-Assumptions!$B$134)*(1+Assumptions!$B$133)^14 -> 440956.35
A41: Diesel and gasoline | B41: =B20*(Assumptions!$B$5*Assumptions!$B$22)*Assumptions!$B$135 -> 43344 | C41: =C20*(Assumptions!$B$5*Assumptions!$B$22)*Assumptions!$B$135*(1+Assumptions!$B$136)^1 -> 44535.96 | D41: =D20*(Assumptions!$B$5*Assumptions!$B$22)*Assumptions!$B$135*(1+Assumptions!$B$136)^2 -> 57200.874 | E41: =E20*(Assumptions!$B$5*Assumptions!$B$22)*Assumptions!$B$135*(1+Assumptions!$B$136)^3 -> 82283.457 | F41: =F20*(Assumptions!$B$5*Assumptions!$B$22)*Assumptions!$B$135*(1+Assumptions!$B$136)^4 -> 96624.288 | G41: =G20*(Assumptions!$B$5*Assumptions!$B$22)*Assumptions!$B$135*(1+Assumptions!$B$136)^5 -> 111691.64 | H41: =H20*(Assumptions!$B$5*Assumptions!$B$22)*Assumptions!$B$135*(1+Assumptions!$B$136)^6 -> 127514.62 | I41: =I20*(Assumptions!$B$5*Assumptions!$B$22)*Assumptions!$B$135*(1+Assumptions!$B$136)^7 -> 144123.4 | J41: =J20*(Assumptions!$B$5*Assumptions!$B$22)*Assumptions!$B$135*(1+Assumptions!$B$136)^8 -> 161549.23 | K41: =K20*(Assumptions!$B$5*Assumptions!$B$22)*Assumptions!$B$135*(1+Assumptions!$B$136)^9 -> 179824.48 | L41: =L20*(Assumptions!$B$5*Assumptions!$B$22)*Assumptions!$B$135*(1+Assumptions!$B$136)^10 -> 198982.71 | M41: =M20*(Assumptions!$B$5*Assumptions!$B$22)*Assumptions!$B$135*(1+Assumptions!$B$136)^11 -> 219058.64 | N41: =N20*(Assumptions!$B$5*Assumptions!$B$22)*Assumptions!$B$135*(1+Assumptions!$B$136)^12 -> 240088.27 | O41: =O20*(Assumptions!$B$5*Assumptions!$B$22)*Assumptions!$B$135*(1+Assumptions!$B$136)^13 -> 246690.7 | P41: =P20*(Assumptions!$B$5*Assumptions!$B$22)*Assumptions!$B$135*(1+Assumptions!$B$136)^14 -> 253474.69 | R41: Held at general inflation deliberately. Fuel swings rather than trends - the sensitivity rows at the bottom show what a fuel shock does instead.
A42: Plan visit costs | B42: =B31*Assumptions!$B$33*Assumptions!$B$37 -> 6826.68 | C42: =C31*Assumptions!$B$33*Assumptions!$B$37*(1+Assumptions!$B$137)^1 -> 13565.978 | D42: =D31*Assumptions!$B$33*Assumptions!$B$37*(1+Assumptions!$B$137)^2 -> 22058.663 | E42: =E31*Assumptions!$B$33*Assumptions!$B$37*(1+Assumptions!$B$137)^3 -> 34249.767 | F42: =F31*Assumptions!$B$33*Assumptions!$B$37*(1+Assumptions!$B$137)^4 -> 48280.173 | G42: =G31*Assumptions!$B$33*Assumptions!$B$37*(1+Assumptions!$B$137)^5 -> 64215.278 | H42: =H31*Assumptions!$B$33*Assumptions!$B$37*(1+Assumptions!$B$137)^6 -> 82125.12 | I42: =I31*Assumptions!$B$33*Assumptions!$B$37*(1+Assumptions!$B$137)^7 -> 102084.51 | J42: =J31*Assumptions!$B$33*Assumptions!$B$37*(1+Assumptions!$B$137)^8 -> 124173.17 | K42: =K31*Assumptions!$B$33*Assumptions!$B$37*(1+Assumptions!$B$137)^9 -> 148475.9 | L42: =L31*Assumptions!$B$33*Assumptions!$B$37*(1+Assumptions!$B$137)^10 -> 175082.73 | M42: =M31*Assumptions!$B$33*Assumptions!$B$37*(1+Assumptions!$B$137)^11 -> 204089.07 | N42: =N31*Assumptions!$B$33*Assumptions!$B$37*(1+Assumptions!$B$137)^12 -> 235595.94 | O42: =O31*Assumptions!$B$33*Assumptions!$B$37*(1+Assumptions!$B$137)^13 -> 267040.96 | P42: =P31*Assumptions!$B$33*Assumptions!$B$37*(1+Assumptions!$B$137)^14 -> 298477.64 | R42: Mostly a technician's time, so it rises with wages.
A43: Materials, fuel and visits - total | B43: =B39+B40+B41+B42 -> 223546.68 | C43: =C39+C40+C41+C42 -> 238434.65 | D43: =D39+D40+D41+D42 -> 313760.8 | E43: =E39+E40+E41+E42 -> 458126.09 | F43: =F39+F40+F41+F42 -> 551170.88 | G43: =G39+G40+G41+G42 -> 651623.16 | H43: =H39+H40+H41+H42 -> 759894.78 | I43: =I39+I40+I41+I42 -> 876423.26 | ... P43: =P39+P40+P41+P42 -> 1773675.1
A44: The same, as a share of revenue - WATCH THIS LINE | B44: =B43/B36 -> 0.20177815 | C44: =C43/C36 -> 0.21096225 | D44: =D43/D36 -> 0.21335838 | E44: =E43/E36 -> 0.21524825 | F44: =F43/F36 -> 0.21770811 | G44: =G43/G36 -> 0.22010075 | H44: =H43/H36 -> 0.22245337 | I44: =I43/I36 -> 0.22478395 | ... P44: =P43/P36 -> 0.24202604 | R44: It starts at the 20% Charlie quotes and drifts UP if aggregate rises faster than the price per foot - which is exactly what the last three years of data show. This single line is the difference between modelling inflation honestly and hiding it inside a fixed percentage of revenue.
A45: GROSS PROFIT | B45: =B36-B38-B43 -> 550640.56 | C45: =C36-C38-C43 -> 546414.02 | D45: =D36-D38-D43 -> 709990.64 | E45: =E36-E38-E43 -> 1022779.2 | F45: =F36-F38-F43 -> 1214677.5 | G45: =G36-G38-G43 -> 1417209.9 | H45: =H36-H38-H43 -> 1630583.8 | I45: =I36-I38-I43 -> 1855009.4 | ... P45: =P36-P38-P43 -> 3394163.1
A46: Gross margin | B46: =B45/B36 -> 0.49702028 | C46: =C45/C36 -> 0.48345627 | D46: =D45/D36 -> 0.48279597 | E46: =E45/E36 -> 0.48054769 | F46: =F45/F36 -> 0.47978794 | G46: =G45/G36 -> 0.47869534 | H46: =H45/H36 -> 0.47734091 | I46: =I45/I36 -> 0.47577051 | ... P46: =P45/P36 -> 0.46314901 | R46: Charlie's 50% rule, tested year by year against costs that each rise at their own rate.
A47: Salaried staff (admin, managers, estimators) | B47: =(B23*Assumptions!$B$55+B24*Assumptions!$B$56+B25*Assumptions!$B$57) -> 48000 | C47: =(C23*Assumptions!$B$55+C24*Assumptions!$B$56+C25*Assumptions!$B$57)*(1+Assumptions!$B$137)^1 -> 49680 | D47: =(D23*Assumptions!$B$55+D24*Assumptions!$B$56+D25*Assumptions!$B$57)*(1+Assumptions!$B$137)^2 -> 102837.6 | E47: =(E23*Assumptions!$B$55+E24*Assumptions!$B$56+E25*Assumptions!$B$57)*(1+Assumptions!$B$137)^3 -> 186264.6 | F47: =(F23*Assumptions!$B$55+F24*Assumptions!$B$56+F25*Assumptions!$B$57)*(1+Assumptions!$B$137)^4 -> 325896.53 | G47: =(G23*Assumptions!$B$55+G24*Assumptions!$B$56+G25*Assumptions!$B$57)*(1+Assumptions!$B$137)^5 -> 422816.32 | H47: =(H23*Assumptions!$B$55+H24*Assumptions!$B$56+H25*Assumptions!$B$57)*(1+Assumptions!$B$137)^6 -> 437614.9 | I47: =(I23*Assumptions!$B$55+I24*Assumptions!$B$56+I25*Assumptions!$B$57)*(1+Assumptions!$B$137)^7 -> 452931.42 | J47: =(J23*Assumptions!$B$55+J24*Assumptions!$B$56+J25*Assumptions!$B$57)*(1+Assumptions!$B$137)^8 -> 531990.85 | K47: =(K23*Assumptions!$B$55+K24*Assumptions!$B$56+K25*Assumptions!$B$57)*(1+Assumptions!$B$137)^9 -> 550610.53 | L47: =(L23*Assumptions!$B$55+L24*Assumptions!$B$56+L25*Assumptions!$B$57)*(1+Assumptions!$B$137)^10 -> 569881.9 | M47: =(M23*Assumptions!$B$55+M24*Assumptions!$B$56+M25*Assumptions!$B$57)*(1+Assumptions!$B$137)^11 -> 589827.77 | N47: =(N23*Assumptions!$B$55+N24*Assumptions!$B$56+N25*Assumptions!$B$57)*(1+Assumptions!$B$137)^12 -> 610471.74 | O47: =(O23*Assumptions!$B$55+O24*Assumptions!$B$56+O25*Assumptions!$B$57)*(1+Assumptions!$B$137)^13 -> 631838.25 | P47: =(P23*Assumptions!$B$55+P24*Assumptions!$B$56+P25*Assumptions!$B$57)*(1+Assumptions!$B$137)^14 -> 653952.59 | R47: Salaries rise with the wage escalator, same as the crews. The step changes are the hiring thresholds on Assumptions - you cannot hire two thirds of an estimator.
A48: Owner draw | B48: =Assumptions!$B$78*12 -> 150000 | C48: =Assumptions!$B$78*12*(1+Assumptions!$B$142)^1 -> 150000 | D48: =Assumptions!$B$78*12*(1+Assumptions!$B$142)^2 -> 150000 | E48: =Assumptions!$B$78*12*(1+Assumptions!$B$142)^3 -> 150000 | F48: =Assumptions!$B$78*12*(1+Assumptions!$B$142)^4 -> 150000 | G48: =Assumptions!$B$78*12*(1+Assumptions!$B$142)^5 -> 150000 | H48: =Assumptions!$B$78*12*(1+Assumptions!$B$142)^6 -> 150000 | I48: =Assumptions!$B$78*12*(1+Assumptions!$B$142)^7 -> 150000 | J48: =Assumptions!$B$78*12*(1+Assumptions!$B$142)^8 -> 150000 | K48: =Assumptions!$B$78*12*(1+Assumptions!$B$142)^9 -> 150000 | L48: =Assumptions!$B$78*12*(1+Assumptions!$B$142)^10 -> 150000 | M48: =Assumptions!$B$78*12*(1+Assumptions!$B$142)^11 -> 150000 | N48: =Assumptions!$B$78*12*(1+Assumptions!$B$142)^12 -> 150000 | O48: =Assumptions!$B$78*12*(1+Assumptions!$B$142)^13 -> 150000 | P48: =Assumptions!$B$78*12*(1+Assumptions!$B$142)^14 -> 150000 | R48: Held flat unless the draw escalator on Assumptions is raised. A draw held flat nominal loses about a quarter of its purchasing power over ten years at 2.75% inflation.
A49: All other overhead (per crew, marketing, yard, office, loans) | B49: =(Assumptions!$B$80+Assumptions!$B$81+Assumptions!$B$82+Assumptions!$B$83)*12+B17*22000+B36*0.05+Assumptions!$B$84*Assumptions!$B$85*12+'Equipment plan'!$H$10*12*MAX(0,B17-1) -> 188494.48 | C49: =(Assumptions!$B$80+Assumptions!$B$81+Assumptions!$B$82+Assumptions!$B$83)*12*(1+Assumptions!$B$141)^1+C17*22000*(1+((Assumptions!$B$138+Assumptions!$B$141)/2))^1+C36*0.05+Assumptions!$B$84*Assumptions!$B$85*12*MIN(3,C17/2)*(1+Assumptions!$B$141)^1+'Equipment plan'!$H$10*12*MAX(0,C17-1) -> 193007.77 | D49: =(Assumptions!$B$80+Assumptions!$B$81+Assumptions!$B$82+Assumptions!$B$83)*12*(1+Assumptions!$B$141)^2+D17*22000*(1+((Assumptions!$B$138+Assumptions!$B$141)/2))^2+D36*0.05+Assumptions!$B$84*Assumptions!$B$85*12*MIN(3,D17/2)*(1+Assumptions!$B$141)^2+'Equipment plan'!$H$10*12*MAX(0,D17-1) -> 245934.06 | E49: =(Assumptions!$B$80+Assumptions!$B$81+Assumptions!$B$82+Assumptions!$B$83)*12*(1+Assumptions!$B$141)^3+E17*22000*(1+((Assumptions!$B$138+Assumptions!$B$141)/2))^3+E36*0.05+Assumptions!$B$84*Assumptions!$B$85*12*MIN(3,E17/2)*(1+Assumptions!$B$141)^3+'Equipment plan'!$H$10*12*MAX(0,E17-1) -> 349182.6 | F49: =(Assumptions!$B$80+Assumptions!$B$81+Assumptions!$B$82+Assumptions!$B$83)*12*(1+Assumptions!$B$141)^4+F17*22000*(1+((Assumptions!$B$138+Assumptions!$B$141)/2))^4+F36*0.05+Assumptions!$B$84*Assumptions!$B$85*12*MIN(3,F17/2)*(1+Assumptions!$B$141)^4+'Equipment plan'!$H$10*12*MAX(0,F17-1) -> 408811.31 | G49: =(Assumptions!$B$80+Assumptions!$B$81+Assumptions!$B$82+Assumptions!$B$83)*12*(1+Assumptions!$B$141)^5+G17*22000*(1+((Assumptions!$B$138+Assumptions!$B$141)/2))^5+G36*0.05+Assumptions!$B$84*Assumptions!$B$85*12*MIN(3,G17/2)*(1+Assumptions!$B$141)^5+'Equipment plan'!$H$10*12*MAX(0,G17-1) -> 471295.89 | H49: =(Assumptions!$B$80+Assumptions!$B$81+Assumptions!$B$82+Assumptions!$B$83)*12*(1+Assumptions!$B$141)^6+H17*22000*(1+((Assumptions!$B$138+Assumptions!$B$141)/2))^6+H36*0.05+Assumptions!$B$84*Assumptions!$B$85*12*MIN(3,H17/2)*(1+Assumptions!$B$141)^6+'Equipment plan'!$H$10*12*MAX(0,H17-1) -> 536766.91 | I49: =(Assumptions!$B$80+Assumptions!$B$81+Assumptions!$B$82+Assumptions!$B$83)*12*(1+Assumptions!$B$141)^7+I17*22000*(1+((Assumptions!$B$138+Assumptions!$B$141)/2))^7+I36*0.05+Assumptions!$B$84*Assumptions!$B$85*12*MIN(3,I17/2)*(1+Assumptions!$B$141)^7+'Equipment plan'!$H$10*12*MAX(0,I17-1) -> 605361.09 | J49: =(Assumptions!$B$80+Assumptions!$B$81+Assumptions!$B$82+Assumptions!$B$83)*12*(1+Assumptions!$B$141)^8+J17*22000*(1+((Assumptions!$B$138+Assumptions!$B$141)/2))^8+J36*0.05+Assumptions!$B$84*Assumptions!$B$85*12*MIN(3,J17/2)*(1+Assumptions!$B$141)^8+'Equipment plan'!$H$10*12*MAX(0,J17-1) -> 677221.47 | K49: =(Assumptions!$B$80+Assumptions!$B$81+Assumptions!$B$82+Assumptions!$B$83)*12*(1+Assumptions!$B$141)^9+K17*22000*(1+((Assumptions!$B$138+Assumptions!$B$141)/2))^9+K36*0.05+Assumptions!$B$84*Assumptions!$B$85*12*MIN(3,K17/2)*(1+Assumptions!$B$141)^9+'Equipment plan'!$H$10*12*MAX(0,K17-1) -> 744359.73 | L49: =(Assumptions!$B$80+Assumptions!$B$81+Assumptions!$B$82+Assumptions!$B$83)*12*(1+Assumptions!$B$141)^10+L17*22000*(1+((Assumptions!$B$138+Assumptions!$B$141)/2))^10+L36*0.05+Assumptions!$B$84*Assumptions!$B$85*12*MIN(3,L17/2)*(1+Assumptions!$B$141)^10+'Equipment plan'!$H$10*12*MAX(0,L17-1) -> 814622.81 | M49: =(Assumptions!$B$80+Assumptions!$B$81+Assumptions!$B$82+Assumptions!$B$83)*12*(1+Assumptions!$B$141)^11+M17*22000*(1+((Assumptions!$B$138+Assumptions!$B$141)/2))^11+M36*0.05+Assumptions!$B$84*Assumptions!$B$85*12*MIN(3,M17/2)*(1+Assumptions!$B$141)^11+'Equipment plan'!$H$10*12*MAX(0,M17-1) -> 888155.91 | N49: =(Assumptions!$B$80+Assumptions!$B$81+Assumptions!$B$82+Assumptions!$B$83)*12*(1+Assumptions!$B$141)^12+N17*22000*(1+((Assumptions!$B$138+Assumptions!$B$141)/2))^12+N36*0.05+Assumptions!$B$84*Assumptions!$B$85*12*MIN(3,N17/2)*(1+Assumptions!$B$141)^12+'Equipment plan'!$H$10*12*MAX(0,N17-1) -> 965111.03 | O49: =(Assumptions!$B$80+Assumptions!$B$81+Assumptions!$B$82+Assumptions!$B$83)*12*(1+Assumptions!$B$141)^13+O17*22000*(1+((Assumptions!$B$138+Assumptions!$B$141)/2))^13+O36*0.05+Assumptions!$B$84*Assumptions!$B$85*12*MIN(3,O17/2)*(1+Assumptions!$B$141)^13+'Equipment plan'!$H$10*12*MAX(0,O17-1) -> 994070.62 | P49: =(Assumptions!$B$80+Assumptions!$B$81+Assumptions!$B$82+Assumptions!$B$83)*12*(1+Assumptions!$B$141)^14+P17*22000*(1+((Assumptions!$B$138+Assumptions!$B$141)/2))^14+P36*0.05+Assumptions!$B$84*Assumptions!$B$85*12*MIN(3,P17/2)*(1+Assumptions!$B$141)^14+'Equipment plan'!$H$10*12*MAX(0,P17-1) -> 1023785.4 | R49: Office overhead and yard rent rise at the general overhead rate. The per-crew figure rises at the midpoint of the insurance and overhead rates, because what sits inside it - truck insurance, repairs, tools - is led by commercial auto, the one line still hardening after 59 straight quarters of increases. Marketing stays 5% of revenue, so it rises with the business. Equipment loan payments are fixed and do not escalate.
A50: AI tools - voice agent, assisted quoting, AI seats | B50: =(Assumptions!$B$182+Assumptions!$B$183*B17)*12*(1+Assumptions!$B$184)^0 -> 4800 | C50: =(Assumptions!$B$182+Assumptions!$B$183*C17)*12*(1+Assumptions!$B$184)^1 -> 5040 | D50: =(Assumptions!$B$182+Assumptions!$B$183*D17)*12*(1+Assumptions!$B$184)^2 -> 5788.125 | E50: =(Assumptions!$B$182+Assumptions!$B$183*E17)*12*(1+Assumptions!$B$184)^3 -> 7119.3938 | F50: =(Assumptions!$B$182+Assumptions!$B$183*F17)*12*(1+Assumptions!$B$184)^4 -> 8022.3413 | G50: =(Assumptions!$B$182+Assumptions!$B$183*G17)*12*(1+Assumptions!$B$184)^5 -> 8997.785 | H50: =(Assumptions!$B$182+Assumptions!$B$183*H17)*12*(1+Assumptions!$B$184)^6 -> 10050.717 | I50: =(Assumptions!$B$182+Assumptions!$B$183*I17)*12*(1+Assumptions!$B$184)^7 -> 11186.448 | J50: =(Assumptions!$B$182+Assumptions!$B$183*J17)*12*(1+Assumptions!$B$184)^8 -> 12410.626 | K50: =(Assumptions!$B$182+Assumptions!$B$183*K17)*12*(1+Assumptions!$B$184)^9 -> 13729.255 | L50: =(Assumptions!$B$182+Assumptions!$B$183*L17)*12*(1+Assumptions!$B$184)^10 -> 15148.72 | M50: =(Assumptions!$B$182+Assumptions!$B$183*M17)*12*(1+Assumptions!$B$184)^11 -> 16675.809 | N50: =(Assumptions!$B$182+Assumptions!$B$183*N17)*12*(1+Assumptions!$B$184)^12 -> 18317.735 | O50: =(Assumptions!$B$182+Assumptions!$B$183*O17)*12*(1+Assumptions!$B$184)^13 -> 19233.621 | P50: =(Assumptions!$B$182+Assumptions!$B$183*P17)*12*(1+Assumptions!$B$184)^14 -> 20195.302 | R50: A real, growing cost - not a free lunch. This category is not deflating: one vendor raised list price 29-41% between mid-2024 and 2026, so it escalates faster than general inflation here on purpose. The saving it buys is on the AI and robotics tab.
A51: OPERATING PROFIT (after the owner draw, before tax) | B51: =B45-B47-B49-B48-B50 -> 159346.07 | C51: =C45-C47-C49-C48-C50 -> 148686.24 | D51: =D45-D47-D49-D48-D50 -> 205430.85 | E51: =E45-E47-E49-E48-E50 -> 330212.62 | F51: =F45-F47-F49-F48-F50 -> 321947.32 | G51: =G45-G47-G49-G48-G50 -> 364099.93 | H51: =H45-H47-H49-H48-H50 -> 496151.3 | I51: =I45-I47-I49-I48-I50 -> 635530.44 | ... P51: =P45-P47-P49-P48-P50 -> 1546229.8 | R51: This is BEFORE anything paid to Ned or a COO - their tabs take their share out of this line. It is AFTER the AI tool stack, so the tooling is paid for before anybody's share is calculated.
A52: WHAT THE COMPANY IS WORTH
A53: Equipment bought this year | B53: =MAX(0,B17-1)*'Equipment plan'!$B$10 -> 138500 | C53: =MAX(0,C17-B17)*'Equipment plan'!$B$10 -> 0 | D53: =MAX(0,D17-C17)*'Equipment plan'!$B$10 -> 69250 | E53: =MAX(0,E17-D17)*'Equipment plan'!$B$10 -> 138500 | F53: =MAX(0,F17-E17)*'Equipment plan'!$B$10 -> 69250 | G53: =MAX(0,G17-F17)*'Equipment plan'!$B$10 -> 69250 | H53: =MAX(0,H17-G17)*'Equipment plan'!$B$10 -> 69250 | I53: =MAX(0,I17-H17)*'Equipment plan'!$B$10 -> 69250 | J53: =MAX(0,J17-I17)*'Equipment plan'!$B$10 -> 69250 | ... P53: =MAX(0,P17-O17)*'Equipment plan'!$B$10 -> 0
A54: Equipment owned, at cost (cumulative) | B54: =Assumptions!$B$45+B53 -> 198500 | C54: =B54+C53 -> 198500 | D54: =C54+D53 -> 267750 | E54: =D54+E53 -> 406250 | F54: =E54+F53 -> 475500 | G54: =F54+G53 -> 544750 | H54: =G54+H53 -> 614000 | I54: =H54+I53 -> 683250 | J54: =I54+J53 -> 752500 | ... P54: =O54+P53 -> 1029500
A55: Equipment at book value (written off over the life on Assumptions) | B55: =B54*(1-1/Assumptions!$B$46) -> 170142.86 | C55: =MAX(C54*0.25,B55*(1-1/Assumptions!$B$46)+C53*(1-1/Assumptions!$B$46)) -> 145836.73 | D55: =MAX(D54*0.25,C55*(1-1/Assumptions!$B$46)+D53*(1-1/Assumptions!$B$46)) -> 184360.06 | E55: =MAX(E54*0.25,D55*(1-1/Assumptions!$B$46)+E53*(1-1/Assumptions!$B$46)) -> 276737.19 | F55: =MAX(F54*0.25,E55*(1-1/Assumptions!$B$46)+F53*(1-1/Assumptions!$B$46)) -> 296560.45 | G55: =MAX(G54*0.25,F55*(1-1/Assumptions!$B$46)+G53*(1-1/Assumptions!$B$46)) -> 313551.82 | H55: =MAX(H54*0.25,G55*(1-1/Assumptions!$B$46)+H53*(1-1/Assumptions!$B$46)) -> 328115.84 | I55: =MAX(I54*0.25,H55*(1-1/Assumptions!$B$46)+I53*(1-1/Assumptions!$B$46)) -> 340599.29 | J55: =MAX(J54*0.25,I55*(1-1/Assumptions!$B$46)+J53*(1-1/Assumptions!$B$46)) -> 351299.39 | ... P55: =MAX(P54*0.25,O55*(1-1/Assumptions!$B$46)+P53*(1-1/Assumptions!$B$46)) -> 279805.31 | R55: Floored at a quarter of cost - machines that are maintained keep a resale value.
A56: Equipment debt still owed | B56: =MAX(0,B53*0.8*0.85) -> 94180 | C56: =MAX(0,B56*0.75+C53*0.8*0.85) -> 70635 | D56: =MAX(0,C56*0.75+D53*0.8*0.85) -> 100066.25 | E56: =MAX(0,D56*0.75+E53*0.8*0.85) -> 169229.69 | F56: =MAX(0,E56*0.75+F53*0.8*0.85) -> 174012.27 | G56: =MAX(0,F56*0.75+G53*0.8*0.85) -> 177599.2 | H56: =MAX(0,G56*0.75+H53*0.8*0.85) -> 180289.4 | I56: =MAX(0,H56*0.75+I53*0.8*0.85) -> 182307.05 | J56: =MAX(0,I56*0.75+J53*0.8*0.85) -> 183820.29 | ... P56: =MAX(0,O56*0.75+P53*0.8*0.85) -> 105144.53 | R56: Roughly: 80% of each purchase financed over five years, paid down about a quarter a year.
A57: Taken out of the company (income tax and distributions) | B57: =MAX(0,B51)*Assumptions!$B$44 -> 95607.644 | C57: =MAX(0,C51)*Assumptions!$B$44 -> 89211.745 | D57: =MAX(0,D51)*Assumptions!$B$44 -> 123258.51 | E57: =MAX(0,E51)*Assumptions!$B$44 -> 198127.57 | F57: =MAX(0,F51)*Assumptions!$B$44 -> 193168.39 | G57: =MAX(0,G51)*Assumptions!$B$44 -> 218459.96 | H57: =MAX(0,H51)*Assumptions!$B$44 -> 297690.78 | I57: =MAX(0,I51)*Assumptions!$B$44 -> 381318.27 | ... P57: =MAX(0,P51)*Assumptions!$B$44 -> 927737.89 | R57: On top of the owner draw, which is already in the overhead above. Change the percentage on the Assumptions tab.
A58: Taken out, running total | B58: =B57 -> 95607.644 | C58: =B58+C57 -> 184819.39 | D58: =C58+D57 -> 308077.9 | E58: =D58+E57 -> 506205.47 | F58: =E58+F57 -> 699373.86 | G58: =F58+G57 -> 917833.82 | H58: =G58+H57 -> 1215524.6 | I58: =H58+I57 -> 1596842.9 | J58: =I58+J57 -> 2028288.4 | ... P58: =O58+P57 -> 6575750.4 | R58: What the owner has actually put in his pocket beyond the draw, by the end of each year.
A59: Cash on hand at year end | B59: =Assumptions!$B$62+B51-B57-B53*0.2 -> 61038.429 | C59: =B59+C51-C57-C53*0.2 -> 120512.93 | D59: =C59+D51-D57-D53*0.2 -> 188835.27 | E59: =D59+E51-E57-E53*0.2 -> 293220.32 | F59: =E59+F51-F57-F53*0.2 -> 408149.24 | G59: =F59+G51-G57-G53*0.2 -> 539939.21 | H59: =G59+H51-H57-H53*0.2 -> 724549.73 | I59: =H59+I51-I57-I53*0.2 -> 964911.91 | J59: =I59+J51-J57-J53*0.2 -> 1238692.3 | ... P59: =O59+P51-P57-P53*0.2 -> 4214933.6 | R59: What is left in the company after tax, distributions and the 20% down payment on new equipment.
A60: Owner cash from the business (profit + owner draw) | B60: =B51+Assumptions!$B$78*12 -> 309346.07 | C60: =C51+Assumptions!$B$78*12 -> 298686.24 | D60: =D51+Assumptions!$B$78*12 -> 355430.85 | E60: =E51+Assumptions!$B$78*12 -> 480212.62 | F60: =F51+Assumptions!$B$78*12 -> 471947.32 | G60: =G51+Assumptions!$B$78*12 -> 514099.93 | H60: =H51+Assumptions!$B$78*12 -> 646151.3 | I60: =I51+Assumptions!$B$78*12 -> 785530.44 | ... P60: =P51+Assumptions!$B$78*12 -> 1696229.8
A61: The same, if the plan book had never been started | B61: =B60-B35+B31*Assumptions!$B$33*Assumptions!$B$37 -> 291889.28 | C61: =C60-C35+C31*Assumptions!$B$33*Assumptions!$B$37 -> 265169.19 | D61: =D60-D35+D31*Assumptions!$B$33*Assumptions!$B$37 -> 300576.71 | E61: =E60-E35+E31*Assumptions!$B$33*Assumptions!$B$37 -> 394527.09 | F61: =F60-F35+F31*Assumptions!$B$33*Assumptions!$B$37 -> 350482.05 | G61: =G60-G35+G31*Assumptions!$B$33*Assumptions!$B$37 -> 351702.9 | H61: =H60-H35+H31*Assumptions!$B$33*Assumptions!$B$37 -> 437460.3 | I61: =I60-I35+I31*Assumptions!$B$33*Assumptions!$B$37 -> 524966.01 | ... P61: =P60-P35+P31*Assumptions!$B$33*Assumptions!$B$37 -> 917389.12 | R61: Plan revenue taken out along with what the visits cost to deliver. Everything else - crews, installs, overhead - is unchanged.
A62: VALUE WITH the service book (owner cash x multiple, plus cash, less debt) | B62: =MAX(0,B60)*Assumptions!$B$47+B59-B56 -> 740223.61 | C62: =MAX(0,C60)*Assumptions!$B$47+C59-C56 -> 796593.53 | D62: =MAX(0,D60)*Assumptions!$B$47+D59-D56 -> 977346.15 | E62: =MAX(0,E60)*Assumptions!$B$47+E59-E56 -> 1324522.2 | F62: =MAX(0,F60)*Assumptions!$B$47+F59-F56 -> 1414005.3 | G62: =MAX(0,G60)*Assumptions!$B$47+G59-G56 -> 1647589.8 | H62: =MAX(0,H60)*Assumptions!$B$47+H59-H56 -> 2159638.6 | I62: =MAX(0,I60)*Assumptions!$B$47+I59-I56 -> 2746431 | ... P62: =MAX(0,P60)*Assumptions!$B$47+P59-P56 -> 8350363.6 | R62: The multiple covers the business and the equipment it runs on; cash is added and equipment debt subtracted.
A63: VALUE WITHOUT the service book | B63: =MAX(0,B61)*Assumptions!$B$48+B59-B56 -> 579825.91 | C63: =MAX(0,C61)*Assumptions!$B$48+C59-C56 -> 606733.23 | D63: =MAX(0,D61)*Assumptions!$B$48+D59-D56 -> 719980.12 | E63: =MAX(0,E61)*Assumptions!$B$48+E59-E56 -> 952497.52 | F63: =MAX(0,F61)*Assumptions!$B$48+F59-F56 -> 970149.29 | G63: =MAX(0,G61)*Assumptions!$B$48+G59-G56 -> 1100916.1 | H63: =MAX(0,H61)*Assumptions!$B$48+H59-H56 -> 1462927 | I63: =MAX(0,I61)*Assumptions!$B$48+I59-I56 -> 1885033.5 | ... P63: =MAX(0,P61)*Assumptions!$B$48+P59-P56 -> 6036306.2
A64: What the service book is worth | B64: =B62-B63 -> 160397.7 | C64: =C62-C63 -> 189860.3 | D64: =D62-D63 -> 257366.04 | E64: =E62-E63 -> 372024.65 | F64: =F62-F63 -> 443855.98 | G64: =G62-G63 -> 546673.73 | H64: =H62-H63 -> 696711.62 | I64: =I62-I63 -> 861397.48 | ... P64: =P62-P63 -> 2314057.4 | R64: Two effects together: the profit the plans throw off, and the higher multiple a buyer pays for revenue that repeats.
A65: Cross-check: the plan book priced on its own (x annual plan revenue) | B65: =B35*Assumptions!$B$49 -> 24283.476 | C65: =C35*Assumptions!$B$49 -> 46624.274 | D65: =D35*Assumptions!$B$49 -> 75446.137 | E65: =E35*Assumptions!$B$49 -> 116576.85 | F65: =F35*Assumptions!$B$49 -> 163538.65 | G65: =G35*Assumptions!$B$49 -> 216464.57 | H65: =H35*Assumptions!$B$49 -> 275499.84 | I65: =I35*Assumptions!$B$49 -> 340801.93 | ... P65: =P35*Assumptions!$B$49 -> 963234.75

Sheet Funding options
A1: What the money costs - every source priced on the same loan
A2: Blue = change it. Each row borrows the same amount (the 'Outside capital raised' cell on Assumptions) and shows what it actually costs to pay back. Rates are the live September 2026 market, sourced on the Sources tab. The order is cheapest first, and the order is the recommendation.
A4: Amount being raised | B4: =Assumptions!$B$110 -> 150000 | D4: Change this on the Assumptions tab and every row below re-prices.
G5: Compare on THIS column, not total cost - a short loan looks cheap only because it is short.
A6: Where the money comes from | B6: Rate (APR) | C6: Term (yrs) | D6: Upfront fee | E6: Monthly payment | F6: Total paid back | G6: Cost of the money | H6: Cost per year borrowed | I6: What it is, and what they want from you
A7: Supplier net terms (SiteOne, Ferguson, aggregate) | B7: 0 | C7: 0.5 | D7: 0 | E7: =IF(B7=0,$B$4/(C7*12),PMT(B7/12,C7*12,-$B$4)) -> 25000 | F7: =E7*C7*12+$B$4*D7 -> 150000 | G7: =F7-$B$4 -> 0 | H7: =G7/C7 -> 0 | I7: Free money, and the first call. SiteOne bills Net 15th prox - every invoice in a month is due on the 15th of the next one, so roughly 30 days of float. At two crews, materials run $16,000-19,000 a month; thirty days of terms on that is $16,000-19,000 of permanent working capital at zero cost, and it takes a credit application, not a loan committee. Do this before drawing anything.
A8: Manufacturer 0% on the equipment (Bobcat, Kubota, Deere) | B8: 0 | C8: 4 | D8: 0 | E8: =IF(B8=0,$B$4/(C8*12),PMT(B8/12,C8*12,-$B$4)) -> 3125 | F8: =E8*C8*12+$B$4*D8 -> 150000 | G8: =F8-$B$4 -> 0 | H8: =G8/C8 -> 0 | I8: Bobcat is running 0% for 60 months on compact loaders and 0% for 48 on compact excavators, OR $8,000-10,000 cash in lieu - PROMO EXPIRES SEPT 30, 2026. It is not really 0%: giving up an $8,000 rebate on an $85,000 excavator to get the 0% is an implied 4.93% APR, and 5.78% on the loader. Still the cheapest equipment money available, but ask every dealer for BOTH numbers - the 0% term and the cash-in-lieu - and compare.
A9: Equipment loan, independent lender | B9: 0.085 | C9: 5 | D9: 0 | E9: =IF(B9=0,$B$4/(C9*12),PMT(B9/12,C9*12,-$B$4)) -> 3077.4797 | F9: =E9*C9*12+$B$4*D9 -> 184648.78 | G9: =F9-$B$4 -> 34648.782 | H9: =G9/C9 -> 6929.7564 | I9: 6-14% for a well-qualified borrower in 2026; 7.5-9.5% is the realistic band here given two-plus years operating, $60,000 of unencumbered iron and an engineer owner. The machine secures it, but a sole owner signs personally anyway. Application-only up to $150,000-$250,000 - no financial statements, just the app, 3-6 months of bank statements and the vendor quote. Approval in 24-48 hours. Do NOT let a dealer steer you into a fair-market-value lease to hit a payment target: it costs you the depreciation deduction and you own nothing at the end.
A10: Louisiana SSBCI loan guaranty, through a bank | B10: 0.095 | C10: 10 | D10: 0.01 | E10: =IF(B10=0,$B$4/(C10*12),PMT(B10/12,C10*12,-$B$4)) -> 1940.9634 | F10: =E10*C10*12+$B$4*D10 -> 234415.6 | G10: =F10-$B$4 -> 84415.604 | H10: =G10/C10 -> 8441.5604 | I10: THE LEAD. Louisiana's state guaranty covers up to 80% of a bank loan (or $1.5M), fee 0-2%, minimum 15% equity for an existing business, no application fee. The job test is one job under $100K and two jobs above - a second crew is three or four hires, so it is met on day one and it is the strongest paragraph in the package. Eligible for equipment AND working capital. You do not apply to the state; a Louisiana bank originates and files it. Because it takes most of the risk off the bank, it is the thing that makes a $150,000 ask worth a bank's time.
A11: SBA 7(a) Small Loan | B11: 0.1275 | C11: 10 | D11: 0.02 | E11: =IF(B11=0,$B$4/(C11*12),PMT(B11/12,C11*12,-$B$4)) -> 2217.5971 | F11: =E11*C11*12+$B$4*D11 -> 269111.66 | G11: =F11-$B$4 -> 119111.66 | H11: =G11/C11 -> 11911.166 | I11: Prime + 6.0% is the cap for $50,001-$250,000, so 12.75% at a 6.75% prime. 85% SBA-guaranteed at or below $150,000. No mandatory equity injection for an expansion. Coverage test is 1.1x on historical AND/OR projected cash flow - projections are allowed, which matters enormously here. Expect a blanket lien on every business asset, a personal guarantee, and a lien on the house if there is equity in it. 30-75 days. Note the perverse pricing: a $360,000 loan is priced 300bp cheaper than a $150,000 one.
